Workbook

Sheet RICE
A1: DEPARTMENT OF AGRICULTURE-REGIONAL FIELD OFFICE NO. 02
A2: CY 2025 & FY 2026 PROGRAM ACCOMPLISHMENTS/STATUS AND FY 2027 PLAN AND BUDGET PROPOSAL
A3: RICE PROGRAM
A4: PROVINCE: ISABELA
A5: DISTRICT: VI
A7: PROGRAM/SUBPROGRAM/ INDICATORS | B7: UNIT OF MEASURE | C7: CY 2025 GAA | E7: FY 2026 GAA | G7: FY 2027 PROPOSAL | M7: Remarks (Breakdown of Municipality Target for FY 2027 )
G8: TIER 1 | I8: TIER 2 | K8: TOTAL
C9: ANNUAL PHYSICAL TARGET | D9: ANNUAL BUDGET (₱ '000) | E9: ACCOMPLISHMENT | G9: PHYSICAL TARGET | H9: ANNUAL BUDGET (₱ '000) | I9: PHYSICAL TARGET | J9: ANNUAL BUDGET (₱ '000) | K9: PHYSICAL TARGET | L9: ANNUAL BUDGET (₱ '000)
E10: PHYSICAL TARGET | F10: ANNUAL BUDGET (₱ '000)
A11: I. TECHNICAL AND SUPPORT SERVICES PROGRAM (TSSP) | C11: =C12+C22 -> 0 | D11: =D12+D22 -> 140386.48 | F11: =F12+F22 -> 253198.79 | H11: =H12+H22 -> 268699.13 | J11: =J12+J22 -> 24078.76 | L11: =L12+L22 -> 381899.78
A12: 1. Production Support Services (PSS) | D12: =SUM(D13:D17) -> 140386.48 | F12: =SUM(F14:F17) -> 253198.79 | H12: =SUM(H14:H17) -> 268699.13 | J12: =SUM(J14:J17) -> 24078.76 | L12: =SUM(L15:L19) -> 381899.78
A13: Fertilizer Assistance - Ameliorants (solid) | B13: Kg | C13: 17769 | D13: =C13*0.92 -> 16347.48
A14: Fertilizer Assistance - Bio Fertilizer (pack) | B14: Kg | C14: 11479 | D14: 11479
A15: Fertilizer Assistance - inorganic - hybrid area | B15: hectare | C15: 13400 | D15: =C15*3.4 -> 45560 | E15: 26962.545 | F15: 91672.654 | G15: 28050 | H15: =56100677.32/1000 -> 56100.677 | I15: 2575.27 | J15: =5150536.84/1000 -> 5150.5368 | K15: =G15+I15 -> 30625.27 | L15: =H15+J15 -> 61251.214 | M15: CITY OF CAUAYAN ECHAGUE SAN GUILLERMO SAN ISIDRO
A16: Fertilizer Assistance - inorganic - inbred area | B16: hectare | E16: 7856.8864 | F16: 26713.414 | G16: 8123.04 | H16: =16246080.81/1000 -> 16246.081 | K16: =G16+I16 -> 8123.04 | L16: =H16+J16 -> 16246.081
A17: Seed assistance-Commercial Hybrid | B17: hectare | C17: 13400 | D17: =C17*5 -> 67000 | E17: 26962.545 | F17: 134812.73 | G17: 28050 | H17: =196352370.62/1000 -> 196352.37 | I17: 2575.27 | J17: =18928222.87/1000 -> 18928.223 | K17: =G17+I17 -> 30625.27 | L17: =H17+J17 -> 215280.59
A18: FDV/IMC for Inbred | I18: 8123.04 | J18: =18682992.94/1000 -> 18682.993 | K18: =G18+I18 -> 8123.04 | L18: =H18+J18 -> 18682.993
A19: FDV/IMC for Hybrid | I19: 30625.61 | J19: =70438896.28/1000 -> 70438.896 | K19: =G19+I19 -> 30625.61 | L19: =H19+J19 -> 70438.896
A20: Drone voucher | B20: hectare | K20: =G20+I20 -> 0 | L20: =H20+J20 -> 0
A21: Hermetic cocoon | B21: number | K21: =G21+I21 -> 0 | L21: =H21+J21 -> 0
A22: 2. Extension Support, Education and Training Services (ESETS) | F22: =SUM(F23:F24) -> 0 | K22: =G22+I22 -> 0 | L22: =H22+J22 -> 0
A23: Rice Farm Cluster Establishment | B23: site | G23: 1 | H23: 4800 | K23: =G23+I23 -> 1 | L23: =H23+J23 -> 4800
A24: Scale-up Palayamanan for Rice Based Farm | B24: site | G24: 13 | H24: 6500 | K24: =G24+I24 -> 13 | L24: =H24+J24 -> 6500
A25: II. AGRICULTURAL MACHINERY, EQUIPMENT, FACILITIES AND INFRASTRUCTURES PROGRAM (AMEFIP) | F25: =F26+F50 -> 0
A26: 1. AGRICULTURAL MACHINERY, EQUIPMENT, AND FACILITIES SUPPORT SERVICES (AMEFSS) | F26: =SUM(F28:F49) -> 0
A28: Vaccum Pack Sealer | B28: number
A29: Fork Lift | B29: number
A30: Seed Processing center | B30: number
A31: Rice Processing Center | B31: number
A32: Recirculating Dryer | B32: number
A33: Drying Pavement
A34: Paddy Rice HAuler | B34: number
A35: Packaging System | B35: number
A36: Hauling Truck | B36: distributed (no.)
A37: Combine Harvester | B37: number
A38: 4wd Tractor | B38: number
A39: Seeder | B39: distributed (no.)
A40: Upgrading RPC (Color Sorter with Control Tank) | B40: distributed (no.)
A41: A. Provision of Farm Production -Related Machinery and Equiment | B41: distributed (no.)
A42: Four-Wheel Drive Tractor with accessories | B42: distributed (no.)
A43: B. Construction Post Harvest Facilities
A44: Recirculating Dryer | B44: distributed (no.)
A45: Machinery Shed | B45: distributed (no.)
A46: Palayshed | B46: distributed (no.)
A47: Construction of Warehouse | B47: distributed (no.)
A48: MCDP with palay shed | B48: number
A49: Construction-Multi-Purpose Drying Pavement (MPDP) | B49: number
A50: III.2. IRRIGATION NETWORK SERVICES (INS)
A53: GRAND TOTAL | C53: =C26+C22+C12 -> 0 | D53: =D26+D22+D12 -> 140386.48 | F53: =F50+F26+F22+F12 -> 253198.79 | H53: =SUM(H15:H52) -> 279999.13 | I53: =SUM(I15:I52) -> 43899.19 | J53: =SUM(J15:J52) -> 113200.65 | K53: =SUM(K15:K52) -> 108136.23 | L53: =L50+L26+L22+L12 -> 381899.78
A54: Prepared by:
C55: In coordination with: | H55: Concurred by:
A57: BERNADETTE T. GALOSO
A58: Chief, PMED | C58: MACARIO B. ANDAL, CPA | H58: ROSE MARY G. AQUINO, Ph.D.
C59: Chief, Budget Section | H59: Regional Executive Director

Sheet CORN
A1: DEPARTMENT OF AGRICULTURE-REGIONAL FIELD OFFICE NO. 02
A2: CY 2025 & FY 2026 PROGRAM ACCOMPLISHMENTS/STATUS AND FY 2027 PLAN AND BUDGET PROPOSAL
A3: CORN PROGRAM
A4: PROVINCE: ISABELA
A5: DISTRICT: VI
A7: PROGRAM/SUBPROGRAM/ INDICATORS | B7: UNIT OF MEASURE | C7: CY 2025 GAA | E7: FY 2025 GAA | G7: FY 2026 GAA | I7: FY 2027 PROPOSAL | O7: Remarks (Breakdown of Municipality Target for FY 2027 )
I8: TIER 1 | K8: TIER 2 | M8: TOTAL
C9: ANNUAL PHYSICAL TARGET | D9: ANNUAL BUDGET (₱ '000) | E9: ACCOMPLISHMENT | G9: ACCOMPLISHMENT | I9: PHYSICAL TARGET | J9: ANNUAL BUDGET (₱ '000) | K9: PHYSICAL TARGET | L9: ANNUAL BUDGET (₱ '000) | M9: PHYSICAL TARGET | N9: ANNUAL BUDGET (₱ '000)
E10: PHYSICAL | F10: BUDGET (Actual Obligation) | G10: PHYSICAL TARGET | H10: ANNUAL BUDGET (₱ '000)
A11: I. PRODUCTION SUPPORT SERVICES | D11: =SUM(D12:D38) -> 68651.5 | F11: =SUM(F12:F41) -> 55877.839 | H11: =SUM(H12:H41) -> 71303.92 | J11: =SUM(J12:J41) -> 12269.667 | L11: =SUM(L12:L41) -> 144954.4 | N11: =SUM(N12:N41) -> 157224.07
A12: 1. Registered Seed (RS) Production
A13: Flint
A14: Glutinous | C14: 200 | D14: 10 | E14: 200 | F14: =E14*0.05 -> 10
A15: 2. Recommended Corn Production Technologies (RCPT)
A16: Hybrid Yellow | B16: kilograms | C16: 3600 | D16: 2400 | E16: =150*18 -> 2700 | F16: =150*2*6000/1000 -> 1800 | G16: 8100 | H16: 5850 | K16: =300*27 -> 8100 | L16: =300*19.5 -> 5850 | M16: =SUM(I16,K16) -> 8100 | N16: =J16+L16 -> 5850 | O16: San Guillermo
A17: Inorganic Fertilizer | B17: kilograms | C17: 110000 | D17: 4950 | E17: 1650 | F17: =2264100/1000 -> 2264.1 | G17: 165000 | H17: 6600 | K17: =300*11*50 -> 165000 | L17: =300*11*2 -> 6600 | M17: =SUM(I17,K17) -> 165000 | N17: =J17+L17 -> 6600 | O17: San Guillermo
A18: Bio-N | B18: packs | C18: 350 | D18: 310 | E18: 750 | F18: =339000/1000 -> 339 | G18: 1800 | H18: 360 | K18: =300*6 -> 1800 | L18: =300*6*0.2 -> 360 | M18: =SUM(I18,K18) -> 1800 | N18: =J18+L18 -> 360 | O18: San Guillermo
A19: Agricultural Lime | B19: kilograms | C19: 100000 | D19: 2000 | E19: 1500 | F19: =651000/1000 -> 651 | G19: =300*50*10 -> 150000 | H19: =300*10*0.6 -> 1800 | K19: =300*10*50 -> 150000 | L19: =300*10*0.6 -> 1800 | M19: =SUM(I19,K19) -> 150000 | N19: =J19+L19 -> 1800 | O19: San Guillermo
A20: Plant Growth Enhancer | B20: packs | G20: 300 | H20: 240
A21: Complete Foliar Fertilizer | B21: kilograms | G21: 900 | H21: 540
A22: 3. Corn Production Enhancement Project (CPEP)
A23: Hybrid (GM) | B23: kilograms | C23: 61722 | D23: 41148 | E23: =6858*9 -> 61722 | F23: =40203000/1000 -> 40203 | G23: 35730 | H23: 25805 | I23: =382*18 -> 6876 | J23: =382*13 -> 4966 | K23: =5000*18 -> 90000 | L23: =5000*13 -> 65000 | M23: =SUM(I23,K23) -> 96876 | N23: =J23+L23 -> 69966 | O23: Cauayan City, Echague, San Guillermo, San Isidro
A24: Inorganic Fertilizer for GM | B24: kilograms | C24: 342900 | D24: 15430.5 | E24: =6858*50 -> 342900 | F24: =(3429*1.35)+(3429*1.411) -> 9467.469 | G24: 198500 | H24: 7940 | I24: =382*50 -> 19100 | J24: =382*2 -> 764 | K24: =5000*50 -> 250000 | L24: =5000*2 -> 10000 | M24: =SUM(I24,K24) -> 269100 | N24: =J24+L24 -> 10764
A25: Hybrid (Conventional) | B25: kilograms | G25: 23832 | H25: 13240 | I25: =255*18 -> 4590 | J25: =255*10 -> 2550 | K25: =3334*18 -> 60012 | L25: =3334*10 -> 33340 | M25: =SUM(I25,K25) -> 64602 | N25: =J25+L25 -> 35890
A26: Inorganic Fertilizer for Conventional | B26: kilograms | G26: 132400 | H26: 5296 | I26: =255*150 -> 38250 | J26: =255*6 -> 1530 | K26: =3334*150 -> 500100 | L26: =3334*6 -> 20004 | M26: =SUM(I26,K26) -> 538350 | N26: =J26+L26 -> 21534
A27: Agricultural Gypsum for Conventional | B27: kilograms | I27: =255*50 -> 12750 | J27: =255*0.6 -> 153 | K27: =3334*50 -> 166700 | L27: =3334*0.6 -> 2000.4 | M27: =SUM(I27,K27) -> 179450 | N27: =J27+L27 -> 2153.4
A28: 4. Support to Cassava
A29: Production of cassava seed pieces | B29: pieces | C29: 200000 | D29: 200 | E29: 200000 | F29: =E29*1/1000 -> 200 | G29: 780000 | H29: 1200 | I29: 780000 | J29: =(I29/65000)*100 -> 1200 | M29: =SUM(I29,K29) -> 780000 | N29: =SUM(J29,L29) -> 1200 | O29: Cauayan City, Echague
A30: Procurement of cassava seed pieces | B30: pieces | C30: 1000000 | D30: =C30*0.0015 -> 1500 | E30: 500000 | F30: =E30*1.5/1000 -> 750
A31: Procurement of Inorganic Fertilizer | B31: kilograms | C31: 12000 | D31: 540 | E31: 7000 | F31: =((70*1.35)+(70*1.411)) -> 193.27 | G31: 6000 | H31: 240 | I31: =(I29/13000)*100 -> 6000 | J31: =55*4 -> 220 | M31: =SUM(I31,K31) -> 6000 | N31: =SUM(J31,L31) -> 220 | O31: Cauayan City, Echague
A32: Solar Bubble Dryer | B32: number | G32: 5 | H32: 1250
A33: 5. Support to Sorghum
A34: Sorghum Seeds | B34: kilograms | G34: 200 | H34: 120 | I34: 400 | J34: =(I34/10)*6 -> 240 | M34: =SUM(I34,K34) -> 400 | N34: =SUM(J34,L34) -> 240 | O34: Cauayan City
A35: Inorganic Fertilizer | B35: kilograms | G35: 2000 | H35: 80 | I35: =(I34/10)*100 -> 4000 | J35: =(I35/100)*4 -> 160 | M35: =SUM(I35,K35) -> 4000 | N35: =SUM(J35,L35) -> 160 | O35: Cauayan City
A36: 6. Support to Soybean
A37: Soybean Seeds | B37: kilograms | C37: 1000 | D37: 50 | G37: 2375 | H37: 197.92 | I37: 2000 | J37: =(100/1200)*I37 -> 166.66667 | M37: =SUM(I37,K37) -> 2000 | N37: =SUM(J37,L37) -> 166.66667 | O37: Echague
A38: Inorganic Fertilizer | B38: kilograms | C38: 2500 | D38: 113 | G38: 9500 | H38: 380 | I38: =(I37/25)*100 -> 8000 | J38: =(I38/100)*4 -> 320 | M38: =SUM(I38,K38) -> 8000 | N38: =SUM(J38,L38) -> 320 | O38: Echague
A39: 7. White Corn Production Enhancement Project (WCPEP)
A40: OPV White Glutinous | B40: kilograms | G40: 600 | H40: 45
A41: Inorganic Fertilizer | B41: kilograms | G41: 3000 | H41: 120
A43: II. EXTENSION SUPPORT, EDUCATION & TRAINING SERVICES | D43: =D45+D44 -> 530 | F43: =F45+F44 -> 380 | H43: =H45+H44 -> 0 | J43: =J45+J44 -> 0 | L43: =L45+L44 -> 0 | N43: =N45+N44 -> 0
A44: Soybean Model Farm | B44: site | C44: 1 | D44: 330 | E44: 1 | F44: 330
A45: Soybean Techno Demo | B45: site | C45: 4 | D45: 200 | E45: 1 | F45: 50
A47: III. AGRICULTURAL MACHINERY, EQUIPMENT AND FACILITIES INFRASTRUCTURE PROGRAM | D47: =D48+D78 -> 10100 | F47: =F48+F78 -> 7847.4306 | H47: =H48+H78 -> 114400 | J47: =J48+J78 -> 175300 | L47: =L48+L78 -> 10000 | N47: =N48+N78 -> 185300
A48: 1. AGRICULTURAL MACHINERY, EQUIPMENT AND FACILITIES SUPPORT SERVICES | D48: =SUM(D49:D76) -> 8100 | F48: =SUM(F49:F76) -> 5847.4306 | H48: =SUM(H49:H76) -> 110400 | J48: =SUM(J49:J76) -> 171800 | L48: =SUM(L49:L76) -> 10000 | N48: =SUM(N49:N76) -> 181800
A49: Four-wheel drive tractor for Corn (90-95HP) | B49: number | I49: 1 | J49: 3100 | M49: =SUM(I49,K49) -> 1 | N49: =SUM(J49,L49) -> 3100 | O49: Echague
A50: Four-wheel drive tractor for Cassava (90-95HP) | B50: number
A51: Forage Chopper | B51: number
A52: Double-row Corn Planter | B52: number
A53: Mechanical Four-row Planter | B53: number | C53: 1 | D53: 200 | I53: 1 | J53: 200 | M53: =SUM(I53,K53) -> 1 | N53: =SUM(J53,L53) -> 200 | O53: Cauayan City
A54: Pneumatic Four-row Planter | B54: number
A55: Two-row seeder | B55: number | C55: 5 | D55: 1500 | E55: 4 | F55: =E55*255 -> 1020 | G55: 5 | H55: 1500
A56: Corn Combine Harvester | B56: number | G56: 1 | H56: 2100 | I56: 1 | J56: 2100 | M56: =SUM(I56,K56) -> 1 | N56: =SUM(J56,L56) -> 2100 | O56: Cauayan City
A57: Hauling Truck (cargo truck) | B57: number | C57: 1 | D57: 2200 | E57: 1 | F57: =E57* 1962.59 -> 1962.59 | I57: 3 | J57: =I57*2300 -> 6900 | M57: =SUM(I57,K57) -> 3 | N57: =SUM(J57,L57) -> 6900 | O57: Cauayan City, Echague
A58: Hauling Truck (heavy cargo truck) | B58: number | I58: 1 | J58: 8000 | M58: =SUM(I58,K58) -> 1 | N58: =SUM(J58,L58) -> 8000 | O58: Cauayan City
A59: Corn Mill (village-type) | B59: number | C59: 1 | D59: 2200
A60: Fork Lift | B60: number | I60: 1 | J60: 1500 | M60: =SUM(I60,K60) -> 1 | N60: =SUM(J60,L60) -> 1500 | O60: Cauayan City
A61: Recirculating Dryer | B61: number
A62: Solar Bubble Dryer | B62: number | C62: 5 | D62: 1000 | E62: 10 | F62: 2000
A63: Cassava Granulator | B63: number | G63: 1 | H63: 300
A64: Cassava Digger with Soil Remover | B64: number
A65: Sorghum Harvester | B65: number
A66: Sorghum Thresher | B66: number
A67: Sorghum Dryer | B67: number
A68: Soybean Thresher | B68: number
A69: Soybean Seed Sorter | B69: number
A70: Multi Crop Drying Pavement (MCDP) with Shed | B70: number | C70: 1 | D70: 1000 | E70: 1 | F70: 864.8406 | G70: 1 | H70: 1000
A71: Warehouse | B71: number | G71: 1 | H71: 12500 | K71: 1 | L71: 10000 | M71: =SUM(I71,K71) -> 1 | N71: =SUM(J71,L71) -> 10000 | O71: Echague
A72: Corn Complex (Phase 1) | B72: number | G72: 1 | H72: 93000
A73: Corn Complex (Phase 2) | I73: 1 | J73: 150000 | M73: =SUM(I73,K73) -> 1 | N73: =SUM(J73,L73) -> 150000 | O73: Cauayan City
A74: Silage Silo (Bunker-type) | B74: number
A75: Water Treatment System Facility | B75: number
A76: Wastewater Treatment System Facility | B76: number
A78: 2. IRRIGATION NETWORK SERVICES | D78: =SUM(D79:D80) -> 2000 | F78: =SUM(F79:F80) -> 2000 | H78: =SUM(H79:H80) -> 4000 | J78: =SUM(J79:J80) -> 3500 | L78: =SUM(L79:L80) -> 0 | N78: =SUM(N79:N80) -> 3500
A79: Open Source Pumping Set | B79: unit | C79: 20 | D79: 2000 | E79: 20 | F79: 2000 | G79: 40 | H79: 4000 | I79: 20 | J79: =I79*125 -> 2500 | M79: =SUM(I79,K79) -> 20 | N79: =SUM(J79,L79) -> 2500 | O79: Echague
A80: Mobile Solar Powered Irrigation System | B80: unit | I80: 1 | J80: 1000 | M80: =SUM(I80,K80) -> 1 | N80: =SUM(J80,L80) -> 1000 | O80: Echague
A82: GRAND TOTAL | D82: =SUM(D11,D48,D43,D78) -> 79281.5 | F82: =F78+F48+F11 -> 63725.27 | H82: =H78+H48+H11 -> 185703.92 | J82: =J11+J47 -> 187569.67 | L82: =L11+L47 -> 154954.4 | N82: =N11+N47 -> 342524.07
A83: Chief, PMED | C83: Chief, Budget Section
A86: Prepared by: | C86: In coordination with: | G86: Concurred by:
A89: BERNADETTE T. GALOSO | C89: MACARIO B. ANDAL, CPA | G89: ROSE MARY G. AQUINO, Ph.D.
A90: Chief, PMED | C90: Chief, Budget Section | G90: Regional Executive Director

Sheet HVCDP
A1: DEPARTMENT OF AGRICULTURE-REGIONAL FIELD OFFICE NO. 02
A2: CY 2025 & FY 2026 PROGRAM ACCOMPLISHMENTS/STATUS AND FY 2027 PLAN AND BUDGET PROPOSAL
A3: HIGH VALUE CROPS DEVELOPMENT PROGRAM
A4: PROVINCE: ISABELA
A5: DISTRICT: VI
A7: PROGRAM/SUBPROGRAM/ INDICATORS | B7: UNIT OF MEASURE | C7: CY 2025 GAA | E7: FY 2026 GAA | G7: FY 2027 PROPOSAL | M7: Remarks (Breakdown of Municipality Target for FY 2027 )
G8: TIER 1 | I8: TIER 2 | K8: TOTAL
C9: ANNUAL PHYSICAL TARGET | D9: ANNUAL BUDGET (₱ '000) | E9: ACCOMPLISHMENT | G9: PHYSICAL TARGET | H9: ANNUAL BUDGET (₱ '000) | I9: PHYSICAL TARGET | J9: ANNUAL BUDGET (₱ '000) | K9: PHYSICAL TARGET | L9: ANNUAL BUDGET (₱ '000)
E10: PHYSICAL TARGET | F10: ANNUAL BUDGET (₱ '000)
A11: OPERATIONS | D11: =D12+D633 -> 3100.09
A12: I. TECHNICAL AND SUPPORT SEVICES PROGRAM | D12: =D13+D471 -> 3100.09 | F12: =F13+F471 -> 300 | H12: =H13 -> 1862.6545 | L12: =L13 -> 1862.6545
A13: 1. Production Support Services Sub-Program | D13: =SUM(D19:D470) -> 2300.09 | F13: =SUM(F19:F470) -> 300 | H13: =sum(H16:H441) -> 1862.6545 | L13: =sum(L16:L441) -> 1862.6545
A14: Outcome Indicators
A15: Beneficiaries rating the production support services (PSS) delivered to be at least satisfactory
A16: Deliveries of producrtion support services validated by LGU's to have been delivered at the appropriate time
A17: Output Indicators
A18: LGU's assisted with production support services
A19: Input Indicators | B19: kilogram
A20: Seed Distribution
A21: Procured
A22: Produced
A23: Distributed
A24: Area Planted
A25: Mungbean
A26: Procured
A27: Produced | G27: =200*20 -> 4000 | H27: =G27*0.25 -> 1000 | K27: =200*20 -> 4000 | L27: =K27*0.25 -> 1000
A28: Distributed | G28: =G27 -> 4000 | K28: =K27 -> 4000
A29: Area Planted | G29: =G28/20 -> 200 | K29: =K28/20 -> 200
A30: Peanut
A31: Procured
A32: Produced
A33: Distributed
A34: Area Planted
A35: White Potato
A36: Procured
A37: Produced
A38: Distributed
A39: Area Planted
A40: Hot Pepper
A41: Procured
... A307: Mango
A308: Procured | C308: 13334 | D308: 2000.09
A309: Produced
A310: Distributed | C310: 13334
A311: Area Planted | C311: 66.67
A312: Other Farm Supplies
A313: Flower Inducer
A314: Flower Inducer
A315: Seedling trays
A316: Garden tools
A317: Plastic crate
A318: Bagging Materials
A319: Ladder
A320: Hermetic bag
A321: Fermentation box
A322: Rattan basket
A323: Pallets
... A339: Foliar Fertilizer
A340: Liquid Fertilizer | G340: =G29*4.85181818 -> 970.36364 | H340: =G340*0.42525764 -> 412.65455 | K340: =K29*4.85181818 -> 970.36364 | L340: =K340*0.42525764 -> 412.65455
A344: Other agri-chemical
A345: Pesticide
A346: Insecticide
A347: Fungicide
A348: Herbicide
A349: Pheromone Lure
A350: Soil Conditioner
A352: Biological Control Agents (distibution only)
A353: Trichogramma chilonis
A354: Earwig
A355: Metarhizium
A356: Beauveria
... A440: Urban agriculture garden
A441: Gulayan sa bayan | C441: 3 | D441: 300 | E441: 3 | F441: 300 | G441: 3 | H441: =G441*150 -> 450 | K441: 3 | L441: =K441*150 -> 450 | M441: All Municipalities except City
A443: Farm production-related machinery and equipment (DA Stations)
A444: Tractors
A445: Vegetable seeder
A446: Hand tractor/multi-cultivator
A447: Power spayer
A448: Fertilizer applicator
A449: Pole prunner/ shear
A450: Mini-chainsaw
A451: Onion/garlic harvester
A452: Grass cutter
A453: Soil Auger
A454: Lifting machine
... A469: Support to Sustainable Pest and Disease Management for High Value Crops (Banana, Mango, Onion)
A471: 2. Extension Support, Education and Training Services Sub-Program | B471: number | D471: =SUM(D472:D632) -> 800 | F471: =SUM(F472:F632) -> 0
A472: Outcome Indicators | B472: number
A473: Adoption rate of beneficiaries of extension support, education and training services | B473: number
A474: Output Indicators | B474: number
A475: Extension workers trained to support the capacity of LGU's | B475: number
A476: Female | B476: number
A477: Male | B477: number
A478: Individual benefiaciaries provided with training support services | B478: number
A479: Female | B479: number
A480: Male | B480: number
A481: Input Indicators | B481: number
A482: Training and training-related events | B482: number
A483: Package of Technology (POT) Conducted | B483: number
... A524: Male | B524: number
...

Sheet NUPAP
A1: DEPARTMENT OF AGRICULTURE-REGIONAL FIELD OFFICE NO. 02
A2: CY 2025 & FY 2026 PROGRAM ACCOMPLISHMENTS/STATUS AND FY 2027 PLAN AND BUDGET PROPOSAL
A3: NATIONAL URBAN AND PERI-URBAN AGRICULTURE PROGRAM
A4: PROVINCE: ISABELA
A5: DISTRICT: VI
A7: PROGRAM/SUBPROGRAM/ INDICATORS | B7: UNIT OF MEASURE | C7: CY 2025 GAA | E7: FY 2026 GAA | G7: FY 2027 PROPOSAL | M7: Remarks (Breakdown of Municipality Target for FY 2027 )
G8: TIER 1 | I8: TIER 2 | K8: TOTAL
C9: ANNUAL PHYSICAL TARGET | D9: ANNUAL BUDGET (₱ '000) | E9: ACCOMPLISHMENT | G9: PHYSICAL TARGET | H9: ANNUAL BUDGET (₱ '000) | I9: PHYSICAL TARGET | J9: ANNUAL BUDGET (₱ '000) | K9: PHYSICAL TARGET | L9: ANNUAL BUDGET (₱ '000)
E10: PHYSICAL TARGET | F10: ANNUAL BUDGET (₱ '000)
A11: OPERATIONS | C11: =C12+C37 -> 0 | D11: =D12+D37 -> 116.44921 | F11: =F12+F37 -> 30
A12: I. TECHNICAL AND SUPPORT SEVICES PROGRAM | C12: =C13+C35 -> 0 | D12: =D13+D35 -> 116.44921 | F12: =F13+F35 -> 30
A13: 1. Production Support Services Sub-Program | D13: =sum(D15:D22) -> 116.44921 | F13: =sum(F15:F22) -> 30
A14: 1.1. Seeds Procured for Distribution
A15: Lowland Vegetables | B15: kilograms distributed | C15: 3 | D15: 38.46153
A16: Highland Vegetables | B16: kilograms distributed | C16: 3 | D16: 38.46153
A17: 1.2. Planting Materials for Distribution
A18: Fruit Bearing Tree (seedlings) | B18: pieces
A19: Strawberry (cuttings) | C19: 50 | D19: 3.8095
A20: 1.3. Soil Mix/Fertilizer:
A21: Organic Fertilizer - Solid | B21: kilograms distributed | C21: 1500 | D21: 19.05 | E21: 60 | F21: 30
A22: Soilless Media/Potting Mix | B22: kilograms distributed | C22: 1125 | D22: 16.66665
A23: Liquid Fertilizer - Hydroponic Solution | B23: liter
A25: 1.4. Other Farm Inputs
A26: Seedling Tray | B26: pieces
A27: Plastic Crate | B27: pieces | E27: 20.5 | F27: 41
A28: Plastic Mulch | B28: rolls | C28: 5 | D28: 14761
A29: Set of Garden Tools | B29: number
A30: Clay Pot | B30: number
A31: Stackable pots | B31: number | C31: 10 | D31: 38.0952
A32: Plastic Drum | B32: number
A33: Garden Hose | B33: number
A34: Wheel Barrow | B34: number
A35: 2. Extension Support, Education and Training Services Sub-Program
A37: II. AGRICULTURAL MACHINERY, EQUIPMENT, FACILITIES AND INFRASTRUCTURE PROGRAM | C37: =C38 -> 0 | D37: =D38 -> 0
A38: 1. Agricultural Machinery, Equipment and Facilities Support Services Sub-Program | C38: =SUM(C41:C48) -> 0 | D38: =SUM(D41:D48) -> 0
A39: 1.1. Farm production-related machinery and equipment distributed
A40: Soil Auger | B40: number | E40: 1 | F40: 47
A41: Multi Cultivator | B41: number | E41: 1 | F41: 100
A42: 1.2. Other facilities and activities
A43: Mushroom House with Spawn | B43: number | E43: 1 | F43: 300
A44: Greenhouse with Hydroponics and Water System | B44: number | E44: 1 | F44: 2000
A45: Rabbit Module with Housing | B45: number
A46: Poultry House with Chickens | E46: 1 | F46: 315
A47: 1.3. Postharvest/processing equipment and machineries distributed/ constructed | E47: =E49 | F47: =F49
A48: Plastic Crate | B48: pieces
A49: 2. Irrigation Network Services (INS) Sub-program
A50: GRAND TOTAL | D50: =D11 -> 116.44921 | F50: =F46+F44+F43+F41+F40+F21 -> 2792 | H50: 0 | J50: 0 | L50: 0
A53: Prepared by: | C53: In coordination with
A58: BERNADETTE T. GALOSO | C58: MACARIO B. ANDAL, CPA
A59: Chief, PMED | C59: Chief, Budget Section
A61: Prepared by: | D61: In coordination with: | H61: Concurred by:
A64: BERNADETTE T. GALOSO | D64: MACARIO B. ANDAL, CPA | H64: ROSE MARY G. AQUINO, Ph.D.
A65: Chief, PMED | D65: Chief, Budget Section | H65: Regional Executive Director

Sheet LIVESTOCK
A1: DEPARTMENT OF AGRICULTURE-REGIONAL FIELD OFFICE NO. 02
A2: CY 2025 & FY 2026 PROGRAM ACCOMPLISHMENTS/STATUS AND FY 2027 PLAN AND BUDGET PROPOSAL
A3: LIVESTOCK PROGRAM
A4: PROVINCE: ISABELA
A5: DISTRICT: VI
A7: PROGRAM/SUBPROGRAM/ INDICATORS | B7: UNIT OF MEASURE | C7: CY 2025 GAA | E7: FY 2025 GAA | G7: FY 2026 GAA | I7: FY 2027 PROPOSAL | O7: Remarks (Breakdown of Municipality Target for FY 2027 )
I8: TIER 1 | K8: TIER 2 | M8: TOTAL
C9: ANNUAL PHYSICAL TARGET | D9: ANNUAL BUDGET (₱ '000) | E9: ACCOMPLISHMENT | G9: ACCOMPLISHMENT | I9: PHYSICAL TARGET | J9: ANNUAL BUDGET (₱ '000) | K9: PHYSICAL TARGET | L9: ANNUAL BUDGET (₱ '000) | M9: PHYSICAL TARGET | N9: ANNUAL BUDGET (₱ '000)
E10: PHYSICAL | F10: BUDGET (Actual Obligation) | G10: PHYSICAL TARGET | H10: ANNUAL BUDGET (₱ '000)
A11: I. Production Support Services Sub-Program | C11: 225 | D11: =SUM(D14:D31) -> 8079.6 | H11: =SUM(H14:H27) -> 369.6 | J11: =SUM(J14:J27) -> 585 | N11: =SUM(N14:N27) -> 585
A12: 1. National Animal Genetic Resources Improvement Program
A13: 1.1. Unified National Artificial Insemination Program
A14: Cattle | B14: number | C14: 200 | D14: 186 | E14: 200 | F14: 186 | G14: 200 | H14: 186 | I14: 160 | J14: =I14*0.5 -> 80 | M14: 160 | N14: =M14*0.5 -> 80
A15: Goat | B15: number | C15: 20 | D15: 18.6 | E15: 20 | F15: 18.6 | G15: 20 | H15: 18.6 | I15: 50 | J15: =I15*0.5 -> 25 | M15: 50 | N15: =M15*0.5 -> 25
A16: Planting Materials distributed | B16: number | I16: 11666 | J16: 175 | M16: 11666 | N16: 175
A17: 2. Philippine Native Animal Development
A18: Duck Stock Distribution | B18: number | I18: 500 | J18: 250 | M18: 500 | N18: 250
A20: 3. Development, Maintenance, and Rehabilitation/ Upgrading of Government Stock Farms, and Other Facilities | B20: number
A21: Sheep | B21: number | C21: 5 | D21: 275 | E21: 5 | F21: 275 | G21: 3 | H21: =G21*55 -> 165 | I21: 1 | J21: 55 | M21: 1 | N21: 55
A23: 4. Support to Prevention and Control of Economically Important Diseases
A24: 1. Drug and Biologic Support | B24: doses
A25: 2. Calibrated sentinelling and Repopulation
A26: No. of Piglets Distributed | B26: number
A27: No. of Feeds Distributed | B27: number
A28: No. of Test Kit Distributed | B28: number
A29: LEED
A30: Duck Multiplier Farm | B30: number | C30: 1 | D30: 3000
A31: Sheep Multiplier Farm | B31: number | C31: 1 | D31: 4600
A32: II. AGRICULTURAL MACHINERY, EQUIPMENT, FACILITIES AND INFRASTRUCTURE PROGRAM | D32: =D33 -> 2700 | H32: =H33 -> 2500 | J32: =J33 -> 13300 | N32: =N33 -> 13300
A33: Agricultural Machinery, Equipment and Facilities Support Services (AMEFSS) | D33: =SUM(D36:D41) -> 2700 | H33: =H42+H44 -> 2500 | J33: =sum(J36:J42) -> 13300 | N33: =sum(N36:N42) -> 13300
A34: 1. Production Facilities Established | B34: number
A35: 1.1 Livestock Economic Enterprise Development (LEED) | B35: number
A36: Cattle Multiplier Farm | B36: number | C36: 1 | D36: 2700 | I36: 2 | J36: 5400 | M36: 2 | N36: 5400 | O36: San Guillermo/Echague
A37: Geese Multiplier Farm | B37: number
A38: Chicken Multiplier Farm | B38: number
A39: Duck Multiplier Farm | B39: number
A40: Goat Multiplier FArm | B40: number
A41: Carabao Multiplier Farm | B41: number | I41: 2 | J41: 5400 | M41: 2 | N41: 5400 | O41: San Isidro/Cauayan City
A42: Animal Hauling Trucks | B42: number | G42: 1 | H42: 2500 | I42: 1 | J42: 2500 | M42: 1 | N42: 2500 | O42: San Guillermo
A43: solar sets | B43: number | C43: -
A45: GRAND TOTAL | D45: =D33+D11 -> 10779.6 | H45: =H32+H11 -> 2869.6 | J45: =J32+J11 -> 13885 | L45: 0 | N45: =N32+N11 -> 13885
A48: Prepared by: | C48: In coordination with
A53: BERNADETTE T. GALOSO | C53: MACARIO B. ANDAL, CPA
A54: Chief, PMED | C54: Chief, Budget Section
A57: Prepared by: | D57: In coordination with: | H57: Concurred by:
A60: BERNADETTE T. GALOSO | D60: MACARIO B. ANDAL, CPA | H60: ROSE MARY G. AQUINO, Ph.D.
A61: Chief, PMED | D61: Chief, Budget Section | H61: Regional Executive Director

Sheet HALAL
A1: DEPARTMENT OF AGRICULTURE-REGIONAL FIELD OFFICE NO. 02
A2: CY 2025 & FY 2026 PROGRAM ACCOMPLISHMENTS/STATUS AND FY 2027 PLAN AND BUDGET PROPOSAL
A3: HALAL PROGRAM
A4: PROVINCE:ISABELA
A5: DISTRICT: VI
A7: PROGRAM/SUBPROGRAM/ INDICATORS | B7: UNIT OF MEASURE | C7: FY 2025 GAA | E7: FY 2026 GAA | G7: FY 2027 PROPOSAL | M7: Remarks (Breakdown of Municipality Target for FY 2027 )
C8: ANNUAL PHYSICAL TARGET | D8: ANNUAL BUDGET (₱ '000) | G8: TIER 1 | I8: TIER 2 | K8: TOTAL
E9: ACCOMPLISHMENT | G9: PHYSICAL TARGET | H9: ANNUAL BUDGET (₱ '000) | I9: PHYSICAL TARGET | J9: ANNUAL BUDGET (₱ '000) | K9: PHYSICAL TARGET | L9: ANNUAL BUDGET (₱ '000)
E10: PHYSICAL TARGET | F10: ANNUAL BUDGET (₱ '000)
A11: I. TECHNICAL AND SUPPORT SERVICES PROGRAM | D11: 200
A12: A. Extension Support, Education and Training Services | D12: 200
A13: 1. Advanced Training cum Production on Halal Farming Systems | D13: 60
A14: Halal orientation conducted | B14: number | C14: 1
A15: Participants | B15: number | C15: 25
A16: 2. Halal Product Certification Assistance | C16: 1 | D16: 50 | E16: 3 | F16: 125
A17: Product for certification | B17: number
A18: 3. Assistance on the Production of DA Assisted Halal Certified Products | C18: 1 | D18: 90
A19: Products assisted | B19: number
A21: B. Field Program Management Activities (FPMA)
A22: 1. Halal Product Certification Assistance
A23: Hiring of | B23: number
A25: GRAND TOTAL | D25: 200 | F25: =F16 -> 125 | H25: 0 | J25: 0 | L25: 0
A27: Prepared by: | C27: In coordination with: | G27: Concurred by:
A30: BERNADETTE T. GALOSO | C30: MACARIO B. ANDAL, CPA | G30: ROSE MARY G. AQUINO, Ph.D.
A31: Chief, PMED | C31: Chief, Budget Section | G31: Regional Executive Director

Sheet FMR
A1: DEPARTMENT OF AGRICULTURE-REGIONAL FIELD OFFICE NO. 02
A2: CY 2025 & FY 2026 PROGRAM ACCOMPLISHMENTS/STATUS AND FY 2027 PLAN AND BUDGET PROPOSAL
A3: FARM-TO-MARKET ROAD DEVELOPMENT PROGRAM
A4: PROVINCE: ISABELA
A5: DISTRICT:VI
A8: FY 2025 NEP
A21: TOTAL | D21: =SUM(D9:D20) -> 0 | E21: =SUM(E9:E20) -> 0
A23: FY 2025 PROPOSAL (TIER I)
A24: CAUAYAN CITY | B24: Naganacan | C24: Concreting of Naganacan-Alinam FMR | D24: 1 | E24: 15000
B25: Santa Luciana-San Francisco | C25: Concreting of Santa Luciana-San Francisco FMR | D25: 1 | E25: 15000
A26: SAN ISIDRO | B26: Camarag-Doña Paulina | C26: Concreting of Camarag-Doña Paulina FMR | D26: 1 | E26: 15000
B27: Purok 4,Gud-Nagbukel | C27: Concreting of Purok 4, Gud-Nagbukel FMR | D27: 1 | E27: 15000
A28: SUBTOTAL | D28: =SUM(D24:D27) -> 4 | E28: =SUM(E24:E27) -> 60000
A30: FY 2025 PROPOSAL TIER II
A31: CAUAYAN CITY | B31: Rogus | C31: Concreting Of Rogus-De Vera FMR | D31: 1 | E31: 15000
B32: Faustino | C32: Concreting Of Brgy. Faustino Farm-To-Market Road | D32: 1 | E32: 15000
B33: Villa Concepcion | C33: Concreting Of Brgy Villa Concepcion FMR | D33: 1.2 | E33: 18000
A34: SAN ISIDRO | B34: Palawan-San Mariano Sur | C34: Concreting Of Palawan-San Mariano Sur FMR | D34: 1 | E34: 15000
A35: SUBTOTAL | D35: =SUM(D31:D33) -> 3.2 | E35: =SUM(E31:E34) -> 63000
A36: TOTAL | D36: =D35+D28 -> 7.2 | E36: =E35+E28 -> 123000
A37: FY 2025 NEP
A38: CAUAYAN CITY | B38: Naganacan | C38: Concreting of Naganacan- Alinam FMR, Brgy. Naganacan, Cauayan City, Isabela | D38: 1 | E38: 15000
B39: Santa Luciana- San Francisco | C39: Concreting of Santa Luciana- San Francisco FMR, Brgy. Santa Luciana- San Francisco, Cauayan City, Isabela | D39: 1 | E39: 15000
B40: Marabulig- Nagrumbuan | C40: Concreting of Brgy. Marabulig- Brgy. Nagrumbuan FMR Phase II, Brgy. Marabulig- Brgy. Nagrumbuan, Cauayan City, Isabela | D40: 0.667 | E40: 10000
B41: Nagrumbuan- Pinoma | C41: Concreting of Brgy. Nagrumbuan- Brgy. Pinoma FMR Phase II,Brgy. Nagrumbuan- Brgy. Pinoma, Cauayan City, Isabela | D41: 0.667 | E41: 10000
B42: Nungnungan I | C42: Concreting of Brgy. Nungnungan I FMR Phase II, Brgy. Nungnungan I, Cauayan City, Isabela | D42: 0.667 | E42: 10000
B43: San Francisco - Faustino | C43: Concreting of Brgy. San Francisco - Brgy. Faustino FMR Phase II, Brgy. San Francisco - Brgy. Faustino , Cauayan City, Isabela | D43: 0.667 | E43: 10000
B44: Buena Suerte | C44: Concreting of Brgy. Buena Suerte FMR Phase II, Brgy. Buena Suerte, Cauayan City, Isabela | D44: 0.666 | E44: 10000
B45: Labinab | C45: Concreting of Brgy. Labinab FMR Phase II, Brgy. Labinab, Cauayan City, Isabela | D45: 2 | E45: 30000
B46: Santa Maria - Villa Concepcion | C46: Construction of Brgy. Santa Maria - Villa Concepcion FMR,Brgy. Santa Maria - Brgy. Villa Concepcion , Cauayan City, Isabela | D46: 0.666 | E46: 10000
A47: ECHAGUE | B47: Narra | C47: Concreting of Brgy. Narra FMR, Brgy. Narra, Echague, Isabela | D47: 1 | E47: 15000
A48: TOTAL | D48: =SUM(D38:D47) -> 9 | E48: =SUM(E38:E47) -> 135000
A50: CY 2025 GAA
A51: Cauayan City | B51: Naganacan- Alinam | C51: Concreting of Naganacan- Alinam FMR, Brgy. Naganacan, Cauayan City, Isabela | D51: 1 | E51: 15000
A52: Cauayan City | B52: Santa Luciana- San Francisco | C52: Concreting of Santa Luciana- San Francisco FMR, Brgy. Santa Luciana- San Francisco, Cauayan City, Isabela | D52: 1 | E52: 15000
A53: Cauayan City | B53: Sitio Calagui, San Pablo | C53: Concreting of Sitio Calagui, Brgy. San Pablo FMR, Brgy. San Pablo, Cauayan City, Isabela | D53: 0.667 | E53: 10000
A54: Cauayan City | B54: Dianao | C54: Concreting of Brgy. Dianao FMR, Brgy. Dianao, Cauayan City, Isabela | D54: 0.333 | E54: 5000
A55: Cauayan City | B55: San Francisco - Dabburab | C55: Concreting of Brgy. San Francisco to Brgy. Dabburab FMR, Brgy. San Francisco to Brgy. Dabburab, Cauayan City, Isabela | D55: 0.333 | E55: 5000
A56: Cauayan City | B56: Linglingay | C56: Concreting of Brgy. Linglingay FMR, Brgy. Linglingay, Cauayan City, Isabela | D56: 0.333 | E56: 5000
A57: Cauayan City | B57: Purok 2 . Villa Concepcion, | C57: Concreting of Purok 2 , Brgy. Villa Concepcion FMR, Brgy. Villa Concepcion, Cauayan City, Isabela | D57: 0.667 | E57: 10000
A58: Cauayan City | B58: Santa Maria - Villa Concepcion | C58: Concreting of Brgy. Santa Maria - Villa Concepcion FMR,Brgy. Santa Maria - Brgy. Villa Concepcion , Cauayan City, Isabela | D58: 0.667 | E58: 10000
A59: Echague | B59: Pangal Norte | C59: Concreting of Brgy. Pangal Norte FMR, Brgy. Pangal Norte, Echague, Isabela | D59: 0.333 | E59: 5000
A60: Echague | B60: Villa Victoria - Villa Fermin | C60: Concreting of Villa Victoria to Villa Fermin FMR, Brgy Villa Victoria - Brgy. Villa Fermin, Echague, Isabela | D60: 0.333 | E60: 5000
A61: TOTAL | D61: =SUM(D51:D60) -> 5.666 | E61: =SUM(E51:E60) -> 85000
A63: FY 2026 NEP
A64: CAUAYAN CITY | B64: San Francisco | C64: Concreting of Santa Luciana- San Francisco FMR, Brgy. Santa Luciana- San Francisco, Cauayan City, Isabela | D64: 1 | E64: 15000
A65: ECHAGUE | B65: Caniguing | C65: Concreting of Caniguing FMR, Brgy. Caniguing, Echague, Isabela | D65: 1 | E65: 15000
A66: SAN GUILLERMO | B66: Palawan-San Mariano Sur | C66: Concreting of Palawan-San Mariano Sur FMR, Brgy. Palawan-San Mariano Sur, San Guillermo, Isabela | D66: 1 | E66: 15000
A67: ECHAGUE | B67: Narra | C67: Concreting of Brgy. Narra FMR, Brgy. Narra, Echague, Isabela | D67: 0.733 | E67: 11000
A68: CAUAYAN CITY | B68: Rizal | C68: Concreting of Brgy. Rizal-San Francisco FMR, Brgy. Rizal, Cauayan City, Isabela | D68: 1 | E68: 15000
A69: CAUAYAN CITY | B69: Disimuray | C69: Concreting of Brgy. Disimuray FMR, Cauayan City, Isabela | D69: 1 | E69: 15000
A70: SAN ISIDRO | B70: Gud-Nagbukel | C70: Concreting of Purok 4, Gud-Nagbukel FMR, Brgy. Gud-Brgy. Nagbukel, San Isidro, Isabela | D70: 1 | E70: 15000
A71: TOTAL | D71: =SUM(D64:D70) -> 6.733 | E71: =SUM(E64:E70) -> 101000
A72: FY 2026 GAA
A73: Cauayan City | B73: Santa Luciana and Brgy. San Francisco | C73: Concreting of Brgy. Santa Luciana - Brgy. San Francisco FMR Phase II, Brgy. Santa Luciana and Brgy. San Francisco, Cauayan City, Isabela | D73: 1 | E73: 15000
A74: Cauayan City | B74: Gappal | C74: Concreting of Brgy. Gappal FMR, Brgy. Gappal, Cauayan City, Isabela | D74: 2 | E74: 30000
A75: Cauayan City | B75: Maligaya | C75: Concreting of Brgy. Maligaya FMR, Brgy. Maligaya, Cauayan City, Isabela | D75: 1 | E75: 15000
A76: Cauayan City | B76: Sta. Maria | C76: Concreting of Brgy. Sta. Maria FMR 2, Brgy. Sta. Maria, Cauayan City, Isabela | D76: 1.47 | E76: 22000
A77: Cauayan City | B77: Disimuray | C77: Concreting of Brgy. Disimuray Phase II FMR, Brgy. Disimuray, Cauayan City, Isabela | D77: 1.6 | E77: 24000
A78: Cauayan City | B78: San Pablo | C78: Concreting of Brgy. San Pablo FMR, Brgy. San Pablo, Cauayan City, Isabela | D78: 1.9 | E78: 28500
A79: Cauayan City | B79: Rizal and San Francisco | C79: Concreting of Brgy. Rizal-Brgy. San Francisco FMR Phase I, Brgy. Rizal, Cauayan City, Isabela | D79: 1 | E79: 15000
A80: Cauayan City | B80: Disimuray | C80: Concreting of Brgy. Disimuray FMR Phase I, Brgy. Disimuray, Cauayan City, Isabela | D80: 1 | E80: 15000
A81: Cauayan City | B81: San Antonio | C81: Concreting of Brgy. San Antonio FMR, Brgy. San Antonio, Cauayan City, Isabela | D81: 1 | E81: 15000
A82: Cauayan City | B82: Nungnungan | C82: Concreting of Brgy. Nungnungan I FMR Phase II, Cauayan City, Isabela | D82: 1.33 | E82: 20000
A83: Cauayan City | B83: Nagrumbuan-Pinoma | C83: Concreting of Brgy. Nagrumbuan - Brgy. Pinoma FMR Phase III, Cauayan City, Isabela | D83: 1.33 | E83: 20000
A84: Cauayan City | B84: Faustino | C84: Concreting of Brgy. Faustino FMR, Cauayan City, Isabela | D84: 1 | E84: 15000
... A100: San Isidro | B100: Victoria and Gomez | C100: Concreting of Brgy. Victoria-Brgy. Gomez FMR, Brgy. Victoria and Brgy. Gomez, San Isidro, Isabela | D100: 1 | E100: 15000
A101: TOTAL | D101: =SUM(D73:D100) -> 36.62 | E101: =SUM(E73:E100) -> 549400
A102: FY 2027 PROPOSAL (TIER I)
A103: San Guillermo | B103: Guam and San Francisco | C103: Concreting of Sitio Americana-San Francisco Norte FMR, Brgy. Guam and Brgy. San Francisco, San Guillermo, Isabela | D103: 2 | E103: 30000
A104: San Isidro | B104: Ramos West and Ramos East | C104: Concreting of Brgy. Ramos West-Ramos East FMR, Brgy. Ramos West and Brgy. Ramos East, San Isidro, Isabela | D104: 2 | E104: 30000
A105: Cauayan City | B105: Maligaya | C105: Concreting of Sitio Maligaya, Brgy. Maligaya FMR, Brgy. Maligaya, Cauayan City, Isabela | D105: 3 | E105: 45000
A106: San Isidro | B106: Gud | C106: Concreting of Brgy Gud FMR, Brgy. Gud, San Isidro, Isabela | D106: 1.8 | E106: 27000
A107: Cauayan City | B107: San Luis | C107: Concreting of Brgy. San Luis FMR, Brgy. San Luis, Cauayan City, Isabela | D107: 1.6 | E107: 23000
A108: SUBTOTAL | D108: =SUM(D103:D107) -> 10.4 | E108: =SUM(E103:E107) -> 155000
A110: FY 2027 PROPOSAL (TIER II)
A111: Cauayan City | B111: Rogus | C111: Concreting of Rogus FMR Phase 2, Brgy. Rogus, Cauayan City, Isabela | D111: 1 | E111: 15000
A112: San Guillermo | B112: Villa Sanchez and Villa Rose | C112: Concreting of Brgy Villa Sanchez-Villa Rose FMR, Brgy Villa Sanchez and Villa Rose, San Guillermo, Isabela | D112: 5.4 | E112: 80000
A113: San Isidro | B113: Ramos East | C113: Concreting of Brgy. Ramos East FMR, Brgy. Ramos East, San Isidro, Isabela | D113: 1 | E113: 15000
A114: San Isidro | B114: Quezon | C114: Concreting of Brgy. Quezon FMR, Brgy. Quezon, San Isidro, Isabela | D114: 1 | E114: 15000
A115: Cauayan City | B115: Baculod | C115: Concreting of Brgy Baculod-Brgy Dianao FMR, Brgy. Baculod and Brgy Dianao, Cauayan City, Cagayan | D115: 1.5 | E115: 22500
A116: Cauayan City | B116: Cabugao and Sinippil | C116: Concreting of Brgy Cabugao-Brgy Sinippil FMR, Brgy Cabugao and Brgy Sinippil, Cauayan City, Cagayan | D116: 1.7 | E116: 25500
A117: Cauayan City | B117: Pinoma | C117: Concreting of Brgy Pinoma FMR, Brgy. Pinoma, Cauayan City, Isabela | D117: 1.3 | E117: 19500
A118: SUBTOTAL | D118: =SUM(D111:D117) -> 12.9 | E118: =SUM(E111:E117) -> 192500
A119: TOTAL | D119: =D108+D118 -> 23.3 | E119: =E108+E118 -> 347500

Sheet OAP
A1: DEPARTMENT OF AGRICULTURE-REGIONAL FIELD OFFICE 02
A2: CY 2023-2024 PROGRAM ACCOMPLISHMENTS/STATUS AND FY 2025 PLAN AND BUDGET BASED ON NEP
A3: ORGANIC AGRICULTURE PROGRAM
A4: PROVINCE: ISABELA
A5: DISTRICT: VI
A7: PROGRAM/SUBPROGRAM/ INDICATORS | B7: UNIT OF MEASURE | C7: CY 2023 GAA | E7: CY 2024 GAA | H7: FY 2025 PROPOSAL
C8: ACCOMPLISHMENT | E8: ANNUAL PHYSICAL TARGET | F8: ANNUAL BUDGET (₱ '000) | G8: ACCOMPLISHMENT
C9: PHYSICAL | D9: ACTUAL OBLIGATION | H9: TIER 1 | J9: TIER 2 | L9: TOTAL
G10: PHYSICAL TARGET (June 30,2024) | H10: PHYSICAL TARGET | I10: BUDGET | J10: PHYSICAL TARGET | K10: BUDGET | L10: PHYSICAL TARGET | M10: ANNUAL BUDGET (₱ '000)
A11: OPERATIONS
A12: I. TECHNICAL AND SUPPORT SERVICES PROGRAM
A13: 1. Production Support Services Sub-program
A14: 2. Extension Support, Education and Training Services Sub-Program
A15: II. AGRICULTURAL, MACHINERIES, FACILITIES AND INFRASTRUCTURE PROGAM
A16: 1. Agricultural and Fishery Machinery, Equipment and Facilities Support Services Sub-program
A17: 2.Irrigation Network Services (INS) Sub-program
D43: 0 | F43: 0 | M43: 0
A45: Prepared by: | C45: Reviewed by: | H45: In coordination with | M45: Approved by:
A50: JONAZON JEFF T. FACTORA | C50: BERNADETTE T. GALOSO | H50: MACARIO B. ANDAL, CPA | M50: ROSE MARY G. AQUINO, Ph.D.
A51: Chief, Planning and Investment | C51: OIC-Chief, PMED | H51: Chief, Budget Section | M51: Regional Executive Director
A52: Programming Section

Sheet SAAD
A1: DEPARTMENT OF AGRICULTURE-REGIONAL FIELD OFFICE NO. 02
A2: CY 2025 & FY 2026 PROGRAM ACCOMPLISHMENTS/STATUS AND FY 2027 PLAN AND BUDGET PROPOSAL
A3: SPECIAL AREA FOR AGRICULTURAL DEVELOPMENT (SAAD) PROGRAM
A4: PROVINCE: ISABELA
A5: DISTRICT:VI
A7: PROGRAM/SUBPROGRAM/ INDICATORS | B7: UNIT OF MEASURE | C7: CY 2025 GAA | E7: FY 2026 GAA | G7: FY 2027 PROPOSAL | M7: Remarks (Breakdown of Municipality Target for FY 2027 )
G8: TIER 1 | I8: TIER 2 | K8: TOTAL
C9: ANNUAL PHYSICAL TARGET | D9: ANNUAL BUDGET (₱ '000) | E9: ACCOMPLISHMENT | G9: PHYSICAL TARGET | H9: ANNUAL BUDGET (₱ '000) | I9: PHYSICAL TARGET | J9: ANNUAL BUDGET (₱ '000) | K9: PHYSICAL TARGET | L9: ANNUAL BUDGET (₱ '000)
E10: PHYSICAL TARGET | F10: ANNUAL BUDGET (₱ '000)
A11: I. SOCIAL PREPARATION | D11: 225 | F11: 287.5 | H11: 265 | L11: 265
A12: A. Community Needs Assessment (CNA)
A13: a.1 Orientations, Meetings, Assessments and Consultation conducted | B13: number | E13: 1 | G13: 1 | K13: 1 | M13: San Isidro
A14: a.2 Beneficiary Needs Assessment/ Participatory Rural Appraisal (PRA) conducted | B14: group | C14: 1 | E14: 1
A15: B. Beneficiary Capacitation and General Development | E15: 4
A16: b.1 Capability Building activities conducted | B16: group | C16: 3 | E16: 8 | G16: 3 | K16: 3 | M16: San Isidro
A17: C. Database and Profiling
A18: c.1 Beneficiary Profiling conducted | B18: group | C18: 3 | E18: 4 | G18: 3 | K18: 3 | M18: San Isidro
A19: c.2 Database Uploading conducted | B19: group | C19: 3 | E19: 4 | G19: 3 | K19: 3 | M19: San Isidro
A21: II. FOOD PRODUCTION AND LIVELIHOOD INTERVENTIONS | D21: =SUM(D22:D23) -> 2491 | F21: =SUM(F22:F23) -> 2710 | H21: =H22 -> 1516 | L21: =L22 -> 1516
A22: 2.1 HVC-based Project distributed | B22: group | C22: 3 | D22: 2396 | E22: 2 | F22: 2510 | G22: 3 | H22: 1516 | K22: 3 | L22: 1516 | M22: San Isidro
A23: 2.2 Specialized Trainings conducted | B23: number | C23: 1 | D23: 95 | E23: 4 | F23: 200
E24: =#REF! -> #REF!
A25: III. MARKETING ASSISTANCE AND ENTERPRISE DEVELOPMENT | D25: =D26+D27 -> 150 | F25: =F26 -> 287.5 | H25: 326 | L25: 326
A26: 3.1 Market-related trainings conducted | B26: number | C26: 2 | D26: 150 | E26: 8 | F26: 287.5 | G26: 3 | K26: 3 | M26: San Isidro
A27: 3.2 Partially established CBEs | B27: group | G27: 1 | K27: 1 | M27: San Isidro
A29: IV. PROGRAM MANAGEMENT | D29: 0 | F29: 0
A30: 4.1.1. Hiring/renewal of manpower
A31: A. RPMSO
A32: B. PPMSO
A33: 4.1.2 Office Oprating Requirements
A34: 4.2. Review and Planning Workshop
A35: A. Plan and Budget Preparation (PBP)
A36: B. Budget Execution Document (BED) Preparation
A37: 4.3. Monitoring and Evaluation
A38: 4.3.1. Conduct of Performance and Budget
A39: 4.3.2. Implementation of management information
A40: - Sub-project monitoring
A41: 4.4. Project Assessment (PA)
... A45: 4.1. Project Management Offices Maintained
A47: GRAND TOTAL | D47: =D29+D25+D21+D11 -> 2866 | F47: =F29+F25+F21+F11 -> 3285 | H47: =H11+H21+H25 -> 2107 | J47: 0 | L47: =L11+L21+L25 -> 2107
A48: Note: FY 2027 budget allocation for the Social Preparation and MAED is by component.
A50: Prepared by: | B50: In coordination with: | F50: Concurred by:
A53: BERNADETTE T. GALOSO | B53: MACARIO B. ANDAL, CPA | F53: ROSE MARY G. AQUINO, Ph.D.
A54: Chief, PMED | B54: Chief, Budget Section | F54: Regional Executive Director

Sheet MCRA
A1: DEPARTMENT OF AGRICULTURE-REGIONAL FIELD OFFICE NO. 02
A2: CY 2025 & FY 2026 PROGRAM ACCOMPLISHMENTS/STATUS AND FY 2027 PLAN AND BUDGET PROPOSAL
A3: MAINSTREAMING CLIMATE RESILIENT AGRICULTURE (MCRA) TO THE REGIONAL PROGRAMS & PROJECTS
A4: PROVINCE: ISABELA
A5: DISTRICT: VI
A7: PROGRAM/SUBPROGRAM/ INDICATORS | B7: UNIT OF MEASURE | C7: CY 2025 GAA | E7: FY 2026 GAA | G7: FY 2027 PROPOSAL | M7: Remarks (Breakdown of Municipality Target for FY 2027 )
G8: TIER 1 | I8: TIER 2 | K8: TOTAL
C9: ANNUAL PHYSICAL TARGET | D9: ANNUAL BUDGET (₱ '000) | E9: ACCOMPLISHMENT | G9: PHYSICAL TARGET | H9: ANNUAL BUDGET (₱ '000) | I9: PHYSICAL TARGET | J9: ANNUAL BUDGET (₱ '000) | K9: PHYSICAL TARGET | L9: ANNUAL BUDGET (₱ '000)
E10: PHYSICAL TARGET | F10: ANNUAL BUDGET (₱ '000)
A11: OPERATIONS
A12: I. TECHNICAL AND SUPPORT SEVICES PROGRAM | D12: =SUM(D14:D33) -> 6576.133 | F12: =SUM(F14:F33) -> 512.8
A14: - Hauling Truck | B14: Number | C14: 1 | D14: 2000
A15: - Rotary tilling type-hand tractor | B15: Number | C15: 1 | D15: 100
A16: - Direct corn seeder | B16: Number
A17: -Impulse Plastic Bag Sealer | B17: Number | C17: 4 | D17: 40
A18: - Digital Weighing Scale | B18: Number | C18: 2 | D18: 20
A19: - Plastic mulch | B19: roll | C19: 3 | D19: 9.9
A20: - Four wheel tractor (corn) | B20: Number | C20: 1 | D20: 3100
A21: -Multifunction-tiller/cultivator (long foong) | B21: Number | C21: 1 | D21: 350
A22: -Rotary tilling type hand tractor | B22: Number | C22: 1 | D22: 100
A23: - Shredder | B23: Number | C23: 1 | D23: 333.333
A24: - Ready to Lay Chicken | B24: heads | C24: 330 | D24: 250.8
A25: - Poultry Feeds | B25: bags | C25: 66 | D25: 122.1
A26: -Biologics | B26: boxes
A27: -Fruiting bags | B27: bag | C27: =1187*2 -> 2374 | D27: 150
A28: -Assorted vegetables | B28: Number | E28: 154 | F28: 153.84
A29: - Seedling tray | B29: Number | E29: 446 | F29: 38.46
A30: - shading net | B30: Number | E30: 4 | F30: 38.46
A31: -seedling rack | B31: Unit | E31: 4 | F31: 61.54
A32: -Organic Fertilizer | B32: Number | E32: 154 | F32: 153.84
A33: - Portable Thumb Edible Garden Nursery | E33: 2 | F33: 66.66
A34: Provision of Swine | B34: heads | I34: 9 | J34: 90 | K34: 9 | L34: 90 | M34: Cauayan City
A35: Provision of Feeds | B35: bags | I35: 18 | J35: 40 | K35: 18 | L35: 40
A36: Provision of Assorted vegetable seeds | B36: packs | I36: 114 | J36: 114.28 | K36: 114 | L36: 114.28
A37: Provision Inorganic Fertilizer | B37: bags | I37: 50 | J37: 100 | K37: 50 | L37: 100
A38: Provision of Organic Fertilizer | B38: bags | I38: 100 | J38: 100 | K38: 100 | L38: 100
A39: Provision of Assorted vegetable seeds | B39: packs | I39: 200 | J39: 50 | K39: 200 | L39: 50
A40: Provision of Free-Range Chicken | B40: heads | I40: 100 | J40: 70 | K40: 100 | L40: 70
A41: Provision of MungBean | B41: packs | I41: 80 | J41: 8 | K41: 80 | L41: 8
A42: Distribution of Ready-to-Lay Chicken with Battery Cage | B42: heads | I42: 290 | J42: 320.75 | K42: 290 | L42: 320.75
A43: Provision of Feeds | B43: bags | I43: 42 | J43: 75 | K43: 42 | L43: 75
A44: Provision of Biologics | B44: boxes | I44: 50 | J44: 25 | K44: 50 | L44: 25
A45: II. AGRICULTURAL MACHINERY, EQUIPMENT, FACILITIES AND INFRASTRUCTURE PROGRAM
A46: Agricultural Machinery, Equipment and Facilities Support Services Sub-Program
A47: - Four Wheel Drive Tractor | B47: no.
A48: GRAND TOTAL | D48: =D12 -> 6576.133 | F48: =F12 -> 512.8 | H48: 0 | J48: =sum(J34:J44) -> 993.03 | L48: =sum(L34:L44) -> 993.03
A51: Prepared by: | C51: In coordination with: | G51: Concurred by:
A54: BERNADETTE T. GALOSO | C54: MACARIO B. ANDAL, CPA | G54: ROSE MARY G. AQUINO, Ph.D.
A55: Chief, PMED | C55: Chief, Budget Section | G55: Regional Executive Director

Sheet NSHP
A1: DEPARTMENT OF AGRICULTURE-REGIONAL FIELD OFFICE NO. 02
A2: CY 2025 & FY 2026 PROGRAM ACCOMPLISHMENTS/STATUS AND FY 2027 PLAN AND BUDGET PROPOSAL
A3: NATIONAL SOIL HEALTH PROGRAM (NSHP)*
A4: PROVINCE: ISABELA
A5: DISTRICT: VI
A7: PROGRAM/SUBPROGRAM/ INDICATORS | B7: UNIT OF MEASURE | C7: CY 2025 GAA | E7: FY 2026 GAA | G7: FY 2027 PROPOSAL | M7: Remarks (Breakdown of Municipality Target for FY 2027 )
G8: TIER 1 | I8: TIER 2 | K8: TOTAL
C9: ANNUAL PHYSICAL TARGET | D9: ANNUAL BUDGET (₱ '000) | E9: ACCOMPLISHMENT | G9: PHYSICAL TARGET | H9: ANNUAL BUDGET (₱ '000) | I9: PHYSICAL TARGET | J9: ANNUAL BUDGET (₱ '000) | K9: PHYSICAL TARGET | L9: ANNUAL BUDGET (₱ '000)
E10: PHYSICAL TARGET | F10: ANNUAL BUDGET (₱ '000)
A11: National Soil Health Program (Tier II)
A12: I. Operation of Regional Soil Laboratories in support to NSHP Activities
A13: 1.1 Soil Analysis | B13: number of samples | C13: 21 | D13: 280 | E13: 27 | F13: 170
A14: 1.2 Fertilizer Analysis | B14: number of samples | C14: 8 | D14: 34 | E14: 8 | F14: 72
A15: 1.3 Plant Tissue Analysis | B15: number of samples | C15: 10 | D15: 30 | E15: 4 | F15: 72
A16: 1.4 Participation to Proficiency Testing | B16: Number of PT participated | F16: 0
A17: 1.5 STK Production/distribution | B17: number of STK Produced/ distributed | E17: 27 | F17: 39
A18: 1.6 Maintenance of Regulatory/Statutory issuances acquired | B18: number of regulatory/ statutory issuances acquired/ maintained | F18: 0
A20: II. Operation of Mobile Soil Laboratory
A21: 2.1 Soil Chemical Analysis (STK/Chemical) | B21: no. of sample analyzed | E21: 165 | F21: 116
A22: 2.2. Soil Physical Analysis | B22: no. of sample analyzed | E22: 25 | F22: 109
A23: 2.3 Soil Microbiological Analysis | B23: no. of sample analyzed | E23: 25 | F23: 109
A24: 2.4 Distribution of Soil Health card | B24: no. of Soil Health Card distributed | E24: 165 | F24: 54
A25: 2.5 Trainings conducted | B25: no. of training conducted
A26: GRAND TOTAL | D26: =SUM(D13:D25) -> 344 | F26: =SUM(F13:F25) -> 741 | H26: 0 | J26: 0 | L26: 0
A27: *Program Implementation will only start on FY 2025
A30: Prepared by: | B30: In coordination with: | F30: Concurred by:
A33: BERNADETTE T. GALOSO | B33: MACARIO B. ANDAL, CPA | F33: ROSE MARY G. AQUINO, Ph.D.
A34: Chief, PMED | B34: Chief, Budget Section | F34: Regional Executive Director

Sheet PRDP
A1: DEPARTMENT OF AGRICULTURE-REGIONAL FIELD OFFICE NO. 02
A2: CY 2025 & FY 2026 PROGRAM ACCOMPLISHMENTS/STATUS AND FY 2027 PLAN AND BUDGET PROPOSAL
A3: PHILIPPINE RURAL DEVELOPMENT PROJECT*
A4: PROVINCE: ISABELA
A5: DISTRICT: VI
A7: MUNICIPALITY | B7: LOCATION (BARANGAY) | C7: NAME OF PROJECTS | D7: ESTIMATED LENGTH (KM) | E7: ESTIMATED AMOUNT (₱ '000)
A8: CY 2026 PIPELINED/PROPOSAL
A9: Echague | B9: Villa Rey, San Carlos | C9: Rehabilitation/Concreting of Villa Rey-San Carlos FMR | D9: 16.13 | E9: =284726000/1000 -> 284726
A10: San Isidro | B10: Gomez | C10: Construction of San Isidro Warehouse with Solar Dryer | D10: 1084.4 sq.m. | E10: =15000000/1000 -> 15000
A11: Cauayan City | B11: San Pablo | C11: Construction of Cauayan City Warehouse | D11: 1084.4 sq.m. | E11: =15000000/1000 -> 15000
A13: TOTAL | D13: =SUM(D8:D10) -> 16.13 | E13: =SUM(E8:E11) -> 314726
A15: Prepared by: | C15: In coordination with: | E15: Concurred by:
A18: BERNADETTE T. GALOSO | C18: MACARIO B. ANDAL, CPA | E18: ROSE MARY G. AQUINO, Ph.D.
A19: Chief, PMED | C19: Chief, Budget Section | E19: Regional Executive Director

Sheet GRAND TOTAL
A2: CY 2024, 2025 AND FY 2026 BUDGET SUMMARY (₱ '000)
A3: REGION 02
A4: ISABELA PROVINCE
A5: DISTRICT VI
A8: PROGRAM/PROJECT FUND SOURCE | B8: CY 2025 GAA | C8: FY 2026 GAA | D8: FY 2027 PROPOSAL | G8: Variance | H8: % Change (Increase/Decrease)
D9: TIER I | E9: TIER II | F9: TOTAL
A10: National Rice Program | B10: =RICE!D53 -> 140386.48 | C10: =RICE!F53 -> 253198.79 | D10: =RICE!H53 -> 279999.13 | E10: =RICE!J53 -> 113200.65 | F10: =D10+E10 -> 393199.78
A11: National Corn Program | B11: =CORN!D82 -> 79281.5 | C11: =CORN!H82 -> 185703.92 | D11: =CORN!J82 -> 187569.67 | E11: =CORN!L82 -> 154954.4 | F11: =D11+E11 -> 342524.07
A12: National High Value Crops Development Program | B12: =HVCDP!D801 -> 3100.09 | C12: 300 | D12: =HVCDP!H801 -> 1862.6545 | F12: =D12+E12 -> 1862.6545
A13: National Urban and Peri-Urban Agriculture Program | B13: 155 | C13: 2792 | D13: =NUPAP!H50 -> 0 | F13: =D13+E13 -> 0
A14: HALAL Food Industry Development Program | B14: =HALAL!D25 -> 200 | C14: =HALAL!F25 -> 125 | F14: =D14+E14 -> 0
A15: National Livestock Program | B15: =LIVESTOCK!D45 -> 10779.6 | C15: 2869.6 | D15: =LIVESTOCK!J45 -> 13885 | E15: =LIVESTOCK!L45 -> 0 | F15: =D15+E15 -> 13885
A16: Locally Funded Projects | F16: =D16+E16 -> 0
A17: Farm-to-Market Road (FMR) Development Program | B17: =FMR!E61 -> 85000 | C17: =FMR!E101 -> 549400 | D17: =FMR!E108 -> 155000 | E17: =FMR!E118 -> 192500 | F17: =D17+E17 -> 347500
A18: Special Area for Agricultural Development (SAAD) Program | B18: =SAAD!D47 -> 2866 | C18: 3285 | D18: =SAAD!H47 -> 2107 | E18: =SAAD!J47 -> 0 | F18: =D18+E18 -> 2107
A19: Mainstreaming Climate Resilient Agriculture (MCRA) to the Regional Programs & Projects | B19: =MCRA!D48 -> 6576.133 | C19: =MCRA!F48 -> 512.8 | D19: =MCRA!H48 -> 0 | E19: =MCRA!J48 -> 993.03 | F19: =D19+E19 -> 993.03
A20: National Soil Health Program | B20: 344 | C20: 741 | F20: =D20+E20 -> 0
A21: Foreign Assisted Project | F21: =D21+E21 -> 0
A22: Philippine Rural Development Project | C22: =PRDP!E13 -> 314726 | F22: =D22+E22 -> 0
A23: TOTAL | B23: =SUM(B4:B22) -> 328688.8 | C23: =SUM(C4:C22) -> 1313654.1 | D23: =SUM(D4:D22) -> 640423.45 | E23: =SUM(E4:E22) -> 461648.08 | F23: =D23+E23 -> 1102071.5 | G23: =F23-C23 -> -211582.59
A25: Prepared by:
A28: BERNADETTE T. GALOSO
A29: Chief, PMED
