Workbook
Name ABRA: OU!$A$38:$A$64
Name AGUSAN_DEL_NORTE: OU!$BX$38:$BX$49
Name AGUSAN_DEL_SUR: OU!$BY$38:$BY$51
Name AKLAN: OU!$AN$38:$AN$54
Name ALBAY: OU!$AH$38:$AH$55
Name ANTIQUE: OU!$AO$38:$AO$55
Name APAYAO: OU!$B$38:$B$44
Name ATI: OU!$Q$3
Name AURORA: OU!$Q$38:$Q$45
Name BAGUIO_CITY: OU!$G$38
Name BAR: OU!$R$3
Name BATAAN: OU!$R$38:$R$49
Name BATANES: OU!$L$38:$L$43
Name BATANGAS: OU!$X$38:$X$71
Name BENGUET: OU!$C$38:$C$50
Name BILIRAN: OU!$AX$38:$AX$45
Name BOHOL: OU!$AT$38:$AT$85
Name BPI: OU!$S$3
Name BSWM: OU!$T$3
Name BUKIDNON: OU!$BI$38:$BI$59
Name BULACAN: OU!$S$38:$S$61
Name BUTUAN_CITY: OU!$CC$38
Name CAGAYAN: OU!$M$38:$M$66
Name CAMARINES_NORTE: OU!$AI$38:$AI$49
Name CAMARINES_SUR: OU!$AJ$38:$AJ$74
Name CAMIGUIN: OU!$BJ$38:$BJ$42
Name CAPIZ: OU!$AP$38:$AP$54
Name CAR: OU!$A$3:$A$10
Name Cassava: PAPbyCommodity!$C$3:$C$7
Name Cassava_AMEFSS: PAPbyCommodity!$E$64:$E$85
Name Cassava_ESETS: PAPbyCommodity!$C$64:$C$74
Name Cassava_INS: PAPbyCommodity!$F$64:$F$69
Name Cassava_PSS: PAPbyCommodity!$B$64:$B$69
Name Cassava_RND: PAPbyCommodity!$D$64:$D$88
Name CATANDUANES: OU!$AK$38:$AK$48
Name CAVITE: OU!$Y$38:$Y$60
Name CEBU: OU!$AU$38:$AU$90
Name Corn: PAPbyCommodity!$B$3:$B$7
Name Corn_AMEFSS: PAPbyCommodity!$E$10:$E$63
Name Corn_ESETS: PAPbyCommodity!$C$10:$C$57
Name Corn_INS: PAPbyCommodity!$F$10:$F$21
Name Corn_PSS: PAPbyCommodity!$B$10:$B$42
Name Corn_RND: PAPbyCommodity!$D$10:$D$39
Name DAVAO_CITY: OU!$BR$38
Name DAVAO_DE_ORO: OU!$BQ$38:$BQ$48
Name DAVAO_DEL_NORTE: OU!$BN$38:$BN$48
Name DAVAO_DEL_SUR: OU!$BO$38:$BO$47
Name DAVAO_OCCIDENTAL: OU!$BS$38:$BS$42
Name DAVAO_ORIENTAL: OU!$BP$38:$BP$48
Name DINAGAT_ISLANDS: OU!$BZ$38:$BZ$44
Name DISTRICT: DISTRICT!$A$2:$H$1744
Name EASTERN_SAMAR: OU!$AY$38:$AY$63
Name GUIMARAS: OU!$AQ$38:$AQ$42
Name IFUGAO: OU!$D$38:$D$48
Name ILOCOS_NORTE: OU!$H$38:$H$60
Name ILOCOS_SUR: OU!$I$38:$I$71
Name ILOILO: OU!$AR$38:$AR$81
Name ISABELA: OU!$N$38:$N$74
Name ISABELA_CITY: OU!$BH$38
Name KALINGA: OU!$E$38:$E$45

Sheet PICS
B1: FY 2025 PLAN AND BUDGET PROPOSAL
B2: BASED ON NATIONAL EXPENDITURE PROGRAM (NEP)
B3: BED 2: PHYSICAL
B4: NAME OF OU | C4: ='CAPTURE SHEET - PHYSICAL'!C2 -> RFOII
B5: PRPOPOSAL/BEDS | C5: BED 2 - PHYSICAL
A6: 1 | B6: 2 | C6: 3 | D6: 4 | E6: 5 | F6: 6 | G6: 7 | H6: 8 | I6: 9 | J6: 10 | K6: 11 | L6: 12 | M6: 13 | N6: 14 | O6: 15 | P6: 16 | Q6: 17 | R6: 18 | S6: 19 | T6: 20 | U6: 21 | V6: 22 | W6: 23 | X6: 24
E7: QUARTER | F7: Values
E8: 1ST QTR | F8: 1ST QTR | G8: 1ST QTR | H8: 1ST QTR | I8: 1ST QTR | J8: 2ND QTR | K8: 2ND QTR | L8: 2ND QTR | M8: 2ND QTR | N8: 2ND QTR | O8: 3RD QTR | P8: 3RD QTR | Q8: 3RD QTR | R8: 3RD QTR | S8: 3RD QTR | T8: 4TH QTR | U8: 4TH QTR | V8: 4TH QTR | W8: 4TH QTR | X8: 4TH QTR
B9: PREXC SUB-PROGRAM | C9: PROVINCE | D9: ACTIVITY | E9: PHYSICAL TARGET | F9: GROUP BENEF | G9: Sum of FEMALE BENEFICIARIES | H9: Sum of MALE BENEFICIARIES | I9: ALLOCATION (Php'000) | J9: PHYSICAL TARGET | K9: GROUP BENEF | L9: Sum of FEMALE BENEFICIARIES | M9: Sum of MALE BENEFICIARIES | N9: ALLOCATION (Php'000) | O9: PHYSICAL TARGET | P9: GROUP BENEF | Q9: Sum of FEMALE BENEFICIARIES | R9: Sum of MALE BENEFICIARIES | S9: ALLOCATION (Php'000) | T9: PHYSICAL TARGET | U9: GROUP BENEF | V9: Sum of FEMALE BENEFICIARIES | W9: Sum of MALE BENEFICIARIES | X9: ALLOCATION (Php'000)
B10: PSS | E10: 3500 | F10: 2 | I10: 163 | J10: 1465794 | K10: 29 | N10: 268793 | O10: 8596967 | P10: 202 | S10: 508173.25 | T10: 835951 | U10: 22 | X10: 11310.75
A11: Cagayan | B11: PSS | C11: Cagayan
A12: CagayanSeed Production - White Corn Registered Seeds | B12: PSS | C12: Cagayan | D12: Seed Production - White Corn Registered Seeds | J12: 3000 | K12: 8 | N12: 150.5 | O12: 1000 | P12: 2 | S12: 50.5 | T12: 2000 | X12: 100
A13: CagayanRCPT - Yellow Corn seeds | B13: PSS | C13: Cagayan | D13: RCPT - Yellow Corn seeds | O13: 9000 | P13: 2 | S13: 6000
A14: CagayanRCPT - Inorganic fertilizer for YC seeds | B14: PSS | C14: Cagayan | D14: RCPT - Inorganic fertilizer for YC seeds | O14: 275000 | P14: 2 | S14: 12375
A15: CagayanBiofertilizer | B15: PSS | C15: Cagayan | D15: Biofertilizer | O15: 2000 | P15: 2 | S15: 1360
A16: CagayanSoil Ameliorant | B16: PSS | C16: Cagayan | D16: Soil Ameliorant | O16: 250000 | P16: 2 | S16: 5000
A17: CagayanYCPEP - Yellow Corn Hybrid seeds | B17: PSS | C17: Cagayan | D17: YCPEP - Yellow Corn Hybrid seeds | O17: 125010 | P17: 25 | S17: 83340
A18: CagayanYCPEP - Inorganic fertilizer for YC Hybrid seeds | B18: PSS | C18: Cagayan | D18: YCPEP - Inorganic fertilizer for YC Hybrid seeds | O18: 694500 | P18: 25 | S18: 31252.5
A19: CagayanCassava Production (seed pieces) | B19: PSS | C19: Cagayan | D19: Cassava Production (seed pieces) | O19: 130000 | P19: 3 | S19: 130
A20: CagayanCassava Procurement (seed pieces) | B20: PSS | C20: Cagayan | D20: Cassava Procurement (seed pieces) | O20: 240000 | P20: 2 | S20: 360
A21: CagayanInorganic fertilizer for Cassava | B21: PSS | C21: Cagayan | D21: Inorganic fertilizer for Cassava | O21: 3700 | P21: 5 | S21: 166.5
A22: Isabela | B22: PSS | C22: Isabela
A23: IsabelaSeed Production - White Corn Registered Seeds | B23: PSS | C23: Isabela | D23: Seed Production - White Corn Registered Seeds | J23: 4000 | K23: 13 | N23: 201 | T23: 4000 | U23: 4 | X23: 201
A24: IsabelaRCPT - Yellow Corn seeds | B24: PSS | C24: Isabela | D24: RCPT - Yellow Corn seeds | O24: 9000 | P24: 2 | S24: 6000
A25: IsabelaRCPT - Inorganic fertilizer for YC seeds | B25: PSS | C25: Isabela | D25: RCPT - Inorganic fertilizer for YC seeds | O25: 275000 | P25: 2 | S25: 12375
A26: IsabelaBiofertilizer | B26: PSS | C26: Isabela | D26: Biofertilizer | O26: 2000 | P26: 2 | S26: 1360
A27: IsabelaSoil Ameliorant | B27: PSS | C27: Isabela | D27: Soil Ameliorant | O27: 250000 | P27: 2 | S27: 5000
A28: IsabelaYCPEP - Yellow Corn Hybrid seeds | B28: PSS | C28: Isabela | D28: YCPEP - Yellow Corn Hybrid seeds | O28: 301140 | P28: 35 | S28: 200760
A29: IsabelaYCPEP - Inorganic fertilizer for YC Hybrid seeds | B29: PSS | C29: Isabela | D29: YCPEP - Inorganic fertilizer for YC Hybrid seeds | O29: 1673000 | P29: 35 | S29: 75285
A30: IsabelaCassava Production (seed pieces) | B30: PSS | C30: Isabela | D30: Cassava Production (seed pieces) | J30: 255000 | K30: 2 | N30: 255 | O30: 200000 | P30: 1 | S30: 200
A31: IsabelaCassava Procurement (seed pieces) | B31: PSS | C31: Isabela | D31: Cassava Procurement (seed pieces) | J31: 730000 | K31: 2 | N31: 1095 | O31: 2450000 | P31: 6 | S31: 3675 | T31: 500000 | U31: 1 | X31: 750
A32: IsabelaInorganic fertilizer for Cassava | B32: PSS | C32: Isabela | D32: Inorganic fertilizer for Cassava | J32: 9900 | K32: 4 | N32: 445.5 | O32: 26500 | P32: 7 | S32: 1192.5 | T32: 5000 | U32: 1 | X32: 225
A33: IsabelaSeed Procurement - Sorghum | B33: PSS | C33: Isabela | D33: Seed Procurement - Sorghum | T33: 20000 | U33: 1 | X33: 1750
A34: IsabelaInorganic fertilizer for Sorghum | B34: PSS | C34: Isabela | D34: Inorganic fertilizer for Sorghum | T34: 100000 | U34: 1 | X34: 4500
A35: IsabelaSeed Production - Soybean | B35: PSS | C35: Isabela | D35: Seed Production - Soybean | E35: 1000 | F35: 1 | I35: 50
A36: IsabelaInorganic fertilizer for Soybean | B36: PSS | C36: Isabela | D36: Inorganic fertilizer for Soybean | E36: 2500 | F36: 1 | I36: 113
A37: Nueva Vizcaya | B37: PSS | C37: Nueva_Vizcaya
A38: Nueva VizcayaSeed Production - White Corn Registered Seeds | B38: PSS | C38: Nueva_Vizcaya | D38: Seed Production - White Corn Registered Seeds | T38: 4000 | U38: 6 | X38: 201
A39: Nueva VizcayaYCPEP - Yellow Corn Hybrid seeds | B39: PSS | C39: Nueva_Vizcaya | D39: YCPEP - Yellow Corn Hybrid seeds | O39: 16200 | P39: 10 | S39: 10800
A40: Nueva VizcayaYCPEP - Inorganic fertilizer for YC Hybrid seeds | B40: PSS | C40: Nueva_Vizcaya | D40: YCPEP - Inorganic fertilizer for YC Hybrid seeds | O40: 90000 | P40: 10 | S40: 4050
A41: Nueva VizcayaCassava Production (seed pieces) | B41: PSS | C41: Nueva_Vizcaya | D41: Cassava Production (seed pieces) | T41: 195000 | U41: 1 | X41: 195
A42: Nueva VizcayaCassava Procurement (seed pieces) | B42: PSS | C42: Nueva_Vizcaya | D42: Cassava Procurement (seed pieces) | O42: 100000 | P42: 1 | S42: 150
A43: Nueva VizcayaInorganic fertilizer for Cassava | B43: PSS | C43: Nueva_Vizcaya | D43: Inorganic fertilizer for Cassava | O43: 1000 | P43: 1 | S43: 45 | T43: 1950 | U43: 1 | X43: 87.75
A44: Quirino | B44: PSS | C44: Quirino
A45: QuirinoSeed Production - White Corn Registered Seeds | B45: PSS | C45: Quirino | D45: Seed Production - White Corn Registered Seeds | T45: 4000 | U45: 6 | X45: 201
A46: QuirinoYCPEP - Yellow Corn Hybrid seeds | B46: PSS | C46: Quirino | D46: YCPEP - Yellow Corn Hybrid seeds | O46: 43650 | P46: 6 | S46: 29100
A47: QuirinoYCPEP - Inorganic fertilizer for YC Hybrid seeds | B47: PSS | C47: Quirino | D47: YCPEP - Inorganic fertilizer for YC Hybrid seeds | O47: 242500 | P47: 6 | S47: 10912.5
A48: QuirinoCassava Production (seed pieces) | B48: PSS | C48: Quirino | D48: Cassava Production (seed pieces) | O48: 195000 | P48: 1 | S48: 195
A49: QuirinoCassava Procurement (seed pieces) | B49: PSS | C49: Quirino | D49: Cassava Procurement (seed pieces) | O49: 980000 | P49: 2 | S49: 1470
A50: QuirinoInorganic fertilizer for Cassava | B50: PSS | C50: Quirino | D50: Inorganic fertilizer for Cassava | O50: 11750 | P50: 3 | S50: 528.75
A51: Regional Office | B51: PSS | C51: Regional_Office
A52: Regional OfficeDRRM - White Corn Seed Procured OPV | B52: PSS | C52: Regional_Office | D52: DRRM - White Corn Seed Procured OPV | J52: 15000 | N52: 1500
A53: Regional OfficeDRRM - Yellow Corn Seed Procured OPV | B53: PSS | C53: Regional_Office | D53: DRRM - Yellow Corn Seed Procured OPV | J53: 3000 | N53: 300
A54: Regional OfficeDRRM - Yellow Corn Seed Procured Hybrid | B54: PSS | C54: Regional_Office | D54: DRRM - Yellow Corn Seed Procured Hybrid | J54: 375894 | N54: 250596
A55: Regional OfficeDRRM - Agricultural chemicals (Insecticide in liters) | B55: PSS | C55: Regional_Office | D55: DRRM - Agricultural chemicals (Insecticide in liters) | J55: 5000 | N55: 6000
A56: Regional OfficeDRRM - Agricultural chemicals (Rodenticides) | B56: PSS | C56: Regional_Office | D56: DRRM - Agricultural chemicals (Rodenticides) | J56: 50000 | N56: 1500
A57: Regional OfficeDRRM - Agricultural chemicals (Pheromone lure) | B57: PSS | C57: Regional_Office | D57: DRRM - Agricultural chemicals (Pheromone lure) | J57: 5000 | N57: 2750
A58: Regional OfficeDRRM - Agricultural chemicals (Streptomycin) | B58: PSS | C58: Regional_Office | D58: DRRM - Agricultural chemicals (Streptomycin) | J58: 10000 | N58: 4000
A59: Regional OfficeDA Stations - Hand tractor with corn planter | B59: PSS | C59: Regional_Office | D59: DA Stations - Hand tractor with corn planter | O59: 4 | S59: 1200
A60: Regional OfficeDA Stations - Silage Chopper | B60: PSS | C60: Regional_Office | D60: DA Stations - Silage Chopper | O60: 4 | S60: 240
A61: Regional OfficeDA Stations - Corn Mill | B61: PSS | C61: Regional_Office | D61: DA Stations - Corn Mill | O61: 4 | S61: 1200
A62: Regional OfficeDA Stations - Pelletizing Machine | B62: PSS | C62: Regional_Office | D62: DA Stations - Pelletizing Machine | O62: 4 | S62: 300
A63: Regional OfficeDA Stations - Light Cargo Truck | B63: PSS | C63: Regional_Office | D63: DA Stations - Light Cargo Truck | O63: 1 | S63: 2100
A64: Regional OfficeDA Stations - Four-wheel Tractor (90 hp min) | B64: PSS | C64: Regional_Office | D64: DA Stations - Four-wheel Tractor (90 hp min) | T64: 1 | X64: 3100
B65: ESETS | E65: 210 | G65: 30 | H65: 120 | I65: 975 | J65: 3024 | L65: 246 | M65: 264 | N65: 5285 | O65: 6214 | Q65: 108 | R65: 252 | S65: 1550 | T65: 2194 | V65: 12 | W65: 78 | X65: 9346
A66: Cagayan | B66: ESETS | C66: Cagayan
A67: CagayanModel Farm - Cassava (sites) | B67: ESETS | C67: Cagayan | D67: Model Farm - Cassava (sites) | O67: 1 | S67: 650
A68: CagayanSupport to LGU Extension Workers Incentives - Provincial Coordinator | B68: ESETS | C68: Cagayan | D68: Support to LGU Extension Workers Incentives - Provincial Coordinator | T68: 1 | X68: 48
A69: CagayanSupport to LGU Extension Workers Incentives - Municipal Agriculturist | B69: ESETS | C69: Cagayan | D69: Support to LGU Extension Workers Incentives - Municipal Agriculturist | T69: 3 | X69: 144
A70: CagayanSupport to LGU Extension Workers Incentives - Agricultural Extension Worker | B70: ESETS | C70: Cagayan | D70: Support to LGU Extension Workers Incentives - Agricultural Extension Worker | T70: 53 | X70: 2226
A71: Isabela | B71: ESETS | C71: Isabela
A72: IsabelaModel Farm - Sorghum (sites) | B72: ESETS | C72: Isabela | D72: Model Farm - Sorghum (sites) | T72: 1 | X72: 280
A73: IsabelaTechno-Demo Sorghum (sites) | B73: ESETS | C73: Isabela | D73: Techno-Demo Sorghum (sites) | T73: 4 | X73: 160
A74: IsabelaModel Farm - Soybean (sites) | B74: ESETS | C74: Isabela | D74: Model Farm - Soybean (sites) | E74: 1 | I74: 330
A75: IsabelaTechno-Demo Soybean (sites) | B75: ESETS | C75: Isabela | D75: Techno-Demo Soybean (sites) | E75: 1 | I75: 200
A76: IsabelaSupport to LGU Extension Workers Incentives - Provincial Coordinator | B76: ESETS | C76: Isabela | D76: Support to LGU Extension Workers Incentives - Provincial Coordinator | T76: 1 | X76: 48
A77: IsabelaSupport to LGU Extension Workers Incentives - Municipal Agriculturist | B77: ESETS | C77: Isabela | D77: Support to LGU Extension Workers Incentives - Municipal Agriculturist | T77: 8 | X77: 384
A78: IsabelaSupport to LGU Extension Workers Incentives - Agricultural Extension Worker | B78: ESETS | C78: Isabela | D78: Support to LGU Extension Workers Incentives - Agricultural Extension Worker | T78: 63 | X78: 2646
A79: Nueva Vizcaya | B79: ESETS | C79: Nueva_Vizcaya
A80: Nueva VizcayaSupport to LGU Extension Workers Incentives - Provincial Coordinator | B80: ESETS | C80: Nueva_Vizcaya | D80: Support to LGU Extension Workers Incentives - Provincial Coordinator | T80: 1 | X80: 48
A81: Nueva VizcayaSupport to LGU Extension Workers Incentives - Agricultural Extension Worker | B81: ESETS | C81: Nueva_Vizcaya | D81: Support to LGU Extension Workers Incentives - Agricultural Extension Worker | T81: 22 | X81: 924
A82: Quirino | B82: ESETS | C82: Quirino
A83: QuirinoSustainable Land Management in Corn-based Sloping Areas (SLM-Corn) | B83: ESETS | C83: Quirino | D83: Sustainable Land Management in Corn-based Sloping Areas (SLM-Corn) | J83: 1 | N83: 3000
A84: QuirinoSupport to LGU Extension Workers Incentives - Provincial Coordinator | B84: ESETS | C84: Quirino | D84: Support to LGU Extension Workers Incentives - Provincial Coordinator | T84: 1 | X84: 48
A85: QuirinoSupport to LGU Extension Workers Incentives - Municipal Agriculturist | B85: ESETS | C85: Quirino | D85: Support to LGU Extension Workers Incentives - Municipal Agriculturist | T85: 1 | X85: 48
A86: QuirinoSupport to LGU Extension Workers Incentives - Agricultural Extension Worker | B86: ESETS | C86: Quirino | D86: Support to LGU Extension Workers Incentives - Agricultural Extension Worker | T86: 31 | X86: 1302
A87: Regional Office | B87: ESETS | C87: Regional_Office
A88: Regional OfficeEstablishment of Corn Derby | B88: ESETS | C88: Regional_Office | D88: Establishment of Corn Derby | J88: 1 | N88: 1000
A89: Regional OfficeTraining - Clientele-based - Corn Cluster Development training | B89: ESETS | C89: Regional_Office | D89: Training - Clientele-based - Corn Cluster Development training | E89: 1 | G89: 6 | H89: 24 | I89: 35 | J89: 3 | L89: 18 | M89: 72 | N89: 105 | O89: 2 | Q89: 12 | R89: 48 | S89: 70
A90: Regional OfficeTraining - Clientele-based - Corn Livelihood training | B90: ESETS | C90: Regional_Office | D90: Training - Clientele-based - Corn Livelihood training | J90: 3 | L90: 90 | N90: 150 | O90: 1 | Q90: 30 | S90: 50
A91: Regional OfficeTraining - Clientele-based - Corn Production Training | B91: ESETS | C91: Regional_Office | D91: Training - Clientele-based - Corn Production Training | J91: 3 | L91: 18 | M91: 72 | N91: 105 | O91: 1 | Q91: 6 | R91: 24 | S91: 35
A92: Regional OfficeTraining - Clientele-based - Integrated Pest Management Training | B92: ESETS | C92: Regional_Office | D92: Training - Clientele-based - Integrated Pest Management Training | J92: 2 | L92: 12 | M92: 48 | N92: 200 | T92: 2 | V92: 12 | W92: 48 | X92: 200
A93: Regional OfficeTraining - Clientele-based - Training on Operation and Maintenance of Farm Machinery and Equipment | B93: ESETS | C93: Regional_Office | D93: Training - Clientele-based - Training on Operation and Maintenance of Farm Machinery and Equipment | O93: 2 | R93: 60 | S93: 200 | T93: 1 | W93: 30 | X93: 100
A94: Regional OfficeAdvocacy and Information Materials - IEC Materials Yellow Corn | B94: ESETS | C94: Regional_Office | D94: Advocacy and Information Materials - IEC Materials Yellow Corn | J94: 3000 | N94: 100 | O94: 3000 | S94: 100
A95: Regional OfficeTraining - Clientele-based - Cassava Livelihood training | B95: ESETS | C95: Regional_Office | D95: Training - Clientele-based - Cassava Livelihood training | J95: 3 | L95: 90 | N95: 150 | O95: 1 | Q95: 30 | S95: 50
A96: Regional OfficeTraining - Clientele-based - Cassava Production Training | B96: ESETS | C96: Regional_Office | D96: Training - Clientele-based - Cassava Production Training | J96: 3 | L96: 18 | M96: 72 | N96: 105 | O96: 1 | Q96: 6 | R96: 24 | S96: 35
A97: Regional OfficeAdvocacy and Information Materials - IEC Materials Cassava | B97: ESETS | C97: Regional_Office | D97: Advocacy and Information Materials - IEC Materials Cassava | O97: 3000 | S97: 90 | T97: 2000 | X97: 60
A98: Regional OfficeTraining - Clientele-based - Sorghum Production Training | B98: ESETS | C98: Regional_Office | D98: Training - Clientele-based - Sorghum Production Training | O98: 4 | Q98: 24 | R98: 96 | S98: 140
A99: Regional OfficeAdvocacy and Information Materials - IEC Materials Sorghum | B99: ESETS | C99: Regional_Office | D99: Advocacy and Information Materials - IEC Materials Sorghum | O99: 200 | S99: 50
A100: Regional OfficeTraining - Clientele-based - Soybean Production Training | B100: ESETS | C100: Regional_Office | D100: Training - Clientele-based - Soybean Production Training | E100: 4 | G100: 24 | H100: 96 | I100: 140
...

Sheet HOW TO FILL OUT
A1: A. CAPTURE SHEET - FINANCIAL
A2: COLUMNS | B2: INSTRUCTIONS
A3: PRPOPOSAL/BEDS | B3: Select BED 1 for obligation and BED 3 for disbursement
A4: OU | B4: Select your respective OUs name
A5: SPECIFIC COMMODITY | B5: Select appropriate commodity to activate dropdown list for the "COMMODITY PREXC SUBPROGRAM" column.
A6: COMMODITY PREXC SUB-PROGRAM | B6: Select appropriate PREXC subprogram to activate the PAP list in the ACTIVITY column
A7: ACTIVITY | B7: Select target activity
A8: TAG- GAD | B8: Select "YES" for activities to be committed as GAD budget (total GAD budget should be at least 5% of the total budget of the OU)
A9: MONTH | B9: Select target month of obligation or disbursement
A10: MOOE (Php '000) | B10: Input corresponding MOOE budget for the activity. Should be a whole number and the same with the submitted BP 201 and BED 2 input
A11: CO (Php '000) | B11: Input corresponding CO budget for the activity. Should be a whole number and the same with the submitted BP 201 and BED 2 input
A14: B. CAPTURE SHEET - PHYSICAL
A15: Inputting for this capture sheet is per cluster beneficiary for PSS, AMEFSS, and INS PAPs
A16: COLUMNS | B16: INSTRUCTIONS
A17: PRPOPOSAL/BEDS | B17: Select BED 2 - Physical
A18: OU | B18: Select your respective OUs name to activate the list of provinces
A19: CLUSTER BENEFICIARY | B19: Input name of cluster beneficiary. One name per row. Do not put multiple names
A20: PROVINCE | B20: Select target province
A21: MUNICIPALITY | B21: Select target municipality
A22: SPECIFIC COMMODITY | B22: Select appropriate commodity to activate dropdown list for the "COMMODITY PREXC SUBPROGRAM" column.
A23: COMMODITY PREXC SUB-PROGRAM | B23: Select appropriate PREXC subprogram to activate the PAP list in the ACTIVITY column
A24: ACTIVITY | B24: Select target activity
A25: TAG-GAD | B25: Select "YES" for activities to be committed as GAD budget (total GAD budget should be at least 5% of the total budget of the OU)
A26: MONTH | B26: Select target month for accomplishment of PAP
A27: TARGET | B27: Input quantity
... A34: GROUP BENEFICIARIES | B34: Input "1" since the inputting will be per cluster beneficiaries
A37: C. DATA GENERATION
A38: 1. Click any of the green sheets (BED 1 and 3 Summary and BED 2 Summary).
A39: 2. On the Toolbar, click Data.
A40: 3. On the Data Tab, click Refresh All to update the generated data in the green sheets.
A42: D. DATA REVIEW/ CHECKING
A43: for BED13 Checking and BED13 vs BED2 sheets
A44: 1. Click any of the orange sheets (BED13 Checking and BED13 vs BED2 sheets).
A45: 2. On the Toolbar, click Data.
A46: 3. On the Data Tab, click Refresh All to update the generated data in the pivot table.
A47: 4. After refreshing the data:
A48: - In BED13 Checking, compare or check if the amount inputted per expense class (MOOE/CO) in BED 1 is tally with the BED 3. Also, check if the budget inputted per PAP is correct.
A49: - In BED2 Checking, check if your inputted physical targets is correct
A50: - In BED13 vs BED2 checking, compare or check if the amount inputted per PAP in BED 2 is tally with the inputted amount in BEDs1 and 3.

Sheet BED 1
A1: CY 2025 PLAN AND BUDGET PROPOSAL
A2: BASED ON GENERAL APPROPRIATIONS ACT (GAA)
A3: BED 1 OBLIGATION
D5: PROPOSAL/BEDS | E5: YEAR | F5: QUARTER | G5: MONTH | H5: Values
D6: BED 1 - OBLIGATION | BC6: BED 1 - OBLIGATION MOOE | BD6: BED 1 - OBLIGATION CO | BE6: BED 1 - OBLIGATION TOTAL | BF6: BED 3 - DISBURSEMENT | DQ6: BED 3 - DISBURSEMENT MOOE | DR6: BED 3 - DISBURSEMENT CO | DS6: BED 3 - DISBURSEMENT TOTAL
D7: 2025 | AZ7: 2025 MOOE | BA7: 2025 CO | BB7: 2025 TOTAL | BF7: 2025 | CY7: 2025 MOOE | CZ7: 2025 CO | DA7: 2025 TOTAL | DB7: 2026 | DN7: 2026 MOOE | DO7: 2026 CO | DP7: 2026 TOTAL
D8: 1ST QTR | M8: 1ST QTR MOOE | N8: 1ST QTR CO | O8: 1ST QTR TOTAL | P8: 2ND QTR | Y8: 2ND QTR MOOE | Z8: 2ND QTR CO | AA8: 2ND QTR TOTAL | AB8: 3RD QTR | AK8: 3RD QTR MOOE | AL8: 3RD QTR CO | AM8: 3RD QTR TOTAL | AN8: 4TH QTR | AW8: 4TH QTR MOOE | AX8: 4TH QTR CO | AY8: 4TH QTR TOTAL | BF8: 1ST QTR | BL8: 1ST QTR MOOE | BM8: 1ST QTR CO | BN8: 1ST QTR TOTAL | BO8: 2ND QTR | BX8: 2ND QTR MOOE | BY8: 2ND QTR CO | BZ8: 2ND QTR TOTAL | CA8: 3RD QTR | CJ8: 3RD QTR MOOE | CK8: 3RD QTR CO | CL8: 3RD QTR TOTAL | CM8: 4TH QTR | CV8: 4TH QTR MOOE | CW8: 4TH QTR CO | CX8: 4TH QTR TOTAL | DB8: 1ST QTR 2026 | DK8: 1ST QTR 2026 MOOE | DL8: 1ST QTR 2026 CO | DM8: 1ST QTR 2026 TOTAL
D9: JANUARY | G9: FEBRUARY | J9: MARCH | P9: APRIL | S9: MAY | V9: JUNE | AB9: JULY | AE9: AUGUST | AH9: SEPTEMBER | AN9: OCTOBER | AQ9: NOVEMBER | AT9: DECEMBER | BF9: FEBRUARY | BI9: MARCH | BO9: APRIL | BR9: MAY | BU9: JUNE | CA9: JULY | CD9: AUGUST | CG9: SEPTEMBER | CM9: OCTOBER | CP9: NOVEMBER | CS9: DECEMBER | DB9: FEBRUARY 2026 | DE9: JANUARY 2026 | DH9: MARCH 2026
A10: PREXC SUB-PROGRAM | B10: STRATEGY | C10: ACTIVITY | D10: MOOE | E10: CO | F10: TOTAL | G10: MOOE | H10: CO | I10: TOTAL | J10: MOOE | K10: CO | L10: TOTAL | P10: MOOE | Q10: CO | R10: TOTAL | S10: MOOE | T10: CO | U10: TOTAL | V10: MOOE | W10: CO | X10: TOTAL | AB10: MOOE | AC10: CO | AD10: TOTAL | AE10: MOOE | AF10: CO | AG10: TOTAL | AH10: MOOE | AI10: CO | AJ10: TOTAL | AN10: MOOE | AO10: CO | AP10: TOTAL | AQ10: MOOE | AR10: CO | AS10: TOTAL | AT10: MOOE | AU10: CO | AV10: TOTAL | BF10: MOOE | BG10: CO | BH10: TOTAL | BI10: MOOE | BJ10: CO | BK10: TOTAL | BO10: MOOE | BP10: CO | BQ10: TOTAL | BR10: MOOE | BS10: CO | BT10: TOTAL | BU10: MOOE | BV10: CO | BW10: TOTAL | CA10: MOOE | CB10: CO | CC10: TOTAL | CD10: MOOE | CE10: CO | CF10: TOTAL | CG10: MOOE | CH10: CO | CI10: TOTAL | CM10: MOOE | CN10: CO | CO10: TOTAL | CP10: MOOE | CQ10: CO | CR10: TOTAL | CS10: MOOE | CT10: CO | CU10: TOTAL | DB10: MOOE | DC10: CO | DD10: TOTAL | DE10: MOOE | DF10: CO | DG10: TOTAL | DH10: MOOE | DI10: CO | DJ10: TOTAL
A11: PSS
B12: OPV Seed Production
C13: Seed Production - White Corn Registered Seeds | J13: 1105 | L13: 1105 | M13: 1105 | O13: 1105 | AZ13: 1105 | BB13: 1105 | BC13: 1105 | BE13: 1105 | BR13: 1105 | BT13: 1105 | BX13: 1105 | BZ13: 1105 | CY13: 1105 | DA13: 1105 | DQ13: 1105 | DS13: 1105
B14: Corn Seed Reserve
C15: DRRM - White Corn Seed Procured OPV | J15: 1500 | L15: 1500 | M15: 1500 | O15: 1500 | AZ15: 1500 | BB15: 1500 | BC15: 1500 | BE15: 1500 | BR15: 1500 | BT15: 1500 | BX15: 1500 | BZ15: 1500 | CY15: 1500 | DA15: 1500 | DQ15: 1500 | DS15: 1500
C16: DRRM - Yellow Corn Seed Procured OPV | J16: 300 | L16: 300 | M16: 300 | O16: 300 | AZ16: 300 | BB16: 300 | BC16: 300 | BE16: 300 | BR16: 300 | BT16: 300 | BX16: 300 | BZ16: 300 | CY16: 300 | DA16: 300 | DQ16: 300 | DS16: 300
C17: DRRM - Yellow Corn Seed Procured Hybrid | P17: 250596 | R17: 250596 | Y17: 250596 | AA17: 250596 | AZ17: 250596 | BB17: 250596 | BC17: 250596 | BE17: 250596 | CA17: 250596 | CC17: 250596 | CJ17: 250596 | CL17: 250596 | CY17: 250596 | DA17: 250596 | DQ17: 250596 | DS17: 250596
B18: Recommended Corn Production Technology
C19: RCPT - Yellow Corn seeds | J19: 12000 | L19: 12000 | M19: 12000 | O19: 12000 | AZ19: 12000 | BB19: 12000 | BC19: 12000 | BE19: 12000 | CD19: 12000 | CF19: 12000 | CJ19: 12000 | CL19: 12000 | CY19: 12000 | DA19: 12000 | DQ19: 12000 | DS19: 12000
C20: RCPT - Inorganic fertilizer for YC seeds | P20: 17600 | R20: 17600 | Y20: 17600 | AA20: 17600 | AB20: 7150 | AD20: 7150 | AK20: 7150 | AM20: 7150 | AZ20: 24750 | BB20: 24750 | BC20: 24750 | BE20: 24750 | CA20: 17600 | CC20: 17600 | CJ20: 17600 | CL20: 17600 | CP20: 7150 | CR20: 7150 | CV20: 7150 | CX20: 7150 | CY20: 24750 | DA20: 24750 | DQ20: 24750 | DS20: 24750
B21: Soil amendments
C22: Biofertilizer | J22: 2720 | L22: 2720 | M22: 2720 | O22: 2720 | AZ22: 2720 | BB22: 2720 | BC22: 2720 | BE22: 2720 | CA22: 2720 | CC22: 2720 | CJ22: 2720 | CL22: 2720 | CY22: 2720 | DA22: 2720 | DQ22: 2720 | DS22: 2720
C23: Soil Ameliorant | J23: 7000 | L23: 7000 | M23: 7000 | O23: 7000 | AB23: 3000 | AD23: 3000 | AK23: 3000 | AM23: 3000 | AZ23: 10000 | BB23: 10000 | BC23: 10000 | BE23: 10000 | CA23: 7000 | CC23: 7000 | CJ23: 7000 | CL23: 7000 | CP23: 3000 | CR23: 3000 | CV23: 3000 | CX23: 3000 | CY23: 10000 | DA23: 10000 | DQ23: 10000 | DS23: 10000
B24: Yellow Corn Production Enhancement Project
C25: YCPEP - Yellow Corn Hybrid seeds | P25: 324000 | R25: 324000 | Y25: 324000 | AA25: 324000 | AZ25: 324000 | BB25: 324000 | BC25: 324000 | BE25: 324000 | CD25: 324000 | CF25: 324000 | CJ25: 324000 | CL25: 324000 | CY25: 324000 | DA25: 324000 | DQ25: 324000 | DS25: 324000
C26: YCPEP - Inorganic fertilizer for YC Hybrid seeds | J26: 86400 | L26: 86400 | M26: 86400 | O26: 86400 | AB26: 35100 | AD26: 35100 | AK26: 35100 | AM26: 35100 | AZ26: 121500 | BB26: 121500 | BC26: 121500 | BE26: 121500 | CA26: 86400 | CC26: 86400 | CJ26: 86400 | CL26: 86400 | CP26: 35100 | CR26: 35100 | CV26: 35100 | CX26: 35100 | CY26: 121500 | DA26: 121500 | DQ26: 121500 | DS26: 121500
B27: Pest and Disease Management
C28: DRRM - Agricultural chemicals (Insecticide in liters) | J28: 6000 | L28: 6000 | M28: 6000 | O28: 6000 | AZ28: 6000 | BB28: 6000 | BC28: 6000 | BE28: 6000 | BU28: 6000 | BW28: 6000 | BX28: 6000 | BZ28: 6000 | CY28: 6000 | DA28: 6000 | DQ28: 6000 | DS28: 6000
C29: DRRM - Agricultural chemicals (Rodenticides) | J29: 1500 | L29: 1500 | M29: 1500 | O29: 1500 | AZ29: 1500 | BB29: 1500 | BC29: 1500 | BE29: 1500 | BU29: 1500 | BW29: 1500 | BX29: 1500 | BZ29: 1500 | CY29: 1500 | DA29: 1500 | DQ29: 1500 | DS29: 1500
C30: DRRM - Agricultural chemicals (Pheromone lure) | J30: 2750 | L30: 2750 | M30: 2750 | O30: 2750 | AZ30: 2750 | BB30: 2750 | BC30: 2750 | BE30: 2750 | BU30: 2750 | BW30: 2750 | BX30: 2750 | BZ30: 2750 | CY30: 2750 | DA30: 2750 | DQ30: 2750 | DS30: 2750
C31: DRRM - Agricultural chemicals (Streptomycin) | J31: 4000 | L31: 4000 | M31: 4000 | O31: 4000 | AZ31: 4000 | BB31: 4000 | BC31: 4000 | BE31: 4000 | CA31: 4000 | CC31: 4000 | CJ31: 4000 | CL31: 4000 | CY31: 4000 | DA31: 4000 | DQ31: 4000 | DS31: 4000
B32: Cassava Production Enhancement Project
C33: Cassava Production (seed pieces) | J33: 975 | L33: 975 | M33: 975 | O33: 975 | AZ33: 975 | BB33: 975 | BC33: 975 | BE33: 975 | BR33: 975 | BT33: 975 | BX33: 975 | BZ33: 975 | CY33: 975 | DA33: 975 | DQ33: 975 | DS33: 975
C34: Cassava Procurement (seed pieces) | J34: 7500 | L34: 7500 | M34: 7500 | O34: 7500 | AZ34: 7500 | BB34: 7500 | BC34: 7500 | BE34: 7500 | CA34: 7500 | CC34: 7500 | CJ34: 7500 | CL34: 7500 | CY34: 7500 | DA34: 7500 | DQ34: 7500 | DS34: 7500
C35: Inorganic fertilizer for Cassava | J35: 1913.6 | L35: 1913.6 | M35: 1913.6 | O35: 1913.6 | AB35: 777.4 | AD35: 777.4 | AK35: 777.4 | AM35: 777.4 | AZ35: 2691 | BB35: 2691 | BC35: 2691 | BE35: 2691 | CA35: 1913.6 | CC35: 1913.6 | CJ35: 1913.6 | CL35: 1913.6 | CP35: 777.4 | CR35: 777.4 | CV35: 777.4 | CX35: 777.4 | CY35: 2691 | DA35: 2691 | DQ35: 2691 | DS35: 2691
B36: Sorghum Production Enhancement Project
C37: Seed Procurement - Sorghum | J37: 1750 | L37: 1750 | M37: 1750 | O37: 1750 | AZ37: 1750 | BB37: 1750 | BC37: 1750 | BE37: 1750 | CA37: 1750 | CC37: 1750 | CJ37: 1750 | CL37: 1750 | CY37: 1750 | DA37: 1750 | DQ37: 1750 | DS37: 1750
C38: Inorganic fertilizer for Sorghum | J38: 3800 | L38: 3800 | M38: 3800 | O38: 3800 | AB38: 700 | AD38: 700 | AK38: 700 | AM38: 700 | AZ38: 4500 | BB38: 4500 | BC38: 4500 | BE38: 4500 | CA38: 3800 | CC38: 3800 | CJ38: 3800 | CL38: 3800 | CP38: 700 | CR38: 700 | CV38: 700 | CX38: 700 | CY38: 4500 | DA38: 4500 | DQ38: 4500 | DS38: 4500
B39: Soybean Production Enhancement Project
C40: Seed Production - Soybean | G40: 50 | I40: 50 | M40: 50 | O40: 50 | AZ40: 50 | BB40: 50 | BC40: 50 | BE40: 50 | BR40: 50 | BT40: 50 | BX40: 50 | BZ40: 50 | CY40: 50 | DA40: 50 | DQ40: 50 | DS40: 50
C41: Inorganic fertilizer for Soybean | G41: 113 | I41: 113 | M41: 113 | O41: 113 | AZ41: 113 | BB41: 113 | BC41: 113 | BE41: 113 | BR41: 113 | BT41: 113 | BX41: 113 | BZ41: 113 | CY41: 113 | DA41: 113 | DQ41: 113 | DS41: 113
B42: DA Facilities Management
C43: DA Stations - Hand tractor with corn planter | Q43: 1200 | R43: 1200 | Z43: 1200 | AA43: 1200 | BA43: 1200 | BB43: 1200 | BD43: 1200 | BE43: 1200 | CE43: 1200 | CF43: 1200 | CK43: 1200 | CL43: 1200 | CZ43: 1200 | DA43: 1200 | DR43: 1200 | DS43: 1200
C44: DA Stations - Silage Chopper | Q44: 240 | R44: 240 | Z44: 240 | AA44: 240 | BA44: 240 | BB44: 240 | BD44: 240 | BE44: 240 | CE44: 240 | CF44: 240 | CK44: 240 | CL44: 240 | CZ44: 240 | DA44: 240 | DR44: 240 | DS44: 240
C45: DA Stations - Corn Mill | Q45: 1200 | R45: 1200 | Z45: 1200 | AA45: 1200 | BA45: 1200 | BB45: 1200 | BD45: 1200 | BE45: 1200 | CE45: 1200 | CF45: 1200 | CK45: 1200 | CL45: 1200 | CZ45: 1200 | DA45: 1200 | DR45: 1200 | DS45: 1200
C46: DA Stations - Pelletizing Machine | Q46: 300 | R46: 300 | Z46: 300 | AA46: 300 | BA46: 300 | BB46: 300 | BD46: 300 | BE46: 300 | CE46: 300 | CF46: 300 | CK46: 300 | CL46: 300 | CZ46: 300 | DA46: 300 | DR46: 300 | DS46: 300
C47: DA Stations - Light Cargo Truck | W47: 2100 | X47: 2100 | Z47: 2100 | AA47: 2100 | BA47: 2100 | BB47: 2100 | BD47: 2100 | BE47: 2100 | CH47: 2100 | CI47: 2100 | CK47: 2100 | CL47: 2100 | CZ47: 2100 | DA47: 2100 | DR47: 2100 | DS47: 2100
C48: DA Stations - Four-wheel Tractor (90 hp min) | W48: 3100 | X48: 3100 | Z48: 3100 | AA48: 3100 | BA48: 3100 | BB48: 3100 | BD48: 3100 | BE48: 3100 | CN48: 3100 | CO48: 3100 | CW48: 3100 | CX48: 3100 | CZ48: 3100 | DA48: 3100 | DR48: 3100 | DS48: 3100
A49: ESETS
B50: Model Farm establishment
C51: Sustainable Land Management in Corn-based Sloping Areas (SLM-Corn) | J51: 3000 | L51: 3000 | M51: 3000 | O51: 3000 | AZ51: 3000 | BB51: 3000 | BC51: 3000 | BE51: 3000 | CA51: 3000 | CC51: 3000 | CJ51: 3000 | CL51: 3000 | CY51: 3000 | DA51: 3000 | DQ51: 3000 | DS51: 3000
C52: Model Farm - Cassava (sites) | J52: 650 | L52: 650 | M52: 650 | O52: 650 | AZ52: 650 | BB52: 650 | BC52: 650 | BE52: 650 | CD52: 650 | CF52: 650 | CJ52: 650 | CL52: 650 | CY52: 650 | DA52: 650 | DQ52: 650 | DS52: 650
C53: Model Farm - Sorghum (sites) | J53: 280 | L53: 280 | M53: 280 | O53: 280 | AZ53: 280 | BB53: 280 | BC53: 280 | BE53: 280 | CP53: 280 | CR53: 280 | CV53: 280 | CX53: 280 | CY53: 280 | DA53: 280 | DQ53: 280 | DS53: 280
C54: Model Farm - Soybean (sites) | G54: 330 | I54: 330 | M54: 330 | O54: 330 | AZ54: 330 | BB54: 330 | BC54: 330 | BE54: 330 | BO54: 330 | BQ54: 330 | BX54: 330 | BZ54: 330 | CY54: 330 | DA54: 330 | DQ54: 330 | DS54: 330
B55: Techno Demo establishment
C56: Establishment of Corn Derby | J56: 1000 | L56: 1000 | M56: 1000 | O56: 1000 | AZ56: 1000 | BB56: 1000 | BC56: 1000 | BE56: 1000 | CA56: 1000 | CC56: 1000 | CJ56: 1000 | CL56: 1000 | CY56: 1000 | DA56: 1000 | DQ56: 1000 | DS56: 1000
C57: Techno-Demo Sorghum (sites) | J57: 160 | L57: 160 | M57: 160 | O57: 160 | AZ57: 160 | BB57: 160 | BC57: 160 | BE57: 160 | CP57: 160 | CR57: 160 | CV57: 160 | CX57: 160 | CY57: 160 | DA57: 160 | DQ57: 160 | DS57: 160
C58: Techno-Demo Soybean (sites) | G58: 200 | I58: 200 | M58: 200 | O58: 200 | AZ58: 200 | BB58: 200 | BC58: 200 | BE58: 200 | BO58: 200 | BQ58: 200 | BX58: 200 | BZ58: 200 | CY58: 200 | DA58: 200 | DQ58: 200 | DS58: 200
B59: Trainings
C60: Training - Clientele-based - Corn Cluster Development training | J60: 210 | L60: 210 | M60: 210 | O60: 210 | AZ60: 210 | BB60: 210 | BC60: 210 | BE60: 210 | BR60: 210 | BT60: 210 | BX60: 210 | BZ60: 210 | CY60: 210 | DA60: 210 | DQ60: 210 | DS60: 210
C61: Training - Clientele-based - Corn Livelihood training | J61: 200 | L61: 200 | M61: 200 | O61: 200 | AZ61: 200 | BB61: 200 | BC61: 200 | BE61: 200 | BR61: 200 | BT61: 200 | BX61: 200 | BZ61: 200 | CY61: 200 | DA61: 200 | DQ61: 200 | DS61: 200
C62: Training - Clientele-based - Corn Production Training | J62: 140 | L62: 140 | M62: 140 | O62: 140 | AZ62: 140 | BB62: 140 | BC62: 140 | BE62: 140 | BR62: 140 | BT62: 140 | BX62: 140 | BZ62: 140 | CY62: 140 | DA62: 140 | DQ62: 140 | DS62: 140
C63: Training - Clientele-based - Integrated Pest Management Training | J63: 400 | L63: 400 | M63: 400 | O63: 400 | AZ63: 400 | BB63: 400 | BC63: 400 | BE63: 400 | BU63: 200 | BW63: 200 | BX63: 200 | BZ63: 200 | CP63: 200 | CR63: 200 | CV63: 200 | CX63: 200 | CY63: 400 | DA63: 400 | DQ63: 400 | DS63: 400
C64: Training - Clientele-based - Training on Operation and Maintenance of Farm Machinery and Equipment | AE64: 100 | AG64: 100 | AH64: 100 | AJ64: 100 | AK64: 200 | AM64: 200 | AN64: 100 | AP64: 100 | AW64: 100 | AY64: 100 | AZ64: 300 | BB64: 300 | BC64: 300 | BE64: 300 | CG64: 100 | CI64: 100 | CJ64: 100 | CL64: 100 | CM64: 100 | CO64: 100 | CP64: 100 | CR64: 100 | CV64: 200 | CX64: 200 | CY64: 300 | DA64: 300 | DQ64: 300 | DS64: 300
C65: Training - Clientele-based - Cassava Livelihood training | J65: 200 | L65: 200 | M65: 200 | O65: 200 | AZ65: 200 | BB65: 200 | BC65: 200 | BE65: 200 | BR65: 200 | BT65: 200 | BX65: 200 | BZ65: 200 | CY65: 200 | DA65: 200 | DQ65: 200 | DS65: 200
C66: Training - Clientele-based - Cassava Production Training | J66: 140 | L66: 140 | M66: 140 | O66: 140 | AZ66: 140 | BB66: 140 | BC66: 140 | BE66: 140 | BR66: 140 | BT66: 140 | BX66: 140 | BZ66: 140 | CY66: 140 | DA66: 140 | DQ66: 140 | DS66: 140
C67: Training - Clientele-based - Sorghum Production Training | J67: 140 | L67: 140 | M67: 140 | O67: 140 | AZ67: 140 | BB67: 140 | BC67: 140 | BE67: 140 | CP67: 140 | CR67: 140 | CV67: 140 | CX67: 140 | CY67: 140 | DA67: 140 | DQ67: 140 | DS67: 140
C68: Training - Clientele-based - Soybean Production Training | G68: 140 | I68: 140 | M68: 140 | O68: 140 | AZ68: 140 | BB68: 140 | BC68: 140 | BE68: 140 | BR68: 140 | BT68: 140 | BX68: 140 | BZ68: 140 | CY68: 140 | DA68: 140 | DQ68: 140 | DS68: 140
B69: Information, Education, and Communication Activities
C70: Advocacy and Information Materials - IEC Materials Yellow Corn | J70: 200 | L70: 200 | M70: 200 | O70: 200 | AZ70: 200 | BB70: 200 | BC70: 200 | BE70: 200 | CA70: 200 | CC70: 200 | CJ70: 200 | CL70: 200 | CY70: 200 | DA70: 200 | DQ70: 200 | DS70: 200
C71: Advocacy and Information Materials - IEC Materials Cassava | J71: 150 | L71: 150 | M71: 150 | O71: 150 | AZ71: 150 | BB71: 150 | BC71: 150 | BE71: 150 | CA71: 150 | CC71: 150 | CJ71: 150 | CL71: 150 | CY71: 150 | DA71: 150 | DQ71: 150 | DS71: 150
C72: Advocacy and Information Materials - IEC Materials Sorghum | J72: 50 | L72: 50 | M72: 50 | O72: 50 | AZ72: 50 | BB72: 50 | BC72: 50 | BE72: 50 | CD72: 50 | CF72: 50 | CJ72: 50 | CL72: 50 | CY72: 50 | DA72: 50 | DQ72: 50 | DS72: 50
C73: Advocacy and Information Materials - IEC Materials Soybean | G73: 50 | I73: 50 | M73: 50 | O73: 50 | AZ73: 50 | BB73: 50 | BC73: 50 | BE73: 50 | BO73: 50 | BQ73: 50 | BX73: 50 | BZ73: 50 | CY73: 50 | DA73: 50 | DQ73: 50 | DS73: 50
C74: Advocacy and Information Materials - Radio Plugs | G74: 350 | I74: 350 | M74: 350 | O74: 350 | AZ74: 350 | BB74: 350 | BC74: 350 | BE74: 350 | BF74: 32 | BH74: 32 | BI74: 32 | BK74: 32 | BL74: 64 | BN74: 64 | BO74: 32 | BQ74: 32 | BR74: 32 | BT74: 32 | BU74: 32 | BW74: 32 | BX74: 96 | BZ74: 96 | CA74: 32 | CC74: 32 | CD74: 32 | CF74: 32 | CG74: 32 | CI74: 32 | CJ74: 96 | CL74: 96 | CM74: 32 | CO74: 32 | CP74: 32 | CR74: 32 | CS74: 30 | CU74: 30 | CV74: 94 | CX74: 94 | CY74: 350 | DA74: 350 | DQ74: 350 | DS74: 350
C75: Advocacy and Information Materials - TV Plugs | G75: 400 | I75: 400 | M75: 400 | O75: 400 | AZ75: 400 | BB75: 400 | BC75: 400 | BE75: 400 | BF75: 36 | BH75: 36 | BI75: 36 | BK75: 36 | BL75: 72 | BN75: 72 | BO75: 36 | BQ75: 36 | BR75: 36 | BT75: 36 | BU75: 36 | BW75: 36 | BX75: 108 | BZ75: 108 | CA75: 36 | CC75: 36 | CD75: 36 | CF75: 36 | CG75: 36 | CI75: 36 | CJ75: 108 | CL75: 108 | CM75: 36 | CO75: 36 | CP75: 36 | CR75: 36 | CS75: 40 | CU75: 40 | CV75: 112 | CX75: 112 | CY75: 400 | DA75: 400 | DQ75: 400 | DS75: 400
B76: Extension Workers Incentives
C77: Support to LGU Extension Workers Incentives - Provincial Coordinator | J77: 192 | L77: 192 | M77: 192 | O77: 192 | AZ77: 192 | BB77: 192 | BC77: 192 | BE77: 192 | BO77: 96 | BQ77: 96 | BX77: 96 | BZ77: 96 | CD77: 96 | CF77: 96 | CJ77: 96 | CL77: 96 | CY77: 192 | DA77: 192 | DQ77: 192 | DS77: 192
C78: Support to LGU Extension Workers Incentives - Municipal Agriculturist | J78: 576 | L78: 576 | M78: 576 | O78: 576 | AZ78: 576 | BB78: 576 | BC78: 576 | BE78: 576 | BO78: 288 | BQ78: 288 | BX78: 288 | BZ78: 288 | CD78: 288 | CF78: 288 | CJ78: 288 | CL78: 288 | CY78: 576 | DA78: 576 | DQ78: 576 | DS78: 576
C79: Support to LGU Extension Workers Incentives - Agricultural Extension Worker | J79: 7098 | L79: 7098 | M79: 7098 | O79: 7098 | AZ79: 7098 | BB79: 7098 | BC79: 7098 | BE79: 7098 | BO79: 3549 | BQ79: 3549 | BX79: 3549 | BZ79: 3549 | CD79: 3549 | CF79: 3549 | CJ79: 3549 | CL79: 3549 | CY79: 7098 | DA79: 7098 | DQ79: 7098 | DS79: 7098
B80: Special Events
C81: Corn and Cassava Congress | AN81: 600 | AP81: 600 | AW81: 600 | AY81: 600 | AZ81: 600 | BB81: 600 | BC81: 600 | BE81: 600 | CP81: 600 | CR81: 600 | CV81: 600 | CX81: 600 | CY81: 600 | DA81: 600 | DQ81: 600 | DS81: 600
A82: RND
B83: R&D conducted
C84: R&D New Studies Conducted - Production | J84: 4500 | L84: 4500 | M84: 4500 | O84: 4500 | V84: 450 | X84: 450 | Y84: 450 | AA84: 450 | AH84: 550 | AJ84: 550 | AK84: 550 | AM84: 550 | AZ84: 5500 | BB84: 5500 | BC84: 5500 | BE84: 5500 | BO84: 4500 | BQ84: 4500 | BX84: 4500 | BZ84: 4500 | CA84: 450 | CC84: 450 | CJ84: 450 | CL84: 450 | CM84: 550 | CO84: 550 | CV84: 550 | CX84: 550 | CY84: 5500 | DA84: 5500 | DQ84: 5500 | DS84: 5500
A85: AMEFSS
B86: Production related machinery & equipment
C87: Farm Production - Four-wheel Tractor (90 hp min) | W87: 36000 | X87: 36000 | Z87: 36000 | AA87: 36000 | BA87: 36000 | BB87: 36000 | BD87: 36000 | BE87: 36000 | CN87: 36000 | CO87: 36000 | CW87: 36000 | CX87: 36000 | CZ87: 36000 | DA87: 36000 | DR87: 36000 | DS87: 36000
C88: Farm Production - Double Row Corn seeder | K88: 2400 | L88: 2400 | N88: 2400 | O88: 2400 | BA88: 2400 | BB88: 2400 | BD88: 2400 | BE88: 2400 | CH88: 2400 | CI88: 2400 | CK88: 2400 | CL88: 2400 | CZ88: 2400 | DA88: 2400 | DR88: 2400 | DS88: 2400
C89: Farm Production - Mechanical four-row seeder | K89: 2000 | L89: 2000 | N89: 2000 | O89: 2000 | BA89: 2000 | BB89: 2000 | BD89: 2000 | BE89: 2000 | CH89: 2000 | CI89: 2000 | CK89: 2000 | CL89: 2000 | CZ89: 2000 | DA89: 2000 | DR89: 2000 | DS89: 2000
C90: Farm Production - Pneumatic Four-row seeder | K90: 1800 | L90: 1800 | N90: 1800 | O90: 1800 | BA90: 1800 | BB90: 1800 | BD90: 1800 | BE90: 1800 | CH90: 1800 | CI90: 1800 | CK90: 1800 | CL90: 1800 | CZ90: 1800 | DA90: 1800 | DR90: 1800 | DS90: 1800
C91: Farm Production - Two-row seeder | K91: 15000 | L91: 15000 | N91: 15000 | O91: 15000 | BA91: 15000 | BB91: 15000 | BD91: 15000 | BE91: 15000 | CH91: 15000 | CI91: 15000 | CK91: 15000 | CL91: 15000 | CZ91: 15000 | DA91: 15000 | DR91: 15000 | DS91: 15000
C92: Farm Production - Combine Harvester | W92: 21000 | X92: 21000 | Z92: 21000 | AA92: 21000 | BA92: 21000 | BB92: 21000 | BD92: 21000 | BE92: 21000 | CN92: 21000 | CO92: 21000 | CW92: 21000 | CX92: 21000 | CZ92: 21000 | DA92: 21000 | DR92: 21000 | DS92: 21000
B93: Postharvest related machinery & equipment
C94: Postharvest-related - Hauling Truck (not exceeding 3000cc) - four-wheel truck | W94: 11000 | X94: 11000 | Z94: 11000 | AA94: 11000 | BA94: 11000 | BB94: 11000 | BD94: 11000 | BE94: 11000 | CN94: 11000 | CO94: 11000 | CW94: 11000 | CX94: 11000 | CZ94: 11000 | DA94: 11000 | DR94: 11000 | DS94: 11000
C95: Postharvest-related - Solar Bubble Dryer | K95: 4000 | L95: 4000 | N95: 4000 | O95: 4000 | BA95: 4000 | BB95: 4000 | BD95: 4000 | BE95: 4000 | CH95: 4000 | CI95: 4000 | CK95: 4000 | CL95: 4000 | CZ95: 4000 | DA95: 4000 | DR95: 4000 | DS95: 4000
B96: Processing related machinery & equipment
C97: Postharvest-related - Corn Mill (1T/hr) | Q97: 4400 | R97: 4400 | Z97: 4400 | AA97: 4400 | BA97: 4400 | BB97: 4400 | BD97: 4400 | BE97: 4400 | CN97: 4400 | CO97: 4400 | CW97: 4400 | CX97: 4400 | CZ97: 4400 | DA97: 4400 | DR97: 4400 | DS97: 4400
C98: Postharvest facilities - Waste Water Treatment System | AI98: 20000 | AJ98: 20000 | AL98: 20000 | AM98: 20000 | BA98: 20000 | BB98: 20000 | BD98: 20000 | BE98: 20000 | CN98: 3000 | CO98: 3000 | CQ98: 4000 | CR98: 4000 | CT98: 4000 | CU98: 4000 | CW98: 11000 | CX98: 11000 | CZ98: 11000 | DA98: 11000 | DC98: 4000 | DD98: 4000 | DF98: 4000 | DG98: 4000 | DI98: 1000 | DJ98: 1000 | DL98: 9000 | DM98: 9000 | DO98: 9000 | DP98: 9000 | DR98: 20000 | DS98: 20000
B99: Postharvest facilities
C100: Postharvest facilities - Multi Crop Drying Pavement (MCDP) | W100: 5000 | X100: 5000 | Z100: 5000 | AA100: 5000 | BA100: 5000 | BB100: 5000 | BD100: 5000 | BE100: 5000 | CQ100: 5000 | CR100: 5000 | CW100: 5000 | CX100: 5000 | CZ100: 5000 | DA100: 5000 | DR100: 5000 | DS100: 5000
A101: INS
...

Sheet BED 3
A1: CY 2025 PLAN AND BUDGET PROPOSAL
A2: BASED ON GENERAL APPROPRIATIONS ACT (GAA)
A3: BED 3 DISBURSEMENT
D5: PROPOSAL/BEDS | E5: YEAR | F5: QUARTER | G5: MONTH | H5: Values
D6: BED 1 - OBLIGATION | BC6: BED 1 - OBLIGATION MOOE | BD6: BED 1 - OBLIGATION CO | BE6: BED 1 - OBLIGATION TOTAL | BF6: BED 3 - DISBURSEMENT | DQ6: BED 3 - DISBURSEMENT MOOE | DR6: BED 3 - DISBURSEMENT CO | DS6: BED 3 - DISBURSEMENT TOTAL
D7: 2025 | AZ7: 2025 MOOE | BA7: 2025 CO | BB7: 2025 TOTAL | BF7: 2025 | CY7: 2025 MOOE | CZ7: 2025 CO | DA7: 2025 TOTAL | DB7: 2026 | DN7: 2026 MOOE | DO7: 2026 CO | DP7: 2026 TOTAL
D8: 1ST QTR | M8: 1ST QTR MOOE | N8: 1ST QTR CO | O8: 1ST QTR TOTAL | P8: 2ND QTR | Y8: 2ND QTR MOOE | Z8: 2ND QTR CO | AA8: 2ND QTR TOTAL | AB8: 3RD QTR | AK8: 3RD QTR MOOE | AL8: 3RD QTR CO | AM8: 3RD QTR TOTAL | AN8: 4TH QTR | AW8: 4TH QTR MOOE | AX8: 4TH QTR CO | AY8: 4TH QTR TOTAL | BF8: 1ST QTR | BL8: 1ST QTR MOOE | BM8: 1ST QTR CO | BN8: 1ST QTR TOTAL | BO8: 2ND QTR | BX8: 2ND QTR MOOE | BY8: 2ND QTR CO | BZ8: 2ND QTR TOTAL | CA8: 3RD QTR | CJ8: 3RD QTR MOOE | CK8: 3RD QTR CO | CL8: 3RD QTR TOTAL | CM8: 4TH QTR | CV8: 4TH QTR MOOE | CW8: 4TH QTR CO | CX8: 4TH QTR TOTAL | DB8: 1ST QTR 2026 | DK8: 1ST QTR 2026 MOOE | DL8: 1ST QTR 2026 CO | DM8: 1ST QTR 2026 TOTAL
D9: JANUARY | G9: FEBRUARY | J9: MARCH | P9: APRIL | S9: MAY | V9: JUNE | AB9: JULY | AE9: AUGUST | AH9: SEPTEMBER | AN9: OCTOBER | AQ9: NOVEMBER | AT9: DECEMBER | BF9: FEBRUARY | BI9: MARCH | BO9: APRIL | BR9: MAY | BU9: JUNE | CA9: JULY | CD9: AUGUST | CG9: SEPTEMBER | CM9: OCTOBER | CP9: NOVEMBER | CS9: DECEMBER | DB9: FEBRUARY 2026 | DE9: JANUARY 2026 | DH9: MARCH 2026
A10: PREXC SUB-PROGRAM | B10: STRATEGY | C10: ACTIVITY | D10: MOOE | E10: CO | F10: TOTAL | G10: MOOE | H10: CO | I10: TOTAL | J10: MOOE | K10: CO | L10: TOTAL | P10: MOOE | Q10: CO | R10: TOTAL | S10: MOOE | T10: CO | U10: TOTAL | V10: MOOE | W10: CO | X10: TOTAL | AB10: MOOE | AC10: CO | AD10: TOTAL | AE10: MOOE | AF10: CO | AG10: TOTAL | AH10: MOOE | AI10: CO | AJ10: TOTAL | AN10: MOOE | AO10: CO | AP10: TOTAL | AQ10: MOOE | AR10: CO | AS10: TOTAL | AT10: MOOE | AU10: CO | AV10: TOTAL | BF10: MOOE | BG10: CO | BH10: TOTAL | BI10: MOOE | BJ10: CO | BK10: TOTAL | BO10: MOOE | BP10: CO | BQ10: TOTAL | BR10: MOOE | BS10: CO | BT10: TOTAL | BU10: MOOE | BV10: CO | BW10: TOTAL | CA10: MOOE | CB10: CO | CC10: TOTAL | CD10: MOOE | CE10: CO | CF10: TOTAL | CG10: MOOE | CH10: CO | CI10: TOTAL | CM10: MOOE | CN10: CO | CO10: TOTAL | CP10: MOOE | CQ10: CO | CR10: TOTAL | CS10: MOOE | CT10: CO | CU10: TOTAL | DB10: MOOE | DC10: CO | DD10: TOTAL | DE10: MOOE | DF10: CO | DG10: TOTAL | DH10: MOOE | DI10: CO | DJ10: TOTAL
A11: PSS
B12: OPV Seed Production
C13: Seed Production - White Corn Registered Seeds | J13: 1105 | L13: 1105 | M13: 1105 | O13: 1105 | AZ13: 1105 | BB13: 1105 | BC13: 1105 | BE13: 1105 | BR13: 1105 | BT13: 1105 | BX13: 1105 | BZ13: 1105 | CY13: 1105 | DA13: 1105 | DQ13: 1105 | DS13: 1105
B14: Corn Seed Reserve
C15: DRRM - White Corn Seed Procured OPV | J15: 1500 | L15: 1500 | M15: 1500 | O15: 1500 | AZ15: 1500 | BB15: 1500 | BC15: 1500 | BE15: 1500 | BR15: 1500 | BT15: 1500 | BX15: 1500 | BZ15: 1500 | CY15: 1500 | DA15: 1500 | DQ15: 1500 | DS15: 1500
C16: DRRM - Yellow Corn Seed Procured OPV | J16: 300 | L16: 300 | M16: 300 | O16: 300 | AZ16: 300 | BB16: 300 | BC16: 300 | BE16: 300 | BR16: 300 | BT16: 300 | BX16: 300 | BZ16: 300 | CY16: 300 | DA16: 300 | DQ16: 300 | DS16: 300
C17: DRRM - Yellow Corn Seed Procured Hybrid | P17: 250596 | R17: 250596 | Y17: 250596 | AA17: 250596 | AZ17: 250596 | BB17: 250596 | BC17: 250596 | BE17: 250596 | CA17: 250596 | CC17: 250596 | CJ17: 250596 | CL17: 250596 | CY17: 250596 | DA17: 250596 | DQ17: 250596 | DS17: 250596
B18: Recommended Corn Production Technology
C19: RCPT - Yellow Corn seeds | J19: 12000 | L19: 12000 | M19: 12000 | O19: 12000 | AZ19: 12000 | BB19: 12000 | BC19: 12000 | BE19: 12000 | CD19: 12000 | CF19: 12000 | CJ19: 12000 | CL19: 12000 | CY19: 12000 | DA19: 12000 | DQ19: 12000 | DS19: 12000
C20: RCPT - Inorganic fertilizer for YC seeds | P20: 17600 | R20: 17600 | Y20: 17600 | AA20: 17600 | AB20: 7150 | AD20: 7150 | AK20: 7150 | AM20: 7150 | AZ20: 24750 | BB20: 24750 | BC20: 24750 | BE20: 24750 | CA20: 17600 | CC20: 17600 | CJ20: 17600 | CL20: 17600 | CP20: 7150 | CR20: 7150 | CV20: 7150 | CX20: 7150 | CY20: 24750 | DA20: 24750 | DQ20: 24750 | DS20: 24750
B21: Soil amendments
C22: Biofertilizer | J22: 2720 | L22: 2720 | M22: 2720 | O22: 2720 | AZ22: 2720 | BB22: 2720 | BC22: 2720 | BE22: 2720 | CA22: 2720 | CC22: 2720 | CJ22: 2720 | CL22: 2720 | CY22: 2720 | DA22: 2720 | DQ22: 2720 | DS22: 2720
C23: Soil Ameliorant | J23: 7000 | L23: 7000 | M23: 7000 | O23: 7000 | AB23: 3000 | AD23: 3000 | AK23: 3000 | AM23: 3000 | AZ23: 10000 | BB23: 10000 | BC23: 10000 | BE23: 10000 | CA23: 7000 | CC23: 7000 | CJ23: 7000 | CL23: 7000 | CP23: 3000 | CR23: 3000 | CV23: 3000 | CX23: 3000 | CY23: 10000 | DA23: 10000 | DQ23: 10000 | DS23: 10000
B24: Yellow Corn Production Enhancement Project
C25: YCPEP - Yellow Corn Hybrid seeds | P25: 324000 | R25: 324000 | Y25: 324000 | AA25: 324000 | AZ25: 324000 | BB25: 324000 | BC25: 324000 | BE25: 324000 | CD25: 324000 | CF25: 324000 | CJ25: 324000 | CL25: 324000 | CY25: 324000 | DA25: 324000 | DQ25: 324000 | DS25: 324000
C26: YCPEP - Inorganic fertilizer for YC Hybrid seeds | J26: 86400 | L26: 86400 | M26: 86400 | O26: 86400 | AB26: 35100 | AD26: 35100 | AK26: 35100 | AM26: 35100 | AZ26: 121500 | BB26: 121500 | BC26: 121500 | BE26: 121500 | CA26: 86400 | CC26: 86400 | CJ26: 86400 | CL26: 86400 | CP26: 35100 | CR26: 35100 | CV26: 35100 | CX26: 35100 | CY26: 121500 | DA26: 121500 | DQ26: 121500 | DS26: 121500
B27: Pest and Disease Management
C28: DRRM - Agricultural chemicals (Insecticide in liters) | J28: 6000 | L28: 6000 | M28: 6000 | O28: 6000 | AZ28: 6000 | BB28: 6000 | BC28: 6000 | BE28: 6000 | BU28: 6000 | BW28: 6000 | BX28: 6000 | BZ28: 6000 | CY28: 6000 | DA28: 6000 | DQ28: 6000 | DS28: 6000
C29: DRRM - Agricultural chemicals (Rodenticides) | J29: 1500 | L29: 1500 | M29: 1500 | O29: 1500 | AZ29: 1500 | BB29: 1500 | BC29: 1500 | BE29: 1500 | BU29: 1500 | BW29: 1500 | BX29: 1500 | BZ29: 1500 | CY29: 1500 | DA29: 1500 | DQ29: 1500 | DS29: 1500
C30: DRRM - Agricultural chemicals (Pheromone lure) | J30: 2750 | L30: 2750 | M30: 2750 | O30: 2750 | AZ30: 2750 | BB30: 2750 | BC30: 2750 | BE30: 2750 | BU30: 2750 | BW30: 2750 | BX30: 2750 | BZ30: 2750 | CY30: 2750 | DA30: 2750 | DQ30: 2750 | DS30: 2750
C31: DRRM - Agricultural chemicals (Streptomycin) | J31: 4000 | L31: 4000 | M31: 4000 | O31: 4000 | AZ31: 4000 | BB31: 4000 | BC31: 4000 | BE31: 4000 | CA31: 4000 | CC31: 4000 | CJ31: 4000 | CL31: 4000 | CY31: 4000 | DA31: 4000 | DQ31: 4000 | DS31: 4000
B32: Cassava Production Enhancement Project
C33: Cassava Production (seed pieces) | J33: 975 | L33: 975 | M33: 975 | O33: 975 | AZ33: 975 | BB33: 975 | BC33: 975 | BE33: 975 | BR33: 975 | BT33: 975 | BX33: 975 | BZ33: 975 | CY33: 975 | DA33: 975 | DQ33: 975 | DS33: 975
C34: Cassava Procurement (seed pieces) | J34: 7500 | L34: 7500 | M34: 7500 | O34: 7500 | AZ34: 7500 | BB34: 7500 | BC34: 7500 | BE34: 7500 | CA34: 7500 | CC34: 7500 | CJ34: 7500 | CL34: 7500 | CY34: 7500 | DA34: 7500 | DQ34: 7500 | DS34: 7500
C35: Inorganic fertilizer for Cassava | J35: 1913.6 | L35: 1913.6 | M35: 1913.6 | O35: 1913.6 | AB35: 777.4 | AD35: 777.4 | AK35: 777.4 | AM35: 777.4 | AZ35: 2691 | BB35: 2691 | BC35: 2691 | BE35: 2691 | CA35: 1913.6 | CC35: 1913.6 | CJ35: 1913.6 | CL35: 1913.6 | CP35: 777.4 | CR35: 777.4 | CV35: 777.4 | CX35: 777.4 | CY35: 2691 | DA35: 2691 | DQ35: 2691 | DS35: 2691
B36: Sorghum Production Enhancement Project
C37: Seed Procurement - Sorghum | J37: 1750 | L37: 1750 | M37: 1750 | O37: 1750 | AZ37: 1750 | BB37: 1750 | BC37: 1750 | BE37: 1750 | CA37: 1750 | CC37: 1750 | CJ37: 1750 | CL37: 1750 | CY37: 1750 | DA37: 1750 | DQ37: 1750 | DS37: 1750
C38: Inorganic fertilizer for Sorghum | J38: 3800 | L38: 3800 | M38: 3800 | O38: 3800 | AB38: 700 | AD38: 700 | AK38: 700 | AM38: 700 | AZ38: 4500 | BB38: 4500 | BC38: 4500 | BE38: 4500 | CA38: 3800 | CC38: 3800 | CJ38: 3800 | CL38: 3800 | CP38: 700 | CR38: 700 | CV38: 700 | CX38: 700 | CY38: 4500 | DA38: 4500 | DQ38: 4500 | DS38: 4500
B39: Soybean Production Enhancement Project
C40: Seed Production - Soybean | G40: 50 | I40: 50 | M40: 50 | O40: 50 | AZ40: 50 | BB40: 50 | BC40: 50 | BE40: 50 | BR40: 50 | BT40: 50 | BX40: 50 | BZ40: 50 | CY40: 50 | DA40: 50 | DQ40: 50 | DS40: 50
C41: Inorganic fertilizer for Soybean | G41: 113 | I41: 113 | M41: 113 | O41: 113 | AZ41: 113 | BB41: 113 | BC41: 113 | BE41: 113 | BR41: 113 | BT41: 113 | BX41: 113 | BZ41: 113 | CY41: 113 | DA41: 113 | DQ41: 113 | DS41: 113
B42: DA Facilities Management
C43: DA Stations - Hand tractor with corn planter | Q43: 1200 | R43: 1200 | Z43: 1200 | AA43: 1200 | BA43: 1200 | BB43: 1200 | BD43: 1200 | BE43: 1200 | CE43: 1200 | CF43: 1200 | CK43: 1200 | CL43: 1200 | CZ43: 1200 | DA43: 1200 | DR43: 1200 | DS43: 1200
C44: DA Stations - Silage Chopper | Q44: 240 | R44: 240 | Z44: 240 | AA44: 240 | BA44: 240 | BB44: 240 | BD44: 240 | BE44: 240 | CE44: 240 | CF44: 240 | CK44: 240 | CL44: 240 | CZ44: 240 | DA44: 240 | DR44: 240 | DS44: 240
C45: DA Stations - Corn Mill | Q45: 1200 | R45: 1200 | Z45: 1200 | AA45: 1200 | BA45: 1200 | BB45: 1200 | BD45: 1200 | BE45: 1200 | CE45: 1200 | CF45: 1200 | CK45: 1200 | CL45: 1200 | CZ45: 1200 | DA45: 1200 | DR45: 1200 | DS45: 1200
C46: DA Stations - Pelletizing Machine | Q46: 300 | R46: 300 | Z46: 300 | AA46: 300 | BA46: 300 | BB46: 300 | BD46: 300 | BE46: 300 | CE46: 300 | CF46: 300 | CK46: 300 | CL46: 300 | CZ46: 300 | DA46: 300 | DR46: 300 | DS46: 300
C47: DA Stations - Light Cargo Truck | W47: 2100 | X47: 2100 | Z47: 2100 | AA47: 2100 | BA47: 2100 | BB47: 2100 | BD47: 2100 | BE47: 2100 | CH47: 2100 | CI47: 2100 | CK47: 2100 | CL47: 2100 | CZ47: 2100 | DA47: 2100 | DR47: 2100 | DS47: 2100
C48: DA Stations - Four-wheel Tractor (90 hp min) | W48: 3100 | X48: 3100 | Z48: 3100 | AA48: 3100 | BA48: 3100 | BB48: 3100 | BD48: 3100 | BE48: 3100 | CN48: 3100 | CO48: 3100 | CW48: 3100 | CX48: 3100 | CZ48: 3100 | DA48: 3100 | DR48: 3100 | DS48: 3100
A49: ESETS
B50: Model Farm establishment
C51: Sustainable Land Management in Corn-based Sloping Areas (SLM-Corn) | J51: 3000 | L51: 3000 | M51: 3000 | O51: 3000 | AZ51: 3000 | BB51: 3000 | BC51: 3000 | BE51: 3000 | CA51: 3000 | CC51: 3000 | CJ51: 3000 | CL51: 3000 | CY51: 3000 | DA51: 3000 | DQ51: 3000 | DS51: 3000
C52: Model Farm - Cassava (sites) | J52: 650 | L52: 650 | M52: 650 | O52: 650 | AZ52: 650 | BB52: 650 | BC52: 650 | BE52: 650 | CD52: 650 | CF52: 650 | CJ52: 650 | CL52: 650 | CY52: 650 | DA52: 650 | DQ52: 650 | DS52: 650
C53: Model Farm - Sorghum (sites) | J53: 280 | L53: 280 | M53: 280 | O53: 280 | AZ53: 280 | BB53: 280 | BC53: 280 | BE53: 280 | CP53: 280 | CR53: 280 | CV53: 280 | CX53: 280 | CY53: 280 | DA53: 280 | DQ53: 280 | DS53: 280
C54: Model Farm - Soybean (sites) | G54: 330 | I54: 330 | M54: 330 | O54: 330 | AZ54: 330 | BB54: 330 | BC54: 330 | BE54: 330 | BO54: 330 | BQ54: 330 | BX54: 330 | BZ54: 330 | CY54: 330 | DA54: 330 | DQ54: 330 | DS54: 330
B55: Techno Demo establishment
C56: Establishment of Corn Derby | J56: 1000 | L56: 1000 | M56: 1000 | O56: 1000 | AZ56: 1000 | BB56: 1000 | BC56: 1000 | BE56: 1000 | CA56: 1000 | CC56: 1000 | CJ56: 1000 | CL56: 1000 | CY56: 1000 | DA56: 1000 | DQ56: 1000 | DS56: 1000
C57: Techno-Demo Sorghum (sites) | J57: 160 | L57: 160 | M57: 160 | O57: 160 | AZ57: 160 | BB57: 160 | BC57: 160 | BE57: 160 | CP57: 160 | CR57: 160 | CV57: 160 | CX57: 160 | CY57: 160 | DA57: 160 | DQ57: 160 | DS57: 160
C58: Techno-Demo Soybean (sites) | G58: 200 | I58: 200 | M58: 200 | O58: 200 | AZ58: 200 | BB58: 200 | BC58: 200 | BE58: 200 | BO58: 200 | BQ58: 200 | BX58: 200 | BZ58: 200 | CY58: 200 | DA58: 200 | DQ58: 200 | DS58: 200
B59: Trainings
C60: Training - Clientele-based - Corn Cluster Development training | J60: 210 | L60: 210 | M60: 210 | O60: 210 | AZ60: 210 | BB60: 210 | BC60: 210 | BE60: 210 | BR60: 210 | BT60: 210 | BX60: 210 | BZ60: 210 | CY60: 210 | DA60: 210 | DQ60: 210 | DS60: 210
C61: Training - Clientele-based - Corn Livelihood training | J61: 200 | L61: 200 | M61: 200 | O61: 200 | AZ61: 200 | BB61: 200 | BC61: 200 | BE61: 200 | BR61: 200 | BT61: 200 | BX61: 200 | BZ61: 200 | CY61: 200 | DA61: 200 | DQ61: 200 | DS61: 200
C62: Training - Clientele-based - Corn Production Training | J62: 140 | L62: 140 | M62: 140 | O62: 140 | AZ62: 140 | BB62: 140 | BC62: 140 | BE62: 140 | BR62: 140 | BT62: 140 | BX62: 140 | BZ62: 140 | CY62: 140 | DA62: 140 | DQ62: 140 | DS62: 140
C63: Training - Clientele-based - Integrated Pest Management Training | J63: 400 | L63: 400 | M63: 400 | O63: 400 | AZ63: 400 | BB63: 400 | BC63: 400 | BE63: 400 | BU63: 200 | BW63: 200 | BX63: 200 | BZ63: 200 | CP63: 200 | CR63: 200 | CV63: 200 | CX63: 200 | CY63: 400 | DA63: 400 | DQ63: 400 | DS63: 400
C64: Training - Clientele-based - Training on Operation and Maintenance of Farm Machinery and Equipment | AE64: 100 | AG64: 100 | AH64: 100 | AJ64: 100 | AK64: 200 | AM64: 200 | AN64: 100 | AP64: 100 | AW64: 100 | AY64: 100 | AZ64: 300 | BB64: 300 | BC64: 300 | BE64: 300 | CG64: 100 | CI64: 100 | CJ64: 100 | CL64: 100 | CM64: 100 | CO64: 100 | CP64: 100 | CR64: 100 | CV64: 200 | CX64: 200 | CY64: 300 | DA64: 300 | DQ64: 300 | DS64: 300
C65: Training - Clientele-based - Cassava Livelihood training | J65: 200 | L65: 200 | M65: 200 | O65: 200 | AZ65: 200 | BB65: 200 | BC65: 200 | BE65: 200 | BR65: 200 | BT65: 200 | BX65: 200 | BZ65: 200 | CY65: 200 | DA65: 200 | DQ65: 200 | DS65: 200
C66: Training - Clientele-based - Cassava Production Training | J66: 140 | L66: 140 | M66: 140 | O66: 140 | AZ66: 140 | BB66: 140 | BC66: 140 | BE66: 140 | BR66: 140 | BT66: 140 | BX66: 140 | BZ66: 140 | CY66: 140 | DA66: 140 | DQ66: 140 | DS66: 140
C67: Training - Clientele-based - Sorghum Production Training | J67: 140 | L67: 140 | M67: 140 | O67: 140 | AZ67: 140 | BB67: 140 | BC67: 140 | BE67: 140 | CP67: 140 | CR67: 140 | CV67: 140 | CX67: 140 | CY67: 140 | DA67: 140 | DQ67: 140 | DS67: 140
C68: Training - Clientele-based - Soybean Production Training | G68: 140 | I68: 140 | M68: 140 | O68: 140 | AZ68: 140 | BB68: 140 | BC68: 140 | BE68: 140 | BR68: 140 | BT68: 140 | BX68: 140 | BZ68: 140 | CY68: 140 | DA68: 140 | DQ68: 140 | DS68: 140
B69: Information, Education, and Communication Activities
C70: Advocacy and Information Materials - IEC Materials Yellow Corn | J70: 200 | L70: 200 | M70: 200 | O70: 200 | AZ70: 200 | BB70: 200 | BC70: 200 | BE70: 200 | CA70: 200 | CC70: 200 | CJ70: 200 | CL70: 200 | CY70: 200 | DA70: 200 | DQ70: 200 | DS70: 200
C71: Advocacy and Information Materials - IEC Materials Cassava | J71: 150 | L71: 150 | M71: 150 | O71: 150 | AZ71: 150 | BB71: 150 | BC71: 150 | BE71: 150 | CA71: 150 | CC71: 150 | CJ71: 150 | CL71: 150 | CY71: 150 | DA71: 150 | DQ71: 150 | DS71: 150
C72: Advocacy and Information Materials - IEC Materials Sorghum | J72: 50 | L72: 50 | M72: 50 | O72: 50 | AZ72: 50 | BB72: 50 | BC72: 50 | BE72: 50 | CD72: 50 | CF72: 50 | CJ72: 50 | CL72: 50 | CY72: 50 | DA72: 50 | DQ72: 50 | DS72: 50
C73: Advocacy and Information Materials - IEC Materials Soybean | G73: 50 | I73: 50 | M73: 50 | O73: 50 | AZ73: 50 | BB73: 50 | BC73: 50 | BE73: 50 | BO73: 50 | BQ73: 50 | BX73: 50 | BZ73: 50 | CY73: 50 | DA73: 50 | DQ73: 50 | DS73: 50
C74: Advocacy and Information Materials - Radio Plugs | G74: 350 | I74: 350 | M74: 350 | O74: 350 | AZ74: 350 | BB74: 350 | BC74: 350 | BE74: 350 | BF74: 32 | BH74: 32 | BI74: 32 | BK74: 32 | BL74: 64 | BN74: 64 | BO74: 32 | BQ74: 32 | BR74: 32 | BT74: 32 | BU74: 32 | BW74: 32 | BX74: 96 | BZ74: 96 | CA74: 32 | CC74: 32 | CD74: 32 | CF74: 32 | CG74: 32 | CI74: 32 | CJ74: 96 | CL74: 96 | CM74: 32 | CO74: 32 | CP74: 32 | CR74: 32 | CS74: 30 | CU74: 30 | CV74: 94 | CX74: 94 | CY74: 350 | DA74: 350 | DQ74: 350 | DS74: 350
C75: Advocacy and Information Materials - TV Plugs | G75: 400 | I75: 400 | M75: 400 | O75: 400 | AZ75: 400 | BB75: 400 | BC75: 400 | BE75: 400 | BF75: 36 | BH75: 36 | BI75: 36 | BK75: 36 | BL75: 72 | BN75: 72 | BO75: 36 | BQ75: 36 | BR75: 36 | BT75: 36 | BU75: 36 | BW75: 36 | BX75: 108 | BZ75: 108 | CA75: 36 | CC75: 36 | CD75: 36 | CF75: 36 | CG75: 36 | CI75: 36 | CJ75: 108 | CL75: 108 | CM75: 36 | CO75: 36 | CP75: 36 | CR75: 36 | CS75: 40 | CU75: 40 | CV75: 112 | CX75: 112 | CY75: 400 | DA75: 400 | DQ75: 400 | DS75: 400
B76: Extension Workers Incentives
C77: Support to LGU Extension Workers Incentives - Provincial Coordinator | J77: 192 | L77: 192 | M77: 192 | O77: 192 | AZ77: 192 | BB77: 192 | BC77: 192 | BE77: 192 | BO77: 96 | BQ77: 96 | BX77: 96 | BZ77: 96 | CD77: 96 | CF77: 96 | CJ77: 96 | CL77: 96 | CY77: 192 | DA77: 192 | DQ77: 192 | DS77: 192
C78: Support to LGU Extension Workers Incentives - Municipal Agriculturist | J78: 576 | L78: 576 | M78: 576 | O78: 576 | AZ78: 576 | BB78: 576 | BC78: 576 | BE78: 576 | BO78: 288 | BQ78: 288 | BX78: 288 | BZ78: 288 | CD78: 288 | CF78: 288 | CJ78: 288 | CL78: 288 | CY78: 576 | DA78: 576 | DQ78: 576 | DS78: 576
C79: Support to LGU Extension Workers Incentives - Agricultural Extension Worker | J79: 7098 | L79: 7098 | M79: 7098 | O79: 7098 | AZ79: 7098 | BB79: 7098 | BC79: 7098 | BE79: 7098 | BO79: 3549 | BQ79: 3549 | BX79: 3549 | BZ79: 3549 | CD79: 3549 | CF79: 3549 | CJ79: 3549 | CL79: 3549 | CY79: 7098 | DA79: 7098 | DQ79: 7098 | DS79: 7098
B80: Special Events
C81: Corn and Cassava Congress | AN81: 600 | AP81: 600 | AW81: 600 | AY81: 600 | AZ81: 600 | BB81: 600 | BC81: 600 | BE81: 600 | CP81: 600 | CR81: 600 | CV81: 600 | CX81: 600 | CY81: 600 | DA81: 600 | DQ81: 600 | DS81: 600
A82: RND
B83: R&D conducted
C84: R&D New Studies Conducted - Production | J84: 4500 | L84: 4500 | M84: 4500 | O84: 4500 | V84: 450 | X84: 450 | Y84: 450 | AA84: 450 | AH84: 550 | AJ84: 550 | AK84: 550 | AM84: 550 | AZ84: 5500 | BB84: 5500 | BC84: 5500 | BE84: 5500 | BO84: 4500 | BQ84: 4500 | BX84: 4500 | BZ84: 4500 | CA84: 450 | CC84: 450 | CJ84: 450 | CL84: 450 | CM84: 550 | CO84: 550 | CV84: 550 | CX84: 550 | CY84: 5500 | DA84: 5500 | DQ84: 5500 | DS84: 5500
A85: AMEFSS
B86: Production related machinery & equipment
C87: Farm Production - Four-wheel Tractor (90 hp min) | W87: 36000 | X87: 36000 | Z87: 36000 | AA87: 36000 | BA87: 36000 | BB87: 36000 | BD87: 36000 | BE87: 36000 | CN87: 36000 | CO87: 36000 | CW87: 36000 | CX87: 36000 | CZ87: 36000 | DA87: 36000 | DR87: 36000 | DS87: 36000
C88: Farm Production - Double Row Corn seeder | K88: 2400 | L88: 2400 | N88: 2400 | O88: 2400 | BA88: 2400 | BB88: 2400 | BD88: 2400 | BE88: 2400 | CH88: 2400 | CI88: 2400 | CK88: 2400 | CL88: 2400 | CZ88: 2400 | DA88: 2400 | DR88: 2400 | DS88: 2400
C89: Farm Production - Mechanical four-row seeder | K89: 2000 | L89: 2000 | N89: 2000 | O89: 2000 | BA89: 2000 | BB89: 2000 | BD89: 2000 | BE89: 2000 | CH89: 2000 | CI89: 2000 | CK89: 2000 | CL89: 2000 | CZ89: 2000 | DA89: 2000 | DR89: 2000 | DS89: 2000
C90: Farm Production - Pneumatic Four-row seeder | K90: 1800 | L90: 1800 | N90: 1800 | O90: 1800 | BA90: 1800 | BB90: 1800 | BD90: 1800 | BE90: 1800 | CH90: 1800 | CI90: 1800 | CK90: 1800 | CL90: 1800 | CZ90: 1800 | DA90: 1800 | DR90: 1800 | DS90: 1800
C91: Farm Production - Two-row seeder | K91: 15000 | L91: 15000 | N91: 15000 | O91: 15000 | BA91: 15000 | BB91: 15000 | BD91: 15000 | BE91: 15000 | CH91: 15000 | CI91: 15000 | CK91: 15000 | CL91: 15000 | CZ91: 15000 | DA91: 15000 | DR91: 15000 | DS91: 15000
C92: Farm Production - Combine Harvester | W92: 21000 | X92: 21000 | Z92: 21000 | AA92: 21000 | BA92: 21000 | BB92: 21000 | BD92: 21000 | BE92: 21000 | CN92: 21000 | CO92: 21000 | CW92: 21000 | CX92: 21000 | CZ92: 21000 | DA92: 21000 | DR92: 21000 | DS92: 21000
B93: Postharvest related machinery & equipment
C94: Postharvest-related - Hauling Truck (not exceeding 3000cc) - four-wheel truck | W94: 11000 | X94: 11000 | Z94: 11000 | AA94: 11000 | BA94: 11000 | BB94: 11000 | BD94: 11000 | BE94: 11000 | CN94: 11000 | CO94: 11000 | CW94: 11000 | CX94: 11000 | CZ94: 11000 | DA94: 11000 | DR94: 11000 | DS94: 11000
C95: Postharvest-related - Solar Bubble Dryer | K95: 4000 | L95: 4000 | N95: 4000 | O95: 4000 | BA95: 4000 | BB95: 4000 | BD95: 4000 | BE95: 4000 | CH95: 4000 | CI95: 4000 | CK95: 4000 | CL95: 4000 | CZ95: 4000 | DA95: 4000 | DR95: 4000 | DS95: 4000
B96: Processing related machinery & equipment
C97: Postharvest-related - Corn Mill (1T/hr) | Q97: 4400 | R97: 4400 | Z97: 4400 | AA97: 4400 | BA97: 4400 | BB97: 4400 | BD97: 4400 | BE97: 4400 | CN97: 4400 | CO97: 4400 | CW97: 4400 | CX97: 4400 | CZ97: 4400 | DA97: 4400 | DR97: 4400 | DS97: 4400
C98: Postharvest facilities - Waste Water Treatment System | AI98: 20000 | AJ98: 20000 | AL98: 20000 | AM98: 20000 | BA98: 20000 | BB98: 20000 | BD98: 20000 | BE98: 20000 | CN98: 3000 | CO98: 3000 | CQ98: 4000 | CR98: 4000 | CT98: 4000 | CU98: 4000 | CW98: 11000 | CX98: 11000 | CZ98: 11000 | DA98: 11000 | DC98: 4000 | DD98: 4000 | DF98: 4000 | DG98: 4000 | DI98: 1000 | DJ98: 1000 | DL98: 9000 | DM98: 9000 | DO98: 9000 | DP98: 9000 | DR98: 20000 | DS98: 20000
B99: Postharvest facilities
C100: Postharvest facilities - Multi Crop Drying Pavement (MCDP) | W100: 5000 | X100: 5000 | Z100: 5000 | AA100: 5000 | BA100: 5000 | BB100: 5000 | BD100: 5000 | BE100: 5000 | CQ100: 5000 | CR100: 5000 | CW100: 5000 | CX100: 5000 | CZ100: 5000 | DA100: 5000 | DR100: 5000 | DS100: 5000
A101: INS
...

Sheet BED 2 SUMMARY (by PAP)
A1: CY 2025 PLAN AND BUDGET PROPOSAL
A2: BASED ON GENERAL APPROPRIATIONS ACT (GAA)
A3: BED 2: PHYSICAL
A4: NAME OF OU: | B4: ='CAPTURE SHEET - PHYSICAL'!C2 -> RFOII
A5: PRPOPOSAL/BEDS | B5: BED 2 - PHYSICAL
D7: YEAR | E7: QUARTER | F7: MONTH | G7: Values
D8: 2025 | CV8: 2025 PHYSICAL TARGET | CW8: 2025 MALE BENEF | CX8: 2025 FEMALE BENEF | CY8: 2025 AEW BENEF | CZ8: 2025 INDIV TOTAL | DA8: 2025 GROUP BENEF | DB8: Total PHYSICAL TARGET | DC8: Total MALE BENEF | DD8: Total FEMALE BENEF | DE8: Total AEW BENEF | DF8: Total INDIV TOTAL | DG8: Total GROUP BENEF
D9: 1ST QTR | V9: 1ST QTR PHYSICAL TARGET | W9: 1ST QTR MALE BENEF | X9: 1ST QTR FEMALE BENEF | Y9: 1ST QTR AEW BENEF | Z9: 1ST QTR INDIV TOTAL | AA9: 1ST QTR GROUP BENEF | AB9: 2ND QTR | AT9: 2ND QTR PHYSICAL TARGET | AU9: 2ND QTR MALE BENEF | AV9: 2ND QTR FEMALE BENEF | AW9: 2ND QTR AEW BENEF | AX9: 2ND QTR INDIV TOTAL | AY9: 2ND QTR GROUP BENEF | AZ9: 3RD QTR | BR9: 3RD QTR PHYSICAL TARGET | BS9: 3RD QTR MALE BENEF | BT9: 3RD QTR FEMALE BENEF | BU9: 3RD QTR AEW BENEF | BV9: 3RD QTR INDIV TOTAL | BW9: 3RD QTR GROUP BENEF | BX9: 4TH QTR | CP9: 4TH QTR PHYSICAL TARGET | CQ9: 4TH QTR MALE BENEF | CR9: 4TH QTR FEMALE BENEF | CS9: 4TH QTR AEW BENEF | CT9: 4TH QTR INDIV TOTAL | CU9: 4TH QTR GROUP BENEF
D10: JANUARY | J10: FEBRUARY | P10: MARCH | AB10: APRIL | AH10: MAY | AN10: JUNE | AZ10: JULY | BF10: AUGUST | BL10: SEPTEMBER | BX10: OCTOBER | CD10: NOVEMBER | CJ10: DECEMBER
A11: PREXC SUB-PROGRAM | B11: STRATEGY | C11: ACTIVITY | D11: PHYSICAL TARGET | E11: MALE BENEF | F11: FEMALE BENEF | G11: AEW BENEF | H11: INDIV TOTAL | I11: GROUP BENEF | J11: PHYSICAL TARGET | K11: MALE BENEF | L11: FEMALE BENEF | M11: AEW BENEF | N11: INDIV TOTAL | O11: GROUP BENEF | P11: PHYSICAL TARGET | Q11: MALE BENEF | R11: FEMALE BENEF | S11: AEW BENEF | T11: INDIV TOTAL | U11: GROUP BENEF | AB11: PHYSICAL TARGET | AC11: MALE BENEF | AD11: FEMALE BENEF | AE11: AEW BENEF | AF11: INDIV TOTAL | AG11: GROUP BENEF | AH11: PHYSICAL TARGET | AI11: MALE BENEF | AJ11: FEMALE BENEF | AK11: AEW BENEF | AL11: INDIV TOTAL | AM11: GROUP BENEF | AN11: PHYSICAL TARGET | AO11: MALE BENEF | AP11: FEMALE BENEF | AQ11: AEW BENEF | AR11: INDIV TOTAL | AS11: GROUP BENEF | AZ11: PHYSICAL TARGET | BA11: MALE BENEF | BB11: FEMALE BENEF | BC11: AEW BENEF | BD11: INDIV TOTAL | BE11: GROUP BENEF | BF11: PHYSICAL TARGET | BG11: MALE BENEF | BH11: FEMALE BENEF | BI11: AEW BENEF | BJ11: INDIV TOTAL | BK11: GROUP BENEF | BL11: PHYSICAL TARGET | BM11: MALE BENEF | BN11: FEMALE BENEF | BO11: AEW BENEF | BP11: INDIV TOTAL | BQ11: GROUP BENEF | BX11: PHYSICAL TARGET | BY11: MALE BENEF | BZ11: FEMALE BENEF | CA11: AEW BENEF | CB11: INDIV TOTAL | CC11: GROUP BENEF | CD11: PHYSICAL TARGET | CE11: MALE BENEF | CF11: FEMALE BENEF | CG11: AEW BENEF | CH11: INDIV TOTAL | CI11: GROUP BENEF | CJ11: PHYSICAL TARGET | CK11: MALE BENEF | CL11: FEMALE BENEF | CM11: AEW BENEF | CN11: INDIV TOTAL | CO11: GROUP BENEF
A12: PSS | J12: 3500 | N12: 0 | O12: 2 | V12: 3500 | Z12: 0 | AA12: 2 | AH12: 88000 | AL12: 0 | AN12: 1377794 | AR12: 0 | AS12: 29 | AT12: 1465794 | AX12: 0 | AY12: 29 | AZ12: 2083016 | BD12: 0 | BE12: 24 | BF12: 4220601 | BJ12: 0 | BK12: 163 | BL12: 2293350 | BP12: 0 | BQ12: 15 | BR12: 8596967 | BV12: 0 | BW12: 202 | BX12: 511001 | CB12: 0 | CC12: 6 | CD12: 324950 | CH12: 0 | CI12: 16 | CP12: 835951 | CT12: 0 | CU12: 22 | CV12: 10902212 | CZ12: 0 | DA12: 255 | DB12: 10902212 | DF12: 0 | DG12: 255
B13: OPV Seed Production
C14: Seed Production - White Corn Registered Seeds | AN14: 7000 | AR14: 0 | AS14: 21 | AT14: 7000 | AX14: 0 | AY14: 21 | AZ14: 1000 | BD14: 0 | BE14: 2 | BR14: 1000 | BV14: 0 | BW14: 2 | BX14: 6000 | CB14: 0 | CC14: 4 | CD14: 8000 | CH14: 0 | CI14: 12 | CP14: 14000 | CT14: 0 | CU14: 16 | CV14: 22000 | CZ14: 0 | DA14: 39 | DB14: 22000 | DF14: 0 | DG14: 39
B15: Corn Seed Reserve
C16: DRRM - White Corn Seed Procured OPV | AH16: 15000 | AL16: 0 | AT16: 15000 | AX16: 0 | CV16: 15000 | CZ16: 0 | DB16: 15000 | DF16: 0
C17: DRRM - Yellow Corn Seed Procured OPV | AH17: 3000 | AL17: 0 | AT17: 3000 | AX17: 0 | CV17: 3000 | CZ17: 0 | DB17: 3000 | DF17: 0
C18: DRRM - Yellow Corn Seed Procured Hybrid | AN18: 375894 | AR18: 0 | AT18: 375894 | AX18: 0 | CV18: 375894 | CZ18: 0 | DB18: 375894 | DF18: 0
B19: Recommended Corn Production Technology
C20: RCPT - Yellow Corn seeds | AZ20: 18000 | BD20: 0 | BE20: 4 | BR20: 18000 | BV20: 0 | BW20: 4 | CV20: 18000 | CZ20: 0 | DA20: 4 | DB20: 18000 | DF20: 0 | DG20: 4
C21: RCPT - Inorganic fertilizer for YC seeds | AZ21: 550000 | BD21: 0 | BE21: 4 | BR21: 550000 | BV21: 0 | BW21: 4 | CV21: 550000 | CZ21: 0 | DA21: 4 | DB21: 550000 | DF21: 0 | DG21: 4
B22: Soil amendments
C23: Biofertilizer | AZ23: 4000 | BD23: 0 | BE23: 4 | BR23: 4000 | BV23: 0 | BW23: 4 | CV23: 4000 | CZ23: 0 | DA23: 4 | DB23: 4000 | DF23: 0 | DG23: 4
C24: Soil Ameliorant | AZ24: 500000 | BD24: 0 | BE24: 4 | BR24: 500000 | BV24: 0 | BW24: 4 | CV24: 500000 | CZ24: 0 | DA24: 4 | DB24: 500000 | DF24: 0 | DG24: 4
B25: Yellow Corn Production Enhancement Project
C26: YCPEP - Yellow Corn Hybrid seeds | BF26: 486000 | BJ26: 0 | BK26: 76 | BR26: 486000 | BV26: 0 | BW26: 76 | CV26: 486000 | CZ26: 0 | DA26: 76 | DB26: 486000 | DF26: 0 | DG26: 76
C27: YCPEP - Inorganic fertilizer for YC Hybrid seeds | BF27: 2700000 | BJ27: 0 | BK27: 76 | BR27: 2700000 | BV27: 0 | BW27: 76 | CV27: 2700000 | CZ27: 0 | DA27: 76 | DB27: 2700000 | DF27: 0 | DG27: 76
B28: Pest and Disease Management
C29: DRRM - Agricultural chemicals (Insecticide in liters) | AH29: 5000 | AL29: 0 | AT29: 5000 | AX29: 0 | CV29: 5000 | CZ29: 0 | DB29: 5000 | DF29: 0
C30: DRRM - Agricultural chemicals (Rodenticides) | AH30: 50000 | AL30: 0 | AT30: 50000 | AX30: 0 | CV30: 50000 | CZ30: 0 | DB30: 50000 | DF30: 0
C31: DRRM - Agricultural chemicals (Pheromone lure) | AH31: 5000 | AL31: 0 | AT31: 5000 | AX31: 0 | CV31: 5000 | CZ31: 0 | DB31: 5000 | DF31: 0
C32: DRRM - Agricultural chemicals (Streptomycin) | AH32: 10000 | AL32: 0 | AT32: 10000 | AX32: 0 | CV32: 10000 | CZ32: 0 | DB32: 10000 | DF32: 0
B33: Cassava Production Enhancement Project
C34: Cassava Production (seed pieces) | AN34: 255000 | AR34: 0 | AS34: 2 | AT34: 255000 | AX34: 0 | AY34: 2 | AZ34: 200000 | BD34: 0 | BE34: 1 | BF34: 325000 | BJ34: 0 | BK34: 4 | BR34: 525000 | BV34: 0 | BW34: 5 | CD34: 195000 | CH34: 0 | CI34: 1 | CP34: 195000 | CT34: 0 | CU34: 1 | CV34: 975000 | CZ34: 0 | DA34: 8 | DB34: 975000 | DF34: 0 | DG34: 8
C35: Cassava Procurement (seed pieces) | AN35: 730000 | AR35: 0 | AS35: 2 | AT35: 730000 | AX35: 0 | AY35: 2 | AZ35: 800000 | BD35: 0 | BE35: 2 | BF35: 700000 | BJ35: 0 | BK35: 2 | BL35: 2270000 | BP35: 0 | BQ35: 7 | BR35: 3770000 | BV35: 0 | BW35: 11 | BX35: 500000 | CB35: 0 | CC35: 1 | CP35: 500000 | CT35: 0 | CU35: 1 | CV35: 5000000 | CZ35: 0 | DA35: 14 | DB35: 5000000 | DF35: 0 | DG35: 14
C36: Inorganic fertilizer for Cassava | AN36: 9900 | AR36: 0 | AS36: 4 | AT36: 9900 | AX36: 0 | AY36: 4 | AZ36: 10000 | BD36: 0 | BE36: 3 | BF36: 9600 | BJ36: 0 | BK36: 5 | BL36: 23350 | BP36: 0 | BQ36: 8 | BR36: 42950 | BV36: 0 | BW36: 16 | BX36: 5000 | CB36: 0 | CC36: 1 | CD36: 1950 | CH36: 0 | CI36: 1 | CP36: 6950 | CT36: 0 | CU36: 2 | CV36: 59800 | CZ36: 0 | DA36: 22 | DB36: 59800 | DF36: 0 | DG36: 22
B37: Sorghum Production Enhancement Project
C38: Seed Procurement - Sorghum | CD38: 20000 | CH38: 0 | CI38: 1 | CP38: 20000 | CT38: 0 | CU38: 1 | CV38: 20000 | CZ38: 0 | DA38: 1 | DB38: 20000 | DF38: 0 | DG38: 1
C39: Inorganic fertilizer for Sorghum | CD39: 100000 | CH39: 0 | CI39: 1 | CP39: 100000 | CT39: 0 | CU39: 1 | CV39: 100000 | CZ39: 0 | DA39: 1 | DB39: 100000 | DF39: 0 | DG39: 1
B40: Soybean Production Enhancement Project
C41: Seed Production - Soybean | J41: 1000 | N41: 0 | O41: 1 | V41: 1000 | Z41: 0 | AA41: 1 | CV41: 1000 | CZ41: 0 | DA41: 1 | DB41: 1000 | DF41: 0 | DG41: 1
C42: Inorganic fertilizer for Soybean | J42: 2500 | N42: 0 | O42: 1 | V42: 2500 | Z42: 0 | AA42: 1 | CV42: 2500 | CZ42: 0 | DA42: 1 | DB42: 2500 | DF42: 0 | DG42: 1
B43: DA Facilities Management
C44: DA Stations - Hand tractor with corn planter | AZ44: 4 | BD44: 0 | BR44: 4 | BV44: 0 | CV44: 4 | CZ44: 0 | DB44: 4 | DF44: 0
C45: DA Stations - Silage Chopper | AZ45: 4 | BD45: 0 | BR45: 4 | BV45: 0 | CV45: 4 | CZ45: 0 | DB45: 4 | DF45: 0
C46: DA Stations - Corn Mill | AZ46: 4 | BD46: 0 | BR46: 4 | BV46: 0 | CV46: 4 | CZ46: 0 | DB46: 4 | DF46: 0
C47: DA Stations - Pelletizing Machine | AZ47: 4 | BD47: 0 | BR47: 4 | BV47: 0 | CV47: 4 | CZ47: 0 | DB47: 4 | DF47: 0
C48: DA Stations - Light Cargo Truck | BF48: 1 | BJ48: 0 | BR48: 1 | BV48: 0 | CV48: 1 | CZ48: 0 | DB48: 1 | DF48: 0
C49: DA Stations - Four-wheel Tractor (90 hp min) | BX49: 1 | CB49: 0 | CP49: 1 | CT49: 0 | CV49: 1 | CZ49: 0 | DB49: 1 | DF49: 0
A50: ESETS | J50: 206 | K50: 48 | L50: 12 | N50: 60 | P50: 4 | Q50: 72 | R50: 18 | T50: 90 | V50: 210 | W50: 120 | X50: 30 | Z50: 150 | AB50: 1007 | AC50: 72 | AD50: 78 | AF50: 150 | AH50: 1008 | AI50: 120 | AJ50: 90 | AL50: 210 | AN50: 1009 | AO50: 72 | AP50: 78 | AR50: 150 | AT50: 3024 | AU50: 264 | AV50: 246 | AX50: 510 | AZ50: 2207 | BA50: 96 | BB50: 84 | BD50: 180 | BF50: 2004 | BG50: 78 | BH50: 12 | BJ50: 90 | BL50: 2003 | BM50: 78 | BN50: 12 | BP50: 90 | BR50: 6214 | BS50: 252 | BT50: 108 | BV50: 360 | BX50: 1004 | BY50: 78 | BZ50: 12 | CB50: 90 | CD50: 1005 | CH50: 0 | CJ50: 185 | CN50: 0 | CP50: 2194 | CQ50: 78 | CR50: 12 | CT50: 90 | CV50: 11642 | CW50: 714 | CX50: 396 | CZ50: 1110 | DB50: 11642 | DC50: 714 | DD50: 396 | DF50: 1110
B51: Model Farm establishment
C52: Sustainable Land Management in Corn-based Sloping Areas (SLM-Corn) | AN52: 1 | AR52: 0 | AT52: 1 | AX52: 0 | CV52: 1 | CZ52: 0 | DB52: 1 | DF52: 0
C53: Model Farm - Cassava (sites) | AZ53: 1 | BD53: 0 | BR53: 1 | BV53: 0 | CV53: 1 | CZ53: 0 | DB53: 1 | DF53: 0
C54: Model Farm - Sorghum (sites) | CD54: 1 | CH54: 0 | CP54: 1 | CT54: 0 | CV54: 1 | CZ54: 0 | DB54: 1 | DF54: 0
C55: Model Farm - Soybean (sites) | J55: 1 | N55: 0 | V55: 1 | Z55: 0 | CV55: 1 | CZ55: 0 | DB55: 1 | DF55: 0
B56: Techno Demo establishment
C57: Establishment of Corn Derby | AN57: 1 | AR57: 0 | AT57: 1 | AX57: 0 | CV57: 1 | CZ57: 0 | DB57: 1 | DF57: 0
C58: Techno-Demo Sorghum (sites) | CD58: 4 | CH58: 0 | CP58: 4 | CT58: 0 | CV58: 4 | CZ58: 0 | DB58: 4 | DF58: 0
C59: Techno-Demo Soybean (sites) | J59: 1 | N59: 0 | V59: 1 | Z59: 0 | CV59: 1 | CZ59: 0 | DB59: 1 | DF59: 0
B60: Trainings
C61: Training - Clientele-based - Corn Cluster Development training | P61: 1 | Q61: 24 | R61: 6 | T61: 30 | V61: 1 | W61: 24 | X61: 6 | Z61: 30 | AN61: 1 | AO61: 24 | AP61: 6 | AR61: 30 | AT61: 1 | AU61: 24 | AV61: 6 | AX61: 30 | AZ61: 1 | BA61: 24 | BB61: 6 | BD61: 30 | BF61: 1 | BG61: 24 | BH61: 6 | BJ61: 30 | BR61: 2 | BS61: 48 | BT61: 12 | BV61: 60 | CV61: 4 | CW61: 96 | CX61: 24 | CZ61: 120 | DB61: 4 | DC61: 96 | DD61: 24 | DF61: 120
C62: Training - Clientele-based - Corn Livelihood training | AB62: 1 | AD62: 30 | AF62: 30 | AH62: 1 | AJ62: 30 | AL62: 30 | AN62: 1 | AP62: 30 | AR62: 30 | AT62: 3 | AV62: 90 | AX62: 90 | AZ62: 1 | BB62: 30 | BD62: 30 | BR62: 1 | BT62: 30 | BV62: 30 | CV62: 4 | CX62: 120 | CZ62: 120 | DB62: 4 | DD62: 120 | DF62: 120
C63: Training - Clientele-based - Corn Production Training | AB63: 1 | AC63: 24 | AD63: 6 | AF63: 30 | AH63: 1 | AI63: 24 | AJ63: 6 | AL63: 30 | AN63: 1 | AO63: 24 | AP63: 6 | AR63: 30 | AT63: 3 | AU63: 72 | AV63: 18 | AX63: 90 | AZ63: 1 | BA63: 24 | BB63: 6 | BD63: 30 | BR63: 1 | BS63: 24 | BT63: 6 | BV63: 30 | CV63: 4 | CW63: 96 | CX63: 24 | CZ63: 120 | DB63: 4 | DC63: 96 | DD63: 24 | DF63: 120
C64: Training - Clientele-based - Integrated Pest Management Training | AH64: 2 | AI64: 48 | AJ64: 12 | AL64: 60 | AT64: 2 | AU64: 48 | AV64: 12 | AX64: 60 | BX64: 2 | BY64: 48 | BZ64: 12 | CB64: 60 | CP64: 2 | CQ64: 48 | CR64: 12 | CT64: 60 | CV64: 4 | CW64: 96 | CX64: 24 | CZ64: 120 | DB64: 4 | DC64: 96 | DD64: 24 | DF64: 120
C65: Training - Clientele-based - Training on Operation and Maintenance of Farm Machinery and Equipment | BF65: 1 | BG65: 30 | BJ65: 30 | BL65: 1 | BM65: 30 | BP65: 30 | BR65: 2 | BS65: 60 | BV65: 60 | BX65: 1 | BY65: 30 | CB65: 30 | CP65: 1 | CQ65: 30 | CT65: 30 | CV65: 3 | CW65: 90 | CZ65: 90 | DB65: 3 | DC65: 90 | DF65: 90
C66: Training - Clientele-based - Cassava Livelihood training | AB66: 1 | AD66: 30 | AF66: 30 | AH66: 1 | AJ66: 30 | AL66: 30 | AN66: 1 | AP66: 30 | AR66: 30 | AT66: 3 | AV66: 90 | AX66: 90 | AZ66: 1 | BB66: 30 | BD66: 30 | BR66: 1 | BT66: 30 | BV66: 30 | CV66: 4 | CX66: 120 | CZ66: 120 | DB66: 4 | DD66: 120 | DF66: 120
C67: Training - Clientele-based - Cassava Production Training | AB67: 1 | AC67: 24 | AD67: 6 | AF67: 30 | AH67: 1 | AI67: 24 | AJ67: 6 | AL67: 30 | AN67: 1 | AO67: 24 | AP67: 6 | AR67: 30 | AT67: 3 | AU67: 72 | AV67: 18 | AX67: 90 | AZ67: 1 | BA67: 24 | BB67: 6 | BD67: 30 | BR67: 1 | BS67: 24 | BT67: 6 | BV67: 30 | CV67: 4 | CW67: 96 | CX67: 24 | CZ67: 120 | DB67: 4 | DC67: 96 | DD67: 24 | DF67: 120
C68: Training - Clientele-based - Sorghum Production Training | AZ68: 1 | BA68: 24 | BB68: 6 | BD68: 30 | BF68: 1 | BG68: 24 | BH68: 6 | BJ68: 30 | BL68: 2 | BM68: 48 | BN68: 12 | BP68: 60 | BR68: 4 | BS68: 96 | BT68: 24 | BV68: 120 | CV68: 4 | CW68: 96 | CX68: 24 | CZ68: 120 | DB68: 4 | DC68: 96 | DD68: 24 | DF68: 120
C69: Training - Clientele-based - Soybean Production Training | J69: 2 | K69: 48 | L69: 12 | N69: 60 | P69: 2 | Q69: 48 | R69: 12 | T69: 60 | V69: 4 | W69: 96 | X69: 24 | Z69: 120 | CV69: 4 | CW69: 96 | CX69: 24 | CZ69: 120 | DB69: 4 | DC69: 96 | DD69: 24 | DF69: 120
B70: (blank)
C71: Training - Clientele-based - Corn Cluster Development training | AB71: 1 | AC71: 24 | AD71: 6 | AF71: 30 | AH71: 1 | AI71: 24 | AJ71: 6 | AL71: 30 | AT71: 2 | AU71: 48 | AV71: 12 | AX71: 60 | CV71: 2 | CW71: 48 | CX71: 12 | CZ71: 60 | DB71: 2 | DC71: 48 | DD71: 12 | DF71: 60
B72: Information, Education, and Communication Activities
C73: Advocacy and Information Materials - IEC Materials Yellow Corn | AB73: 1000 | AF73: 0 | AH73: 1000 | AL73: 0 | AN73: 1000 | AR73: 0 | AT73: 3000 | AX73: 0 | AZ73: 1000 | BD73: 0 | BF73: 1000 | BJ73: 0 | BL73: 1000 | BP73: 0 | BR73: 3000 | BV73: 0 | CV73: 6000 | CZ73: 0 | DB73: 6000 | DF73: 0
C74: Advocacy and Information Materials - IEC Materials Cassava | AZ74: 1000 | BD74: 0 | BF74: 1000 | BJ74: 0 | BL74: 1000 | BP74: 0 | BR74: 3000 | BV74: 0 | BX74: 1000 | CB74: 0 | CD74: 1000 | CH74: 0 | CP74: 2000 | CT74: 0 | CV74: 5000 | CZ74: 0 | DB74: 5000 | DF74: 0
C75: Advocacy and Information Materials - IEC Materials Sorghum | AZ75: 200 | BD75: 0 | BR75: 200 | BV75: 0 | CV75: 200 | CZ75: 0 | DB75: 200 | DF75: 0
C76: Advocacy and Information Materials - IEC Materials Soybean | J76: 200 | N76: 0 | V76: 200 | Z76: 0 | CV76: 200 | CZ76: 0 | DB76: 200 | DF76: 0
C77: Advocacy and Information Materials - Radio Plugs | J77: 1 | N77: 0 | P77: 1 | T77: 0 | V77: 2 | Z77: 0 | AB77: 1 | AF77: 0 | AH77: 1 | AL77: 0 | AN77: 1 | AR77: 0 | AT77: 3 | AX77: 0 | CV77: 5 | CZ77: 0 | DB77: 5 | DF77: 0
C78: Advocacy and Information Materials - TV Plugs | J78: 1 | N78: 0 | V78: 1 | Z78: 0 | AB78: 1 | AF78: 0 | AN78: 1 | AR78: 0 | AT78: 2 | AX78: 0 | BF78: 1 | BJ78: 0 | BR78: 1 | BV78: 0 | BX78: 1 | CB78: 0 | CP78: 1 | CT78: 0 | CV78: 5 | CZ78: 0 | DB78: 5 | DF78: 0
B79: Extension Workers Incentives
C80: Support to LGU Extension Workers Incentives - Provincial Coordinator | CJ80: 4 | CN80: 0 | CP80: 4 | CT80: 0 | CV80: 4 | CZ80: 0 | DB80: 4 | DF80: 0
C81: Support to LGU Extension Workers Incentives - Municipal Agriculturist | CJ81: 12 | CN81: 0 | CP81: 12 | CT81: 0 | CV81: 12 | CZ81: 0 | DB81: 12 | DF81: 0
C82: Support to LGU Extension Workers Incentives - Agricultural Extension Worker | CJ82: 169 | CN82: 0 | CP82: 169 | CT82: 0 | CV82: 169 | CZ82: 0 | DB82: 169 | DF82: 0
B83: Special Events
C84: Corn and Cassava Congress | CB84: 0 | CT84: 0 | CZ84: 0 | DF84: 0
A85: RND | CJ85: 1 | CN85: 0 | CP85: 1 | CT85: 0 | CV85: 1 | CZ85: 0 | DB85: 1 | DF85: 0
B86: R&D conducted
C87: R&D New Studies Conducted - Production | CJ87: 1 | CN87: 0 | CP87: 1 | CT87: 0 | CV87: 1 | CZ87: 0 | DB87: 1 | DF87: 0
A88: AMEFSS | BL88: 84 | BP88: 0 | BQ88: 27 | BR88: 84 | BV88: 0 | BW88: 27 | BX88: 31 | CB88: 0 | CC88: 31 | CD88: 2 | CH88: 0 | CI88: 2 | CJ88: 1 | CN88: 0 | CO88: 1 | CP88: 34 | CT88: 0 | CU88: 34 | CV88: 118 | CZ88: 0 | DA88: 61 | DB88: 118 | DF88: 0 | DG88: 61
B89: Production related machinery & equipment
C90: Farm Production - Four-wheel Tractor (90 hp min) | BX90: 11 | CB90: 0 | CC90: 11 | CP90: 11 | CT90: 0 | CU90: 11 | CV90: 11 | CZ90: 0 | DA90: 11 | DB90: 11 | DF90: 0 | DG90: 11
C91: Farm Production - Double Row Corn seeder | BL91: 3 | BP91: 0 | BQ91: 3 | BR91: 3 | BV91: 0 | BW91: 3 | CV91: 3 | CZ91: 0 | DA91: 3 | DB91: 3 | DF91: 0 | DG91: 3
C92: Farm Production - Mechanical four-row seeder | BL92: 10 | BP92: 0 | BQ92: 10 | BR92: 10 | BV92: 0 | BW92: 10 | CV92: 10 | CZ92: 0 | DA92: 10 | DB92: 10 | DF92: 0 | DG92: 10
C93: Farm Production - Two-row seeder | BL93: 50 | BP93: 0 | BQ93: 10 | BR93: 50 | BV93: 0 | BW93: 10 | CV93: 50 | CZ93: 0 | DA93: 10 | DB93: 50 | DF93: 0 | DG93: 10
C94: Farm Production - Pneumatic Four-row seeder | BL94: 1 | BP94: 0 | BQ94: 1 | BR94: 1 | BV94: 0 | BW94: 1 | CV94: 1 | CZ94: 0 | DA94: 1 | DB94: 1 | DF94: 0 | DG94: 1
C95: Farm Production - Combine Harvester | BX95: 10 | CB95: 0 | CC95: 10 | CP95: 10 | CT95: 0 | CU95: 10 | CV95: 10 | CZ95: 0 | DA95: 10 | DB95: 10 | DF95: 0 | DG95: 10
B96: Postharvest related machinery & equipment
C97: Postharvest-related - Hauling Truck (not exceeding 3000cc) - four-wheel truck | BX97: 5 | CB97: 0 | CC97: 5 | CP97: 5 | CT97: 0 | CU97: 5 | CV97: 5 | CZ97: 0 | DA97: 5 | DB97: 5 | DF97: 0 | DG97: 5
C98: Postharvest-related - Solar Bubble Dryer | BL98: 20 | BP98: 0 | BQ98: 3 | BR98: 20 | BV98: 0 | BW98: 3 | CV98: 20 | CZ98: 0 | DA98: 3 | DB98: 20 | DF98: 0 | DG98: 3
B99: Processing related machinery & equipment
C100: Postharvest-related - Corn Mill (1T/hr) | BX100: 2 | CB100: 0 | CC100: 2 | CP100: 2 | CT100: 0 | CU100: 2 | CV100: 2 | CZ100: 0 | DA100: 2 | DB100: 2 | DF100: 0 | DG100: 2
C101: Postharvest facilities - Waste Water Treatment System | CJ101: 1 | CN101: 0 | CO101: 1 | CP101: 1 | CT101: 0 | CU101: 1 | CV101: 1 | CZ101: 0 | DA101: 1 | DB101: 1 | DF101: 0 | DG101: 1
...

Sheet BED13 Checking
D5: PRPOPOSAL/BEDS | E5: Values
D6: PROPOSAL | G6: BED 1 - OBLIGATION | J6: BED 3 - DISBURSEMENT | N6: vs BED 1 | R6: vs BED 3 | V6: BED 1 vs BED 3
A7: PREXC SUB-PROGRAM | B7: STRATEGY | C7: ACTIVITY | D7: MOOE | E7: CO | F7: TOTAL | G7: MOOE | H7: CO | I7: TOTAL | J7: MOOE | K7: CO | L7: TOTAL | N7: MOOE | O7: CO | P7: TOTAL | R7: MOOE | S7: CO | T7: TOTAL | V7: MOOE | W7: CO | X7: TOTAL
A8: PSS | D8: 780300 | E8: 8140 | F8: 788440 | G8: 780300 | H8: 8140 | I8: 788440 | J8: 780300 | K8: 8140 | L8: 788440 | N8: =+D8-G8 -> 0 | O8: =+E8-H8 -> 0 | P8: =+F8-I8 -> 0 | R8: =+D8-J8 -> 0 | S8: =+E8-K8 -> 0 | T8: =+F8-L8 -> 0 | V8: =+G8-J8 -> 0 | W8: =+H8-K8 -> 0 | X8: =+I8-L8 -> 0
B9: OPV Seed Production | D9: 1106 | F9: 1106 | G9: 1105 | I9: 1105 | J9: 1105 | L9: 1105 | N9: =+D9-G9 -> 1 | O9: =+E9-H9 -> 0 | P9: =+F9-I9 -> 1 | R9: =+D9-J9 -> 1 | S9: =+E9-K9 -> 0 | T9: =+F9-L9 -> 1 | V9: =+G9-J9 -> 0 | W9: =+H9-K9 -> 0 | X9: =+I9-L9 -> 0
C10: Seed Production - White Corn Registered Seeds | D10: 1106 | F10: 1106 | G10: 1105 | I10: 1105 | J10: 1105 | L10: 1105 | N10: =+D10-G10 -> 1 | O10: =+E10-H10 -> 0 | P10: =+F10-I10 -> 1 | R10: =+D10-J10 -> 1 | S10: =+E10-K10 -> 0 | T10: =+F10-L10 -> 1 | V10: =+G10-J10 -> 0 | W10: =+H10-K10 -> 0 | X10: =+I10-L10 -> 0
B11: Corn Seed Reserve | D11: 252396 | F11: 252396 | G11: 252396 | I11: 252396 | J11: 252396 | L11: 252396 | N11: =+D11-G11 -> 0 | O11: =+E11-H11 -> 0 | P11: =+F11-I11 -> 0 | R11: =+D11-J11 -> 0 | S11: =+E11-K11 -> 0 | T11: =+F11-L11 -> 0 | V11: =+G11-J11 -> 0 | W11: =+H11-K11 -> 0 | X11: =+I11-L11 -> 0
C12: DRRM - White Corn Seed Procured OPV | D12: 1500 | F12: 1500 | G12: 1500 | I12: 1500 | J12: 1500 | L12: 1500 | N12: =+D12-G12 -> 0 | O12: =+E12-H12 -> 0 | P12: =+F12-I12 -> 0 | R12: =+D12-J12 -> 0 | S12: =+E12-K12 -> 0 | T12: =+F12-L12 -> 0 | V12: =+G12-J12 -> 0 | W12: =+H12-K12 -> 0 | X12: =+I12-L12 -> 0
C13: DRRM - Yellow Corn Seed Procured OPV | D13: 300 | F13: 300 | G13: 300 | I13: 300 | J13: 300 | L13: 300 | N13: =+D13-G13 -> 0 | O13: =+E13-H13 -> 0 | P13: =+F13-I13 -> 0 | R13: =+D13-J13 -> 0 | S13: =+E13-K13 -> 0 | T13: =+F13-L13 -> 0 | V13: =+G13-J13 -> 0 | W13: =+H13-K13 -> 0 | X13: =+I13-L13 -> 0
C14: DRRM - Yellow Corn Seed Procured Hybrid | D14: 250596 | F14: 250596 | G14: 250596 | I14: 250596 | J14: 250596 | L14: 250596 | N14: =+D14-G14 -> 0 | O14: =+E14-H14 -> 0 | P14: =+F14-I14 -> 0 | R14: =+D14-J14 -> 0 | S14: =+E14-K14 -> 0 | T14: =+F14-L14 -> 0 | V14: =+G14-J14 -> 0 | W14: =+H14-K14 -> 0 | X14: =+I14-L14 -> 0
B15: Recommended Corn Production Technology | D15: 36750 | F15: 36750 | G15: 36750 | I15: 36750 | J15: 36750 | L15: 36750 | N15: =+D15-G15 -> 0 | O15: =+E15-H15 -> 0 | P15: =+F15-I15 -> 0 | R15: =+D15-J15 -> 0 | S15: =+E15-K15 -> 0 | T15: =+F15-L15 -> 0 | V15: =+G15-J15 -> 0 | W15: =+H15-K15 -> 0 | X15: =+I15-L15 -> 0
C16: RCPT - Yellow Corn seeds | D16: 12000 | F16: 12000 | G16: 12000 | I16: 12000 | J16: 12000 | L16: 12000 | N16: =+D16-G16 -> 0 | O16: =+E16-H16 -> 0 | P16: =+F16-I16 -> 0 | R16: =+D16-J16 -> 0 | S16: =+E16-K16 -> 0 | T16: =+F16-L16 -> 0 | V16: =+G16-J16 -> 0 | W16: =+H16-K16 -> 0 | X16: =+I16-L16 -> 0
C17: RCPT - Inorganic fertilizer for YC seeds | D17: 24750 | F17: 24750 | G17: 24750 | I17: 24750 | J17: 24750 | L17: 24750 | N17: =+D17-G17 -> 0 | O17: =+E17-H17 -> 0 | P17: =+F17-I17 -> 0 | R17: =+D17-J17 -> 0 | S17: =+E17-K17 -> 0 | T17: =+F17-L17 -> 0 | V17: =+G17-J17 -> 0 | W17: =+H17-K17 -> 0 | X17: =+I17-L17 -> 0
B18: Soil amendments | D18: 12720 | F18: 12720 | G18: 12720 | I18: 12720 | J18: 12720 | L18: 12720 | N18: =+D18-G18 -> 0 | O18: =+E18-H18 -> 0 | P18: =+F18-I18 -> 0 | R18: =+D18-J18 -> 0 | S18: =+E18-K18 -> 0 | T18: =+F18-L18 -> 0 | V18: =+G18-J18 -> 0 | W18: =+H18-K18 -> 0 | X18: =+I18-L18 -> 0
C19: Biofertilizer | D19: 2720 | F19: 2720 | G19: 2720 | I19: 2720 | J19: 2720 | L19: 2720 | N19: =+D19-G19 -> 0 | O19: =+E19-H19 -> 0 | P19: =+F19-I19 -> 0 | R19: =+D19-J19 -> 0 | S19: =+E19-K19 -> 0 | T19: =+F19-L19 -> 0 | V19: =+G19-J19 -> 0 | W19: =+H19-K19 -> 0 | X19: =+I19-L19 -> 0
C20: Soil Ameliorant | D20: 10000 | F20: 10000 | G20: 10000 | I20: 10000 | J20: 10000 | L20: 10000 | N20: =+D20-G20 -> 0 | O20: =+E20-H20 -> 0 | P20: =+F20-I20 -> 0 | R20: =+D20-J20 -> 0 | S20: =+E20-K20 -> 0 | T20: =+F20-L20 -> 0 | V20: =+G20-J20 -> 0 | W20: =+H20-K20 -> 0 | X20: =+I20-L20 -> 0
B21: Yellow Corn Production Enhancement Project | D21: 445500 | F21: 445500 | G21: 445500 | I21: 445500 | J21: 445500 | L21: 445500 | N21: =+D21-G21 -> 0 | O21: =+E21-H21 -> 0 | P21: =+F21-I21 -> 0 | R21: =+D21-J21 -> 0 | S21: =+E21-K21 -> 0 | T21: =+F21-L21 -> 0 | V21: =+G21-J21 -> 0 | W21: =+H21-K21 -> 0 | X21: =+I21-L21 -> 0
C22: YCPEP - Yellow Corn Hybrid seeds | D22: 324000 | F22: 324000 | G22: 324000 | I22: 324000 | J22: 324000 | L22: 324000 | N22: =+D22-G22 -> 0 | O22: =+E22-H22 -> 0 | P22: =+F22-I22 -> 0 | R22: =+D22-J22 -> 0 | S22: =+E22-K22 -> 0 | T22: =+F22-L22 -> 0 | V22: =+G22-J22 -> 0 | W22: =+H22-K22 -> 0 | X22: =+I22-L22 -> 0
C23: YCPEP - Inorganic fertilizer for YC Hybrid seeds | D23: 121500 | F23: 121500 | G23: 121500 | I23: 121500 | J23: 121500 | L23: 121500 | N23: =+D23-G23 -> 0 | O23: =+E23-H23 -> 0 | P23: =+F23-I23 -> 0 | R23: =+D23-J23 -> 0 | S23: =+E23-K23 -> 0 | T23: =+F23-L23 -> 0 | V23: =+G23-J23 -> 0 | W23: =+H23-K23 -> 0 | X23: =+I23-L23 -> 0
B24: Pest and Disease Management | D24: 14250 | F24: 14250 | G24: 14250 | I24: 14250 | J24: 14250 | L24: 14250 | N24: =+D24-G24 -> 0 | O24: =+E24-H24 -> 0 | P24: =+F24-I24 -> 0 | R24: =+D24-J24 -> 0 | S24: =+E24-K24 -> 0 | T24: =+F24-L24 -> 0 | V24: =+G24-J24 -> 0 | W24: =+H24-K24 -> 0 | X24: =+I24-L24 -> 0
C25: DRRM - Agricultural chemicals (Insecticide in liters) | D25: 6000 | F25: 6000 | G25: 6000 | I25: 6000 | J25: 6000 | L25: 6000 | N25: =+D25-G25 -> 0 | O25: =+E25-H25 -> 0 | P25: =+F25-I25 -> 0 | R25: =+D25-J25 -> 0 | S25: =+E25-K25 -> 0 | T25: =+F25-L25 -> 0 | V25: =+G25-J25 -> 0 | W25: =+H25-K25 -> 0 | X25: =+I25-L25 -> 0
C26: DRRM - Agricultural chemicals (Rodenticides) | D26: 1500 | F26: 1500 | G26: 1500 | I26: 1500 | J26: 1500 | L26: 1500 | N26: =+D26-G26 -> 0 | O26: =+E26-H26 -> 0 | P26: =+F26-I26 -> 0 | R26: =+D26-J26 -> 0 | S26: =+E26-K26 -> 0 | T26: =+F26-L26 -> 0 | V26: =+G26-J26 -> 0 | W26: =+H26-K26 -> 0 | X26: =+I26-L26 -> 0
C27: DRRM - Agricultural chemicals (Pheromone lure) | D27: 2750 | F27: 2750 | G27: 2750 | I27: 2750 | J27: 2750 | L27: 2750 | N27: =+D27-G27 -> 0 | O27: =+E27-H27 -> 0 | P27: =+F27-I27 -> 0 | R27: =+D27-J27 -> 0 | S27: =+E27-K27 -> 0 | T27: =+F27-L27 -> 0 | V27: =+G27-J27 -> 0 | W27: =+H27-K27 -> 0 | X27: =+I27-L27 -> 0
C28: DRRM - Agricultural chemicals (Streptomycin) | D28: 4000 | F28: 4000 | G28: 4000 | I28: 4000 | J28: 4000 | L28: 4000 | N28: =+D28-G28 -> 0 | O28: =+E28-H28 -> 0 | P28: =+F28-I28 -> 0 | R28: =+D28-J28 -> 0 | S28: =+E28-K28 -> 0 | T28: =+F28-L28 -> 0 | V28: =+G28-J28 -> 0 | W28: =+H28-K28 -> 0 | X28: =+I28-L28 -> 0
B29: Cassava Production Enhancement Project | D29: 11166 | F29: 11166 | G29: 11166 | I29: 11166 | J29: 11166 | L29: 11166 | N29: =+D29-G29 -> 0 | O29: =+E29-H29 -> 0 | P29: =+F29-I29 -> 0 | R29: =+D29-J29 -> 0 | S29: =+E29-K29 -> 0 | T29: =+F29-L29 -> 0 | V29: =+G29-J29 -> 0 | W29: =+H29-K29 -> 0 | X29: =+I29-L29 -> 0
C30: Cassava Production (seed pieces) | D30: 975 | F30: 975 | G30: 975 | I30: 975 | J30: 975 | L30: 975 | N30: =+D30-G30 -> 0 | O30: =+E30-H30 -> 0 | P30: =+F30-I30 -> 0 | R30: =+D30-J30 -> 0 | S30: =+E30-K30 -> 0 | T30: =+F30-L30 -> 0 | V30: =+G30-J30 -> 0 | W30: =+H30-K30 -> 0 | X30: =+I30-L30 -> 0
C31: Cassava Procurement (seed pieces) | D31: 7500 | F31: 7500 | G31: 7500 | I31: 7500 | J31: 7500 | L31: 7500 | N31: =+D31-G31 -> 0 | O31: =+E31-H31 -> 0 | P31: =+F31-I31 -> 0 | R31: =+D31-J31 -> 0 | S31: =+E31-K31 -> 0 | T31: =+F31-L31 -> 0 | V31: =+G31-J31 -> 0 | W31: =+H31-K31 -> 0 | X31: =+I31-L31 -> 0
C32: Inorganic fertilizer for Cassava | D32: 2691 | F32: 2691 | G32: 2691 | I32: 2691 | J32: 2691 | L32: 2691 | N32: =+D32-G32 -> 0 | O32: =+E32-H32 -> 0 | P32: =+F32-I32 -> 0 | R32: =+D32-J32 -> 0 | S32: =+E32-K32 -> 0 | T32: =+F32-L32 -> 0 | V32: =+G32-J32 -> 0 | W32: =+H32-K32 -> 0 | X32: =+I32-L32 -> 0
B33: Sorghum Production Enhancement Project | D33: 6250 | F33: 6250 | G33: 6250 | I33: 6250 | J33: 6250 | L33: 6250 | N33: =+D33-G33 -> 0 | O33: =+E33-H33 -> 0 | P33: =+F33-I33 -> 0 | R33: =+D33-J33 -> 0 | S33: =+E33-K33 -> 0 | T33: =+F33-L33 -> 0 | V33: =+G33-J33 -> 0 | W33: =+H33-K33 -> 0 | X33: =+I33-L33 -> 0
C34: Seed Procurement - Sorghum | D34: 1750 | F34: 1750 | G34: 1750 | I34: 1750 | J34: 1750 | L34: 1750 | N34: =+D34-G34 -> 0 | O34: =+E34-H34 -> 0 | P34: =+F34-I34 -> 0 | R34: =+D34-J34 -> 0 | S34: =+E34-K34 -> 0 | T34: =+F34-L34 -> 0 | V34: =+G34-J34 -> 0 | W34: =+H34-K34 -> 0 | X34: =+I34-L34 -> 0
C35: Inorganic fertilizer for Sorghum | D35: 4500 | F35: 4500 | G35: 4500 | I35: 4500 | J35: 4500 | L35: 4500 | N35: =+D35-G35 -> 0 | O35: =+E35-H35 -> 0 | P35: =+F35-I35 -> 0 | R35: =+D35-J35 -> 0 | S35: =+E35-K35 -> 0 | T35: =+F35-L35 -> 0 | V35: =+G35-J35 -> 0 | W35: =+H35-K35 -> 0 | X35: =+I35-L35 -> 0
B36: Soybean Production Enhancement Project | D36: 162 | F36: 162 | G36: 163 | I36: 163 | J36: 163 | L36: 163 | N36: =+D36-G36 -> -1 | O36: =+E36-H36 -> 0 | P36: =+F36-I36 -> -1 | R36: =+D36-J36 -> -1 | S36: =+E36-K36 -> 0 | T36: =+F36-L36 -> -1 | V36: =+G36-J36 -> 0 | W36: =+H36-K36 -> 0 | X36: =+I36-L36 -> 0
C37: Seed Production - Soybean | D37: 50 | F37: 50 | G37: 50 | I37: 50 | J37: 50 | L37: 50 | N37: =+D37-G37 -> 0 | O37: =+E37-H37 -> 0 | P37: =+F37-I37 -> 0 | R37: =+D37-J37 -> 0 | S37: =+E37-K37 -> 0 | T37: =+F37-L37 -> 0 | V37: =+G37-J37 -> 0 | W37: =+H37-K37 -> 0 | X37: =+I37-L37 -> 0
C38: Inorganic fertilizer for Soybean | D38: 112 | F38: 112 | G38: 113 | I38: 113 | J38: 113 | L38: 113 | N38: =+D38-G38 -> -1 | O38: =+E38-H38 -> 0 | P38: =+F38-I38 -> -1 | R38: =+D38-J38 -> -1 | S38: =+E38-K38 -> 0 | T38: =+F38-L38 -> -1 | V38: =+G38-J38 -> 0 | W38: =+H38-K38 -> 0 | X38: =+I38-L38 -> 0
B39: DA Facilities Management | E39: 8140 | F39: 8140 | H39: 8140 | I39: 8140 | K39: 8140 | L39: 8140 | N39: =+D39-G39 -> 0 | O39: =+E39-H39 -> 0 | P39: =+F39-I39 -> 0 | R39: =+D39-J39 -> 0 | S39: =+E39-K39 -> 0 | T39: =+F39-L39 -> 0 | V39: =+G39-J39 -> 0 | W39: =+H39-K39 -> 0 | X39: =+I39-L39 -> 0
C40: DA Stations - Hand tractor with corn planter | E40: 1200 | F40: 1200 | H40: 1200 | I40: 1200 | K40: 1200 | L40: 1200 | N40: =+D40-G40 -> 0 | O40: =+E40-H40 -> 0 | P40: =+F40-I40 -> 0 | R40: =+D40-J40 -> 0 | S40: =+E40-K40 -> 0 | T40: =+F40-L40 -> 0 | V40: =+G40-J40 -> 0 | W40: =+H40-K40 -> 0 | X40: =+I40-L40 -> 0
C41: DA Stations - Silage Chopper | E41: 240 | F41: 240 | H41: 240 | I41: 240 | K41: 240 | L41: 240 | N41: =+D41-G41 -> 0 | O41: =+E41-H41 -> 0 | P41: =+F41-I41 -> 0 | R41: =+D41-J41 -> 0 | S41: =+E41-K41 -> 0 | T41: =+F41-L41 -> 0 | V41: =+G41-J41 -> 0 | W41: =+H41-K41 -> 0 | X41: =+I41-L41 -> 0
C42: DA Stations - Corn Mill | E42: 1200 | F42: 1200 | H42: 1200 | I42: 1200 | K42: 1200 | L42: 1200 | N42: =+D42-G42 -> 0 | O42: =+E42-H42 -> 0 | P42: =+F42-I42 -> 0 | R42: =+D42-J42 -> 0 | S42: =+E42-K42 -> 0 | T42: =+F42-L42 -> 0 | V42: =+G42-J42 -> 0 | W42: =+H42-K42 -> 0 | X42: =+I42-L42 -> 0
C43: DA Stations - Pelletizing Machine | E43: 300 | F43: 300 | H43: 300 | I43: 300 | K43: 300 | L43: 300 | N43: =+D43-G43 -> 0 | O43: =+E43-H43 -> 0 | P43: =+F43-I43 -> 0 | R43: =+D43-J43 -> 0 | S43: =+E43-K43 -> 0 | T43: =+F43-L43 -> 0 | V43: =+G43-J43 -> 0 | W43: =+H43-K43 -> 0 | X43: =+I43-L43 -> 0
C44: DA Stations - Light Cargo Truck | E44: 2100 | F44: 2100 | H44: 2100 | I44: 2100 | K44: 2100 | L44: 2100 | N44: =+D44-G44 -> 0 | O44: =+E44-H44 -> 0 | P44: =+F44-I44 -> 0 | R44: =+D44-J44 -> 0 | S44: =+E44-K44 -> 0 | T44: =+F44-L44 -> 0 | V44: =+G44-J44 -> 0 | W44: =+H44-K44 -> 0 | X44: =+I44-L44 -> 0
C45: DA Stations - Four-wheel Tractor (90 hp min) | E45: 3100 | F45: 3100 | H45: 3100 | I45: 3100 | K45: 3100 | L45: 3100 | N45: =+D45-G45 -> 0 | O45: =+E45-H45 -> 0 | P45: =+F45-I45 -> 0 | R45: =+D45-J45 -> 0 | S45: =+E45-K45 -> 0 | T45: =+F45-L45 -> 0 | V45: =+G45-J45 -> 0 | W45: =+H45-K45 -> 0 | X45: =+I45-L45 -> 0
A46: ESETS | D46: 17156 | F46: 17156 | G46: 17156 | I46: 17156 | J46: 17156 | L46: 17156 | N46: =+D46-G46 -> 0 | O46: =+E46-H46 -> 0 | P46: =+F46-I46 -> 0 | R46: =+D46-J46 -> 0 | S46: =+E46-K46 -> 0 | T46: =+F46-L46 -> 0 | V46: =+G46-J46 -> 0 | W46: =+H46-K46 -> 0 | X46: =+I46-L46 -> 0
B47: Model Farm establishment | D47: 4260 | F47: 4260 | G47: 4260 | I47: 4260 | J47: 4260 | L47: 4260 | N47: =+D47-G47 -> 0 | O47: =+E47-H47 -> 0 | P47: =+F47-I47 -> 0 | R47: =+D47-J47 -> 0 | S47: =+E47-K47 -> 0 | T47: =+F47-L47 -> 0 | V47: =+G47-J47 -> 0 | W47: =+H47-K47 -> 0 | X47: =+I47-L47 -> 0
C48: Sustainable Land Management in Corn-based Sloping Areas (SLM-Corn) | D48: 3000 | F48: 3000 | G48: 3000 | I48: 3000 | J48: 3000 | L48: 3000 | N48: =+D48-G48 -> 0 | O48: =+E48-H48 -> 0 | P48: =+F48-I48 -> 0 | R48: =+D48-J48 -> 0 | S48: =+E48-K48 -> 0 | T48: =+F48-L48 -> 0 | V48: =+G48-J48 -> 0 | W48: =+H48-K48 -> 0 | X48: =+I48-L48 -> 0
C49: Model Farm - Cassava (sites) | D49: 650 | F49: 650 | G49: 650 | I49: 650 | J49: 650 | L49: 650 | N49: =+D49-G49 -> 0 | O49: =+E49-H49 -> 0 | P49: =+F49-I49 -> 0 | R49: =+D49-J49 -> 0 | S49: =+E49-K49 -> 0 | T49: =+F49-L49 -> 0 | V49: =+G49-J49 -> 0 | W49: =+H49-K49 -> 0 | X49: =+I49-L49 -> 0
C50: Model Farm - Sorghum (sites) | D50: 280 | F50: 280 | G50: 280 | I50: 280 | J50: 280 | L50: 280 | N50: =+D50-G50 -> 0 | O50: =+E50-H50 -> 0 | P50: =+F50-I50 -> 0 | R50: =+D50-J50 -> 0 | S50: =+E50-K50 -> 0 | T50: =+F50-L50 -> 0 | V50: =+G50-J50 -> 0 | W50: =+H50-K50 -> 0 | X50: =+I50-L50 -> 0
C51: Model Farm - Soybean (sites) | D51: 330 | F51: 330 | G51: 330 | I51: 330 | J51: 330 | L51: 330 | N51: =+D51-G51 -> 0 | O51: =+E51-H51 -> 0 | P51: =+F51-I51 -> 0 | R51: =+D51-J51 -> 0 | S51: =+E51-K51 -> 0 | T51: =+F51-L51 -> 0 | V51: =+G51-J51 -> 0 | W51: =+H51-K51 -> 0 | X51: =+I51-L51 -> 0
B52: Techno Demo establishment | D52: 1360 | F52: 1360 | G52: 1360 | I52: 1360 | J52: 1360 | L52: 1360 | N52: =+D52-G52 -> 0 | O52: =+E52-H52 -> 0 | P52: =+F52-I52 -> 0 | R52: =+D52-J52 -> 0 | S52: =+E52-K52 -> 0 | T52: =+F52-L52 -> 0 | V52: =+G52-J52 -> 0 | W52: =+H52-K52 -> 0 | X52: =+I52-L52 -> 0
C53: Establishment of Corn Derby | D53: 1000 | F53: 1000 | G53: 1000 | I53: 1000 | J53: 1000 | L53: 1000 | N53: =+D53-G53 -> 0 | O53: =+E53-H53 -> 0 | P53: =+F53-I53 -> 0 | R53: =+D53-J53 -> 0 | S53: =+E53-K53 -> 0 | T53: =+F53-L53 -> 0 | V53: =+G53-J53 -> 0 | W53: =+H53-K53 -> 0 | X53: =+I53-L53 -> 0
C54: Techno-Demo Sorghum (sites) | D54: 160 | F54: 160 | G54: 160 | I54: 160 | J54: 160 | L54: 160 | N54: =+D54-G54 -> 0 | O54: =+E54-H54 -> 0 | P54: =+F54-I54 -> 0 | R54: =+D54-J54 -> 0 | S54: =+E54-K54 -> 0 | T54: =+F54-L54 -> 0 | V54: =+G54-J54 -> 0 | W54: =+H54-K54 -> 0 | X54: =+I54-L54 -> 0
C55: Techno-Demo Soybean (sites) | D55: 200 | F55: 200 | G55: 200 | I55: 200 | J55: 200 | L55: 200 | N55: =+D55-G55 -> 0 | O55: =+E55-H55 -> 0 | P55: =+F55-I55 -> 0 | R55: =+D55-J55 -> 0 | S55: =+E55-K55 -> 0 | T55: =+F55-L55 -> 0 | V55: =+G55-J55 -> 0 | W55: =+H55-K55 -> 0 | X55: =+I55-L55 -> 0
B56: Trainings | D56: 1870 | F56: 1870 | G56: 1870 | I56: 1870 | J56: 1870 | L56: 1870 | N56: =+D56-G56 -> 0 | O56: =+E56-H56 -> 0 | P56: =+F56-I56 -> 0 | R56: =+D56-J56 -> 0 | S56: =+E56-K56 -> 0 | T56: =+F56-L56 -> 0 | V56: =+G56-J56 -> 0 | W56: =+H56-K56 -> 0 | X56: =+I56-L56 -> 0
C57: Training - Clientele-based - Corn Cluster Development training | D57: 210 | F57: 210 | G57: 210 | I57: 210 | J57: 210 | L57: 210 | N57: =+D57-G57 -> 0 | O57: =+E57-H57 -> 0 | P57: =+F57-I57 -> 0 | R57: =+D57-J57 -> 0 | S57: =+E57-K57 -> 0 | T57: =+F57-L57 -> 0 | V57: =+G57-J57 -> 0 | W57: =+H57-K57 -> 0 | X57: =+I57-L57 -> 0
C58: Training - Clientele-based - Corn Livelihood training | D58: 200 | F58: 200 | G58: 200 | I58: 200 | J58: 200 | L58: 200 | N58: =+D58-G58 -> 0 | O58: =+E58-H58 -> 0 | P58: =+F58-I58 -> 0 | R58: =+D58-J58 -> 0 | S58: =+E58-K58 -> 0 | T58: =+F58-L58 -> 0 | V58: =+G58-J58 -> 0 | W58: =+H58-K58 -> 0 | X58: =+I58-L58 -> 0
C59: Training - Clientele-based - Corn Production Training | D59: 140 | F59: 140 | G59: 140 | I59: 140 | J59: 140 | L59: 140 | N59: =+D59-G59 -> 0 | O59: =+E59-H59 -> 0 | P59: =+F59-I59 -> 0 | R59: =+D59-J59 -> 0 | S59: =+E59-K59 -> 0 | T59: =+F59-L59 -> 0 | V59: =+G59-J59 -> 0 | W59: =+H59-K59 -> 0 | X59: =+I59-L59 -> 0
C60: Training - Clientele-based - Integrated Pest Management Training | D60: 400 | F60: 400 | G60: 400 | I60: 400 | J60: 400 | L60: 400 | N60: =+D60-G60 -> 0 | O60: =+E60-H60 -> 0 | P60: =+F60-I60 -> 0 | R60: =+D60-J60 -> 0 | S60: =+E60-K60 -> 0 | T60: =+F60-L60 -> 0 | V60: =+G60-J60 -> 0 | W60: =+H60-K60 -> 0 | X60: =+I60-L60 -> 0
C61: Training - Clientele-based - Training on Operation and Maintenance of Farm Machinery and Equipment | D61: 300 | F61: 300 | G61: 300 | I61: 300 | J61: 300 | L61: 300 | N61: =+D61-G61 -> 0 | O61: =+E61-H61 -> 0 | P61: =+F61-I61 -> 0 | R61: =+D61-J61 -> 0 | S61: =+E61-K61 -> 0 | T61: =+F61-L61 -> 0 | V61: =+G61-J61 -> 0 | W61: =+H61-K61 -> 0 | X61: =+I61-L61 -> 0
C62: Training - Clientele-based - Cassava Livelihood training | D62: 200 | F62: 200 | G62: 200 | I62: 200 | J62: 200 | L62: 200 | N62: =+D62-G62 -> 0 | O62: =+E62-H62 -> 0 | P62: =+F62-I62 -> 0 | R62: =+D62-J62 -> 0 | S62: =+E62-K62 -> 0 | T62: =+F62-L62 -> 0 | V62: =+G62-J62 -> 0 | W62: =+H62-K62 -> 0 | X62: =+I62-L62 -> 0
C63: Training - Clientele-based - Cassava Production Training | D63: 140 | F63: 140 | G63: 140 | I63: 140 | J63: 140 | L63: 140 | N63: =+D63-G63 -> 0 | O63: =+E63-H63 -> 0 | P63: =+F63-I63 -> 0 | R63: =+D63-J63 -> 0 | S63: =+E63-K63 -> 0 | T63: =+F63-L63 -> 0 | V63: =+G63-J63 -> 0 | W63: =+H63-K63 -> 0 | X63: =+I63-L63 -> 0
C64: Training - Clientele-based - Sorghum Production Training | D64: 140 | F64: 140 | G64: 140 | I64: 140 | J64: 140 | L64: 140 | N64: =+D64-G64 -> 0 | O64: =+E64-H64 -> 0 | P64: =+F64-I64 -> 0 | R64: =+D64-J64 -> 0 | S64: =+E64-K64 -> 0 | T64: =+F64-L64 -> 0 | V64: =+G64-J64 -> 0 | W64: =+H64-K64 -> 0 | X64: =+I64-L64 -> 0
C65: Training - Clientele-based - Soybean Production Training | D65: 140 | F65: 140 | G65: 140 | I65: 140 | J65: 140 | L65: 140 | N65: =+D65-G65 -> 0 | O65: =+E65-H65 -> 0 | P65: =+F65-I65 -> 0 | R65: =+D65-J65 -> 0 | S65: =+E65-K65 -> 0 | T65: =+F65-L65 -> 0 | V65: =+G65-J65 -> 0 | W65: =+H65-K65 -> 0 | X65: =+I65-L65 -> 0
B66: Information, Education, and Communication Activities | D66: 1200 | F66: 1200 | G66: 1200 | I66: 1200 | J66: 1200 | L66: 1200 | N66: =+D66-G66 -> 0 | O66: =+E66-H66 -> 0 | P66: =+F66-I66 -> 0 | R66: =+D66-J66 -> 0 | S66: =+E66-K66 -> 0 | T66: =+F66-L66 -> 0 | V66: =+G66-J66 -> 0 | W66: =+H66-K66 -> 0 | X66: =+I66-L66 -> 0
C67: Advocacy and Information Materials - IEC Materials Yellow Corn | D67: 200 | F67: 200 | G67: 200 | I67: 200 | J67: 200 | L67: 200 | N67: =+D67-G67 -> 0 | O67: =+E67-H67 -> 0 | P67: =+F67-I67 -> 0 | R67: =+D67-J67 -> 0 | S67: =+E67-K67 -> 0 | T67: =+F67-L67 -> 0 | V67: =+G67-J67 -> 0 | W67: =+H67-K67 -> 0 | X67: =+I67-L67 -> 0
C68: Advocacy and Information Materials - IEC Materials Cassava | D68: 150 | F68: 150 | G68: 150 | I68: 150 | J68: 150 | L68: 150 | N68: =+D68-G68 -> 0 | O68: =+E68-H68 -> 0 | P68: =+F68-I68 -> 0 | R68: =+D68-J68 -> 0 | S68: =+E68-K68 -> 0 | T68: =+F68-L68 -> 0 | V68: =+G68-J68 -> 0 | W68: =+H68-K68 -> 0 | X68: =+I68-L68 -> 0
C69: Advocacy and Information Materials - IEC Materials Sorghum | D69: 50 | F69: 50 | G69: 50 | I69: 50 | J69: 50 | L69: 50 | N69: =+D69-G69 -> 0 | O69: =+E69-H69 -> 0 | P69: =+F69-I69 -> 0 | R69: =+D69-J69 -> 0 | S69: =+E69-K69 -> 0 | T69: =+F69-L69 -> 0 | V69: =+G69-J69 -> 0 | W69: =+H69-K69 -> 0 | X69: =+I69-L69 -> 0
C70: Advocacy and Information Materials - IEC Materials Soybean | D70: 50 | F70: 50 | G70: 50 | I70: 50 | J70: 50 | L70: 50 | N70: =+D70-G70 -> 0 | O70: =+E70-H70 -> 0 | P70: =+F70-I70 -> 0 | R70: =+D70-J70 -> 0 | S70: =+E70-K70 -> 0 | T70: =+F70-L70 -> 0 | V70: =+G70-J70 -> 0 | W70: =+H70-K70 -> 0 | X70: =+I70-L70 -> 0
C71: Advocacy and Information Materials - Radio Plugs | D71: 350 | F71: 350 | G71: 350 | I71: 350 | J71: 350 | L71: 350 | N71: =+D71-G71 -> 0 | O71: =+E71-H71 -> 0 | P71: =+F71-I71 -> 0 | R71: =+D71-J71 -> 0 | S71: =+E71-K71 -> 0 | T71: =+F71-L71 -> 0 | V71: =+G71-J71 -> 0 | W71: =+H71-K71 -> 0 | X71: =+I71-L71 -> 0
C72: Advocacy and Information Materials - TV Plugs | D72: 400 | F72: 400 | G72: 400 | I72: 400 | J72: 400 | L72: 400 | N72: =+D72-G72 -> 0 | O72: =+E72-H72 -> 0 | P72: =+F72-I72 -> 0 | R72: =+D72-J72 -> 0 | S72: =+E72-K72 -> 0 | T72: =+F72-L72 -> 0 | V72: =+G72-J72 -> 0 | W72: =+H72-K72 -> 0 | X72: =+I72-L72 -> 0
B73: Extension Workers Incentives | D73: 7866 | F73: 7866 | G73: 7866 | I73: 7866 | J73: 7866 | L73: 7866 | N73: =+D73-G73 -> 0 | O73: =+E73-H73 -> 0 | P73: =+F73-I73 -> 0 | R73: =+D73-J73 -> 0 | S73: =+E73-K73 -> 0 | T73: =+F73-L73 -> 0 | V73: =+G73-J73 -> 0 | W73: =+H73-K73 -> 0 | X73: =+I73-L73 -> 0
C74: Support to LGU Extension Workers Incentives - Provincial Coordinator | D74: 192 | F74: 192 | G74: 192 | I74: 192 | J74: 192 | L74: 192 | N74: =+D74-G74 -> 0 | O74: =+E74-H74 -> 0 | P74: =+F74-I74 -> 0 | R74: =+D74-J74 -> 0 | S74: =+E74-K74 -> 0 | T74: =+F74-L74 -> 0 | V74: =+G74-J74 -> 0 | W74: =+H74-K74 -> 0 | X74: =+I74-L74 -> 0
C75: Support to LGU Extension Workers Incentives - Municipal Agriculturist | D75: 576 | F75: 576 | G75: 576 | I75: 576 | J75: 576 | L75: 576 | N75: =+D75-G75 -> 0 | O75: =+E75-H75 -> 0 | P75: =+F75-I75 -> 0 | R75: =+D75-J75 -> 0 | S75: =+E75-K75 -> 0 | T75: =+F75-L75 -> 0 | V75: =+G75-J75 -> 0 | W75: =+H75-K75 -> 0 | X75: =+I75-L75 -> 0
C76: Support to LGU Extension Workers Incentives - Agricultural Extension Worker | D76: 7098 | F76: 7098 | G76: 7098 | I76: 7098 | J76: 7098 | L76: 7098 | N76: =+D76-G76 -> 0 | O76: =+E76-H76 -> 0 | P76: =+F76-I76 -> 0 | R76: =+D76-J76 -> 0 | S76: =+E76-K76 -> 0 | T76: =+F76-L76 -> 0 | V76: =+G76-J76 -> 0 | W76: =+H76-K76 -> 0 | X76: =+I76-L76 -> 0
B77: Special Events | D77: 600 | F77: 600 | G77: 600 | I77: 600 | J77: 600 | L77: 600 | N77: =+D77-G77 -> 0 | O77: =+E77-H77 -> 0 | P77: =+F77-I77 -> 0 | R77: =+D77-J77 -> 0 | S77: =+E77-K77 -> 0 | T77: =+F77-L77 -> 0 | V77: =+G77-J77 -> 0 | W77: =+H77-K77 -> 0 | X77: =+I77-L77 -> 0
C78: Corn and Cassava Congress | D78: 600 | F78: 600 | G78: 600 | I78: 600 | J78: 600 | L78: 600 | N78: =+D78-G78 -> 0 | O78: =+E78-H78 -> 0 | P78: =+F78-I78 -> 0 | R78: =+D78-J78 -> 0 | S78: =+E78-K78 -> 0 | T78: =+F78-L78 -> 0 | V78: =+G78-J78 -> 0 | W78: =+H78-K78 -> 0 | X78: =+I78-L78 -> 0
A79: RND | D79: 5500 | F79: 5500 | G79: 5500 | I79: 5500 | J79: 5500 | L79: 5500 | N79: =+D79-G79 -> 0 | O79: =+E79-H79 -> 0 | P79: =+F79-I79 -> 0 | R79: =+D79-J79 -> 0 | S79: =+E79-K79 -> 0 | T79: =+F79-L79 -> 0 | V79: =+G79-J79 -> 0 | W79: =+H79-K79 -> 0 | X79: =+I79-L79 -> 0
B80: R&D conducted | D80: 5500 | F80: 5500 | G80: 5500 | I80: 5500 | J80: 5500 | L80: 5500 | N80: =+D80-G80 -> 0 | O80: =+E80-H80 -> 0 | P80: =+F80-I80 -> 0 | R80: =+D80-J80 -> 0 | S80: =+E80-K80 -> 0 | T80: =+F80-L80 -> 0 | V80: =+G80-J80 -> 0 | W80: =+H80-K80 -> 0 | X80: =+I80-L80 -> 0
C81: R&D New Studies Conducted - Production | D81: 5500 | F81: 5500 | G81: 5500 | I81: 5500 | J81: 5500 | L81: 5500 | N81: =+D81-G81 -> 0 | O81: =+E81-H81 -> 0 | P81: =+F81-I81 -> 0 | R81: =+D81-J81 -> 0 | S81: =+E81-K81 -> 0 | T81: =+F81-L81 -> 0 | V81: =+G81-J81 -> 0 | W81: =+H81-K81 -> 0 | X81: =+I81-L81 -> 0
A82: AMEFSS | E82: 122600 | F82: 122600 | H82: 122600 | I82: 122600 | K82: 122600 | L82: 122600 | N82: =+D82-G82 -> 0 | O82: =+E82-H82 -> 0 | P82: =+F82-I82 -> 0 | R82: =+D82-J82 -> 0 | S82: =+E82-K82 -> 0 | T82: =+F82-L82 -> 0 | V82: =+G82-J82 -> 0 | W82: =+H82-K82 -> 0 | X82: =+I82-L82 -> 0
B83: Production related machinery & equipment | E83: 73200 | F83: 73200 | H83: 78200 | I83: 78200 | K83: 78200 | L83: 78200 | N83: =+D83-G83 -> 0 | O83: =+E83-H83 -> -5000 | P83: =+F83-I83 -> -5000 | R83: =+D83-J83 -> 0 | S83: =+E83-K83 -> -5000 | T83: =+F83-L83 -> -5000 | V83: =+G83-J83 -> 0 | W83: =+H83-K83 -> 0 | X83: =+I83-L83 -> 0
C84: Farm Production - Four-wheel Tractor (90 hp min) | E84: 31000 | F84: 31000 | H84: 36000 | I84: 36000 | K84: 36000 | L84: 36000 | N84: =+D84-G84 -> 0 | O84: =+E84-H84 -> -5000 | P84: =+F84-I84 -> -5000 | R84: =+D84-J84 -> 0 | S84: =+E84-K84 -> -5000 | T84: =+F84-L84 -> -5000 | V84: =+G84-J84 -> 0 | W84: =+H84-K84 -> 0 | X84: =+I84-L84 -> 0
C85: Farm Production - Double Row Corn seeder | E85: 2400 | F85: 2400 | H85: 2400 | I85: 2400 | K85: 2400 | L85: 2400 | N85: =+D85-G85 -> 0 | O85: =+E85-H85 -> 0 | P85: =+F85-I85 -> 0 | R85: =+D85-J85 -> 0 | S85: =+E85-K85 -> 0 | T85: =+F85-L85 -> 0 | V85: =+G85-J85 -> 0 | W85: =+H85-K85 -> 0 | X85: =+I85-L85 -> 0
C86: Farm Production - Mechanical four-row seeder | E86: 2000 | F86: 2000 | H86: 2000 | I86: 2000 | K86: 2000 | L86: 2000 | N86: =+D86-G86 -> 0 | O86: =+E86-H86 -> 0 | P86: =+F86-I86 -> 0 | R86: =+D86-J86 -> 0 | S86: =+E86-K86 -> 0 | T86: =+F86-L86 -> 0 | V86: =+G86-J86 -> 0 | W86: =+H86-K86 -> 0 | X86: =+I86-L86 -> 0
C87: Farm Production - Pneumatic Four-row seeder | E87: 1800 | F87: 1800 | H87: 1800 | I87: 1800 | K87: 1800 | L87: 1800 | N87: =+D87-G87 -> 0 | O87: =+E87-H87 -> 0 | P87: =+F87-I87 -> 0 | R87: =+D87-J87 -> 0 | S87: =+E87-K87 -> 0 | T87: =+F87-L87 -> 0 | V87: =+G87-J87 -> 0 | W87: =+H87-K87 -> 0 | X87: =+I87-L87 -> 0
C88: Farm Production - Two-row seeder | E88: 15000 | F88: 15000 | H88: 15000 | I88: 15000 | K88: 15000 | L88: 15000 | N88: =+D88-G88 -> 0 | O88: =+E88-H88 -> 0 | P88: =+F88-I88 -> 0 | R88: =+D88-J88 -> 0 | S88: =+E88-K88 -> 0 | T88: =+F88-L88 -> 0 | V88: =+G88-J88 -> 0 | W88: =+H88-K88 -> 0 | X88: =+I88-L88 -> 0
C89: Farm Production - Combine Harvester | E89: 21000 | F89: 21000 | H89: 21000 | I89: 21000 | K89: 21000 | L89: 21000 | N89: =+D89-G89 -> 0 | O89: =+E89-H89 -> 0 | P89: =+F89-I89 -> 0 | R89: =+D89-J89 -> 0 | S89: =+E89-K89 -> 0 | T89: =+F89-L89 -> 0 | V89: =+G89-J89 -> 0 | W89: =+H89-K89 -> 0 | X89: =+I89-L89 -> 0
B90: Postharvest related machinery & equipment | E90: 20000 | F90: 20000 | H90: 15000 | I90: 15000 | K90: 15000 | L90: 15000 | N90: =+D90-G90 -> 0 | O90: =+E90-H90 -> 5000 | P90: =+F90-I90 -> 5000 | R90: =+D90-J90 -> 0 | S90: =+E90-K90 -> 5000 | T90: =+F90-L90 -> 5000 | V90: =+G90-J90 -> 0 | W90: =+H90-K90 -> 0 | X90: =+I90-L90 -> 0
C91: Postharvest-related - Hauling Truck (not exceeding 3000cc) - four-wheel truck | E91: 11000 | F91: 11000 | H91: 11000 | I91: 11000 | K91: 11000 | L91: 11000 | N91: =+D91-G91 -> 0 | O91: =+E91-H91 -> 0 | P91: =+F91-I91 -> 0 | R91: =+D91-J91 -> 0 | S91: =+E91-K91 -> 0 | T91: =+F91-L91 -> 0 | V91: =+G91-J91 -> 0 | W91: =+H91-K91 -> 0 | X91: =+I91-L91 -> 0
C92: Postharvest-related - Solar Bubble Dryer | E92: 4000 | F92: 4000 | H92: 4000 | I92: 4000 | K92: 4000 | L92: 4000 | N92: =+D92-G92 -> 0 | O92: =+E92-H92 -> 0 | P92: =+F92-I92 -> 0 | R92: =+D92-J92 -> 0 | S92: =+E92-K92 -> 0 | T92: =+F92-L92 -> 0 | V92: =+G92-J92 -> 0 | W92: =+H92-K92 -> 0 | X92: =+I92-L92 -> 0
C93: Postharvest-related - Forage Chopper | E93: 5000 | F93: 5000 | N93: =+D93-G93 -> 0 | O93: =+E93-H93 -> 5000 | P93: =+F93-I93 -> 5000 | R93: =+D93-J93 -> 0 | S93: =+E93-K93 -> 5000 | T93: =+F93-L93 -> 5000 | V93: =+G93-J93 -> 0 | W93: =+H93-K93 -> 0 | X93: =+I93-L93 -> 0
B94: Processing related machinery & equipment | E94: 24400 | F94: 24400 | H94: 24400 | I94: 24400 | K94: 24400 | L94: 24400 | N94: =+D94-G94 -> 0 | O94: =+E94-H94 -> 0 | P94: =+F94-I94 -> 0 | R94: =+D94-J94 -> 0 | S94: =+E94-K94 -> 0 | T94: =+F94-L94 -> 0 | V94: =+G94-J94 -> 0 | W94: =+H94-K94 -> 0 | X94: =+I94-L94 -> 0
C95: Postharvest-related - Corn Mill (1T/hr) | H95: 4400 | I95: 4400 | K95: 4400 | L95: 4400 | N95: =+D95-G95 -> 0 | O95: =+E95-H95 -> -4400 | P95: =+F95-I95 -> -4400 | R95: =+D95-J95 -> 0 | S95: =+E95-K95 -> -4400 | T95: =+F95-L95 -> -4400 | V95: =+G95-J95 -> 0 | W95: =+H95-K95 -> 0 | X95: =+I95-L95 -> 0
C96: Postharvest facilities - Waste Water Treatment System | E96: 20000 | F96: 20000 | H96: 20000 | I96: 20000 | K96: 20000 | L96: 20000 | N96: =+D96-G96 -> 0 | O96: =+E96-H96 -> 0 | P96: =+F96-I96 -> 0 | R96: =+D96-J96 -> 0 | S96: =+E96-K96 -> 0 | T96: =+F96-L96 -> 0 | V96: =+G96-J96 -> 0 | W96: =+H96-K96 -> 0 | X96: =+I96-L96 -> 0
C97: Postharvest-related - Corn Mill (250kg/hr) | E97: 4400 | F97: 4400 | N97: =+D97-G97 -> 0 | O97: =+E97-H97 -> 4400 | P97: =+F97-I97 -> 4400 | R97: =+D97-J97 -> 0 | S97: =+E97-K97 -> 4400 | T97: =+F97-L97 -> 4400 | V97: =+G97-J97 -> 0 | W97: =+H97-K97 -> 0 | X97: =+I97-L97 -> 0
B98: Postharvest facilities | E98: 5000 | F98: 5000 | H98: 5000 | I98: 5000 | K98: 5000 | L98: 5000 | N98: =+D98-G98 -> 0 | O98: =+E98-H98 -> 0 | P98: =+F98-I98 -> 0 | R98: =+D98-J98 -> 0 | S98: =+E98-K98 -> 0 | T98: =+F98-L98 -> 0 | V98: =+G98-J98 -> 0 | W98: =+H98-K98 -> 0 | X98: =+I98-L98 -> 0
C99: Postharvest facilities - Multi Crop Drying Pavement (MCDP) | E99: 5000 | F99: 5000 | H99: 5000 | I99: 5000 | K99: 5000 | L99: 5000 | N99: =+D99-G99 -> 0 | O99: =+E99-H99 -> 0 | P99: =+F99-I99 -> 0 | R99: =+D99-J99 -> 0 | S99: =+E99-K99 -> 0 | T99: =+F99-L99 -> 0 | V99: =+G99-J99 -> 0 | W99: =+H99-K99 -> 0 | X99: =+I99-L99 -> 0
A100: INS | E100: 35000 | F100: 35000 | H100: 35000 | I100: 35000 | K100: 35000 | L100: 35000 | N100: =+D100-G100 -> 0 | O100: =+E100-H100 -> 0 | P100: =+F100-I100 -> 0 | R100: =+D100-J100 -> 0 | S100: =+E100-K100 -> 0 | T100: =+F100-L100 -> 0 | V100: =+G100-J100 -> 0 | W100: =+H100-K100 -> 0 | X100: =+I100-L100 -> 0
B101: Small-scale Irrigation Projects | E101: 35000 | F101: 35000 | H101: 35000 | I101: 35000 | K101: 35000 | L101: 35000 | N101: =+D101-G101 -> 0 | O101: =+E101-H101 -> 0 | P101: =+F101-I101 -> 0 | R101: =+D101-J101 -> 0 | S101: =+E101-K101 -> 0 | T101: =+F101-L101 -> 0 | V101: =+G101-J101 -> 0 | W101: =+H101-K101 -> 0 | X101: =+I101-L101 -> 0
C102: Open Source Pumping Set (unit) | E102: 25000 | F102: 25000 | H102: 25000 | I102: 25000 | K102: 25000 | L102: 25000 | N102: =+D102-G102 -> 0 | O102: =+E102-H102 -> 0 | P102: =+F102-I102 -> 0 | R102: =+D102-J102 -> 0 | S102: =+E102-K102 -> 0 | T102: =+F102-L102 -> 0 | V102: =+G102-J102 -> 0 | W102: =+H102-K102 -> 0 | X102: =+I102-L102 -> 0
C103: Mobile Solar Powered Irrigation System (unit) | E103: 10000 | F103: 10000 | H103: 10000 | I103: 10000 | K103: 10000 | L103: 10000 | N103: =+D103-G103 -> 0 | O103: =+E103-H103 -> 0 | P103: =+F103-I103 -> 0 | R103: =+D103-J103 -> 0 | S103: =+E103-K103 -> 0 | T103: =+F103-L103 -> 0 | V103: =+G103-J103 -> 0 | W103: =+H103-K103 -> 0 | X103: =+I103-L103 -> 0
A104: FPMA | D104: 21509 | F104: 21509 | G104: 36509 | I104: 36509 | J104: 36509 | L104: 36509 | N104: =+D104-G104 -> -15000 | O104: =+E104-H104 -> 0 | P104: =+F104-I104 -> -15000 | R104: =+D104-J104 -> -15000 | S104: =+E104-K104 -> 0 | T104: =+F104-L104 -> -15000 | V104: =+G104-J104 -> 0 | W104: =+H104-K104 -> 0 | X104: =+I104-L104 -> 0
...

Sheet BED2 checking
A1: FY 2025 PLAN AND BUDGET PROPOSAL
A2: BASED ON NATIONAL EXPENDITURE PROGRAM (NEP)
A3: BED 2: PHYSICAL
A4: NAME OF OU | B4: ='CAPTURE SHEET - PHYSICAL'!C2 -> RFOII
D7: PRPOPOSAL/BEDS | E7: Values
D8: PROPOSAL | H8: BED 2 - PHYSICAL
A9: PREXC SUB-PROGRAM | B9: ACTIVITY | C9: PROVINCE | D9: PHYSICAL TARGET | E9: GROUP BENEF | F9: Sum of TOTAL INDIV | G9: ALLOCATION (Php'000) | H9: PHYSICAL TARGET | I9: GROUP BENEF | J9: Sum of TOTAL INDIV | K9: ALLOCATION (Php'000) | M9: PHYSICAL TARGET | N9: GROUP BENEF | O9: Sum of TOTAL INDIV | P9: ALLOCATION (Php'000)
A10: PSS | B10: Seed Production - White Corn Registered Seeds | C10: Cagayan | D10: 6000 | E10: 10 | H10: 6000 | I10: 10 | J10: 0 | K10: 301 | M10: =+D10-H10 -> 0 | N10: =+E10-I10 -> 0 | O10: =+F10-J10 -> 0 | P10: =+G10-K10 -> -301
C11: Isabela | D11: 8000 | E11: 17 | H11: 8000 | I11: 17 | J11: 0 | K11: 402 | M11: =+D11-H11 -> 0 | N11: =+E11-I11 -> 0 | O11: =+F11-J11 -> 0 | P11: =+G11-K11 -> -402
C12: Nueva_Vizcaya | D12: 4000 | E12: 6 | H12: 4000 | I12: 6 | J12: 0 | K12: 201 | M12: =+D12-H12 -> 0 | N12: =+E12-I12 -> 0 | O12: =+F12-J12 -> 0 | P12: =+G12-K12 -> -201
C13: Quirino | D13: 4000 | E13: 6 | H13: 4000 | I13: 6 | J13: 0 | K13: 201 | M13: =+D13-H13 -> 0 | N13: =+E13-I13 -> 0 | O13: =+F13-J13 -> 0 | P13: =+G13-K13 -> -201
C14: Regional_Office | G14: 1106 | M14: =+D14-H14 -> 0 | N14: =+E14-I14 -> 0 | O14: =+F14-J14 -> 0 | P14: =+G14-K14 -> 1106
B15: Seed Production - White Corn Registered Seeds Total | D15: 22000 | E15: 39 | G15: 1106 | H15: 22000 | I15: 39 | J15: 0 | K15: 1105 | M15: =+D15-H15 -> 0 | N15: =+E15-I15 -> 0 | O15: =+F15-J15 -> 0 | P15: =+G15-K15 -> 1
B16: DRRM - White Corn Seed Procured OPV | C16: Regional_Office | D16: 15000 | G16: 1500 | H16: 15000 | J16: 0 | K16: 1500 | M16: =+D16-H16 -> 0 | N16: =+E16-I16 -> 0 | O16: =+F16-J16 -> 0 | P16: =+G16-K16 -> 0
B17: DRRM - White Corn Seed Procured OPV Total | D17: 15000 | G17: 1500 | H17: 15000 | J17: 0 | K17: 1500 | M17: =+D17-H17 -> 0 | N17: =+E17-I17 -> 0 | O17: =+F17-J17 -> 0 | P17: =+G17-K17 -> 0
B18: RCPT - Yellow Corn seeds | C18: Cagayan | D18: 9000 | E18: 2 | G18: 6000 | H18: 9000 | I18: 2 | J18: 0 | K18: 6000 | M18: =+D18-H18 -> 0 | N18: =+E18-I18 -> 0 | O18: =+F18-J18 -> 0 | P18: =+G18-K18 -> 0
C19: Isabela | D19: 9000 | E19: 2 | G19: 6000 | H19: 9000 | I19: 2 | J19: 0 | K19: 6000 | M19: =+D19-H19 -> 0 | N19: =+E19-I19 -> 0 | O19: =+F19-J19 -> 0 | P19: =+G19-K19 -> 0
B20: RCPT - Yellow Corn seeds Total | D20: 18000 | E20: 4 | G20: 12000 | H20: 18000 | I20: 4 | J20: 0 | K20: 12000 | M20: =+D20-H20 -> 0 | N20: =+E20-I20 -> 0 | O20: =+F20-J20 -> 0 | P20: =+G20-K20 -> 0
B21: RCPT - Inorganic fertilizer for YC seeds | C21: Cagayan | D21: 275000 | E21: 2 | G21: 12375 | H21: 275000 | I21: 2 | J21: 0 | K21: 12375 | M21: =+D21-H21 -> 0 | N21: =+E21-I21 -> 0 | O21: =+F21-J21 -> 0 | P21: =+G21-K21 -> 0
C22: Isabela | D22: 275000 | E22: 2 | G22: 12375 | H22: 275000 | I22: 2 | J22: 0 | K22: 12375 | M22: =+D22-H22 -> 0 | N22: =+E22-I22 -> 0 | O22: =+F22-J22 -> 0 | P22: =+G22-K22 -> 0
B23: RCPT - Inorganic fertilizer for YC seeds Total | D23: 550000 | E23: 4 | G23: 24750 | H23: 550000 | I23: 4 | J23: 0 | K23: 24750 | M23: =+D23-H23 -> 0 | N23: =+E23-I23 -> 0 | O23: =+F23-J23 -> 0 | P23: =+G23-K23 -> 0
B24: Biofertilizer | C24: Cagayan | D24: 2000 | E24: 2 | G24: 1360 | H24: 2000 | I24: 2 | J24: 0 | K24: 1360 | M24: =+D24-H24 -> 0 | N24: =+E24-I24 -> 0 | O24: =+F24-J24 -> 0 | P24: =+G24-K24 -> 0
C25: Isabela | D25: 2000 | E25: 2 | G25: 1360 | H25: 2000 | I25: 2 | J25: 0 | K25: 1360 | M25: =+D25-H25 -> 0 | N25: =+E25-I25 -> 0 | O25: =+F25-J25 -> 0 | P25: =+G25-K25 -> 0
B26: Biofertilizer Total | D26: 4000 | E26: 4 | G26: 2720 | H26: 4000 | I26: 4 | J26: 0 | K26: 2720 | M26: =+D26-H26 -> 0 | N26: =+E26-I26 -> 0 | O26: =+F26-J26 -> 0 | P26: =+G26-K26 -> 0
B27: Soil Ameliorant | C27: Cagayan | D27: 250000 | E27: 2 | G27: 5000 | H27: 250000 | I27: 2 | J27: 0 | K27: 5000 | M27: =+D27-H27 -> 0 | N27: =+E27-I27 -> 0 | O27: =+F27-J27 -> 0 | P27: =+G27-K27 -> 0
C28: Isabela | D28: 250000 | E28: 2 | G28: 5000 | H28: 250000 | I28: 2 | J28: 0 | K28: 5000 | M28: =+D28-H28 -> 0 | N28: =+E28-I28 -> 0 | O28: =+F28-J28 -> 0 | P28: =+G28-K28 -> 0
B29: Soil Ameliorant Total | D29: 500000 | E29: 4 | G29: 10000 | H29: 500000 | I29: 4 | J29: 0 | K29: 10000 | M29: =+D29-H29 -> 0 | N29: =+E29-I29 -> 0 | O29: =+F29-J29 -> 0 | P29: =+G29-K29 -> 0
B30: YCPEP - Yellow Corn Hybrid seeds | C30: Cagayan | D30: 125010 | E30: 25 | G30: 83340 | H30: 125010 | I30: 25 | J30: 0 | K30: 83340 | M30: =+D30-H30 -> 0 | N30: =+E30-I30 -> 0 | O30: =+F30-J30 -> 0 | P30: =+G30-K30 -> 0
C31: Isabela | D31: 301140 | E31: 35 | G31: 200760 | H31: 301140 | I31: 35 | J31: 0 | K31: 200760 | M31: =+D31-H31 -> 0 | N31: =+E31-I31 -> 0 | O31: =+F31-J31 -> 0 | P31: =+G31-K31 -> 0
C32: Nueva_Vizcaya | D32: 16200 | E32: 9 | G32: 10800 | H32: 16200 | I32: 10 | J32: 0 | K32: 10800 | M32: =+D32-H32 -> 0 | N32: =+E32-I32 -> -1 | O32: =+F32-J32 -> 0 | P32: =+G32-K32 -> 0
C33: Quirino | D33: 43650 | E33: 6 | G33: 29100 | H33: 43650 | I33: 6 | J33: 0 | K33: 29100 | M33: =+D33-H33 -> 0 | N33: =+E33-I33 -> 0 | O33: =+F33-J33 -> 0 | P33: =+G33-K33 -> 0
B34: YCPEP - Yellow Corn Hybrid seeds Total | D34: 486000 | E34: 75 | G34: 324000 | H34: 486000 | I34: 76 | J34: 0 | K34: 324000 | M34: =+D34-H34 -> 0 | N34: =+E34-I34 -> -1 | O34: =+F34-J34 -> 0 | P34: =+G34-K34 -> 0
B35: YCPEP - Inorganic fertilizer for YC Hybrid seeds | C35: Cagayan | D35: 694500 | E35: 25 | G35: 31252.5 | H35: 694500 | I35: 25 | J35: 0 | K35: 31252.5 | M35: =+D35-H35 -> 0 | N35: =+E35-I35 -> 0 | O35: =+F35-J35 -> 0 | P35: =+G35-K35 -> 0
C36: Isabela | D36: 1673000 | E36: 35 | G36: 75285 | H36: 1673000 | I36: 35 | J36: 0 | K36: 75285 | M36: =+D36-H36 -> 0 | N36: =+E36-I36 -> 0 | O36: =+F36-J36 -> 0 | P36: =+G36-K36 -> 0
C37: Nueva_Vizcaya | D37: 90000 | E37: 9 | G37: 4050 | H37: 90000 | I37: 10 | J37: 0 | K37: 4050 | M37: =+D37-H37 -> 0 | N37: =+E37-I37 -> -1 | O37: =+F37-J37 -> 0 | P37: =+G37-K37 -> 0
C38: Quirino | D38: 242500 | E38: 6 | G38: 10912.5 | H38: 242500 | I38: 6 | J38: 0 | K38: 10912.5 | M38: =+D38-H38 -> 0 | N38: =+E38-I38 -> 0 | O38: =+F38-J38 -> 0 | P38: =+G38-K38 -> 0
B39: YCPEP - Inorganic fertilizer for YC Hybrid seeds Total | D39: 2700000 | E39: 75 | G39: 121500 | H39: 2700000 | I39: 76 | J39: 0 | K39: 121500 | M39: =+D39-H39 -> 0 | N39: =+E39-I39 -> -1 | O39: =+F39-J39 -> 0 | P39: =+G39-K39 -> 0
B40: DRRM - Yellow Corn Seed Procured OPV | C40: Regional_Office | D40: 3000 | G40: 300 | H40: 3000 | J40: 0 | K40: 300 | M40: =+D40-H40 -> 0 | N40: =+E40-I40 -> 0 | O40: =+F40-J40 -> 0 | P40: =+G40-K40 -> 0
B41: DRRM - Yellow Corn Seed Procured OPV Total | D41: 3000 | G41: 300 | H41: 3000 | J41: 0 | K41: 300 | M41: =+D41-H41 -> 0 | N41: =+E41-I41 -> 0 | O41: =+F41-J41 -> 0 | P41: =+G41-K41 -> 0
B42: DRRM - Yellow Corn Seed Procured Hybrid | C42: Regional_Office | D42: 375894 | G42: 250596 | H42: 375894 | J42: 0 | K42: 250596 | M42: =+D42-H42 -> 0 | N42: =+E42-I42 -> 0 | O42: =+F42-J42 -> 0 | P42: =+G42-K42 -> 0
B43: DRRM - Yellow Corn Seed Procured Hybrid Total | D43: 375894 | G43: 250596 | H43: 375894 | J43: 0 | K43: 250596 | M43: =+D43-H43 -> 0 | N43: =+E43-I43 -> 0 | O43: =+F43-J43 -> 0 | P43: =+G43-K43 -> 0
B44: DRRM - Agricultural chemicals (Insecticide in liters) | C44: Regional_Office | D44: 5000 | G44: 6000 | H44: 5000 | J44: 0 | K44: 6000 | M44: =+D44-H44 -> 0 | N44: =+E44-I44 -> 0 | O44: =+F44-J44 -> 0 | P44: =+G44-K44 -> 0
B45: DRRM - Agricultural chemicals (Insecticide in liters) Total | D45: 5000 | G45: 6000 | H45: 5000 | J45: 0 | K45: 6000 | M45: =+D45-H45 -> 0 | N45: =+E45-I45 -> 0 | O45: =+F45-J45 -> 0 | P45: =+G45-K45 -> 0
B46: DRRM - Agricultural chemicals (Rodenticides) | C46: Regional_Office | D46: 50000 | G46: 1500 | H46: 50000 | J46: 0 | K46: 1500 | M46: =+D46-H46 -> 0 | N46: =+E46-I46 -> 0 | O46: =+F46-J46 -> 0 | P46: =+G46-K46 -> 0
B47: DRRM - Agricultural chemicals (Rodenticides) Total | D47: 50000 | G47: 1500 | H47: 50000 | J47: 0 | K47: 1500 | M47: =+D47-H47 -> 0 | N47: =+E47-I47 -> 0 | O47: =+F47-J47 -> 0 | P47: =+G47-K47 -> 0
B48: DRRM - Agricultural chemicals (Pheromone lure) | C48: Regional_Office | D48: 5000 | G48: 2750 | H48: 5000 | J48: 0 | K48: 2750 | M48: =+D48-H48 -> 0 | N48: =+E48-I48 -> 0 | O48: =+F48-J48 -> 0 | P48: =+G48-K48 -> 0
B49: DRRM - Agricultural chemicals (Pheromone lure) Total | D49: 5000 | G49: 2750 | H49: 5000 | J49: 0 | K49: 2750 | M49: =+D49-H49 -> 0 | N49: =+E49-I49 -> 0 | O49: =+F49-J49 -> 0 | P49: =+G49-K49 -> 0
B50: Cassava Production (seed pieces) | C50: Cagayan | D50: 130000 | F50: 13 | H50: 130000 | I50: 3 | J50: 0 | K50: 130 | M50: =+D50-H50 -> 0 | N50: =+E50-I50 -> -3 | O50: =+F50-J50 -> 13 | P50: =+G50-K50 -> -130
C51: Isabela | D51: 455000 | F51: 45 | H51: 455000 | I51: 3 | J51: 0 | K51: 455 | M51: =+D51-H51 -> 0 | N51: =+E51-I51 -> -3 | O51: =+F51-J51 -> 45 | P51: =+G51-K51 -> -455
C52: Nueva_Vizcaya | D52: 195000 | F52: 15 | H52: 195000 | I52: 1 | J52: 0 | K52: 195 | M52: =+D52-H52 -> 0 | N52: =+E52-I52 -> -1 | O52: =+F52-J52 -> 15 | P52: =+G52-K52 -> -195
C53: Quirino | D53: 195000 | F53: 15 | H53: 195000 | I53: 1 | J53: 0 | K53: 195 | M53: =+D53-H53 -> 0 | N53: =+E53-I53 -> -1 | O53: =+F53-J53 -> 15 | P53: =+G53-K53 -> -195
C54: Regional_Office | G54: 975 | M54: =+D54-H54 -> 0 | N54: =+E54-I54 -> 0 | O54: =+F54-J54 -> 0 | P54: =+G54-K54 -> 975
B55: Cassava Production (seed pieces) Total | D55: 975000 | F55: 88 | G55: 975 | H55: 975000 | I55: 8 | J55: 0 | K55: 975 | M55: =+D55-H55 -> 0 | N55: =+E55-I55 -> -8 | O55: =+F55-J55 -> 88 | P55: =+G55-K55 -> 0
B56: Cassava Procurement (seed pieces) | C56: Cagayan | D56: 240000 | F56: 24 | G56: 360 | H56: 240000 | I56: 2 | J56: 0 | K56: 360 | M56: =+D56-H56 -> 0 | N56: =+E56-I56 -> -2 | O56: =+F56-J56 -> 24 | P56: =+G56-K56 -> 0
C57: Isabela | D57: 3680000 | F57: 368 | G57: 5520 | H57: 3680000 | I57: 9 | J57: 0 | K57: 5520 | M57: =+D57-H57 -> 0 | N57: =+E57-I57 -> -9 | O57: =+F57-J57 -> 368 | P57: =+G57-K57 -> 0
C58: Nueva_Vizcaya | D58: 100000 | F58: 10 | G58: 150 | H58: 100000 | I58: 1 | J58: 0 | K58: 150 | M58: =+D58-H58 -> 0 | N58: =+E58-I58 -> -1 | O58: =+F58-J58 -> 10 | P58: =+G58-K58 -> 0
C59: Quirino | D59: 980000 | F59: 98 | G59: 1470 | H59: 980000 | I59: 2 | J59: 0 | K59: 1470 | M59: =+D59-H59 -> 0 | N59: =+E59-I59 -> -2 | O59: =+F59-J59 -> 98 | P59: =+G59-K59 -> 0
B60: Cassava Procurement (seed pieces) Total | D60: 5000000 | F60: 500 | G60: 7500 | H60: 5000000 | I60: 14 | J60: 0 | K60: 7500 | M60: =+D60-H60 -> 0 | N60: =+E60-I60 -> -14 | O60: =+F60-J60 -> 500 | P60: =+G60-K60 -> 0
B61: Inorganic fertilizer for Cassava | C61: Cagayan | D61: 3700 | F61: 37 | G61: 166.5 | H61: 3700 | I61: 5 | J61: 0 | K61: 166.5 | M61: =+D61-H61 -> 0 | N61: =+E61-I61 -> -5 | O61: =+F61-J61 -> 37 | P61: =+G61-K61 -> 0
C62: Isabela | D62: 41400 | F62: 414 | G62: 1863 | H62: 41400 | I62: 12 | J62: 0 | K62: 1863 | M62: =+D62-H62 -> 0 | N62: =+E62-I62 -> -12 | O62: =+F62-J62 -> 414 | P62: =+G62-K62 -> 0
C63: Nueva_Vizcaya | D63: 2950 | F63: 30 | G63: 132.75 | H63: 2950 | I63: 2 | J63: 0 | K63: 132.75 | M63: =+D63-H63 -> 0 | N63: =+E63-I63 -> -2 | O63: =+F63-J63 -> 30 | P63: =+G63-K63 -> 0
C64: Quirino | D64: 11750 | F64: 118 | G64: 528.75 | H64: 11750 | I64: 3 | J64: 0 | K64: 528.75 | M64: =+D64-H64 -> 0 | N64: =+E64-I64 -> -3 | O64: =+F64-J64 -> 118 | P64: =+G64-K64 -> 0
B65: Inorganic fertilizer for Cassava Total | D65: 59800 | F65: 599 | G65: 2691 | H65: 59800 | I65: 22 | J65: 0 | K65: 2691 | M65: =+D65-H65 -> 0 | N65: =+E65-I65 -> -22 | O65: =+F65-J65 -> 599 | P65: =+G65-K65 -> 0
B66: DRRM - Agricultural chemicals (Streptomycin) | C66: Regional_Office | D66: 10000 | G66: 4000 | H66: 10000 | J66: 0 | K66: 4000 | M66: =+D66-H66 -> 0 | N66: =+E66-I66 -> 0 | O66: =+F66-J66 -> 0 | P66: =+G66-K66 -> 0
B67: DRRM - Agricultural chemicals (Streptomycin) Total | D67: 10000 | G67: 4000 | H67: 10000 | J67: 0 | K67: 4000 | M67: =+D67-H67 -> 0 | N67: =+E67-I67 -> 0 | O67: =+F67-J67 -> 0 | P67: =+G67-K67 -> 0
B68: Seed Procurement - Sorghum | C68: Isabela | D68: 20000 | F68: 1000 | G68: 1750 | H68: 20000 | I68: 1 | J68: 0 | K68: 1750 | M68: =+D68-H68 -> 0 | N68: =+E68-I68 -> -1 | O68: =+F68-J68 -> 1000 | P68: =+G68-K68 -> 0
B69: Seed Procurement - Sorghum Total | D69: 20000 | F69: 1000 | G69: 1750 | H69: 20000 | I69: 1 | J69: 0 | K69: 1750 | M69: =+D69-H69 -> 0 | N69: =+E69-I69 -> -1 | O69: =+F69-J69 -> 1000 | P69: =+G69-K69 -> 0
B70: Inorganic fertilizer for Sorghum | C70: Isabela | D70: 100000 | F70: 1000 | G70: 4500 | H70: 100000 | I70: 1 | J70: 0 | K70: 4500 | M70: =+D70-H70 -> 0 | N70: =+E70-I70 -> -1 | O70: =+F70-J70 -> 1000 | P70: =+G70-K70 -> 0
B71: Inorganic fertilizer for Sorghum Total | D71: 100000 | F71: 1000 | G71: 4500 | H71: 100000 | I71: 1 | J71: 0 | K71: 4500 | M71: =+D71-H71 -> 0 | N71: =+E71-I71 -> -1 | O71: =+F71-J71 -> 1000 | P71: =+G71-K71 -> 0
B72: Seed Production - Soybean | C72: Isabela | D72: 1000 | F72: 25 | H72: 1000 | I72: 1 | J72: 0 | K72: 50 | M72: =+D72-H72 -> 0 | N72: =+E72-I72 -> -1 | O72: =+F72-J72 -> 25 | P72: =+G72-K72 -> -50
C73: Regional_Office | G73: 50 | M73: =+D73-H73 -> 0 | N73: =+E73-I73 -> 0 | O73: =+F73-J73 -> 0 | P73: =+G73-K73 -> 50
B74: Seed Production - Soybean Total | D74: 1000 | F74: 25 | G74: 50 | H74: 1000 | I74: 1 | J74: 0 | K74: 50 | M74: =+D74-H74 -> 0 | N74: =+E74-I74 -> -1 | O74: =+F74-J74 -> 25 | P74: =+G74-K74 -> 0
B75: Inorganic fertilizer for Soybean | C75: Isabela | D75: 2500 | F75: 25 | G75: 112 | H75: 2500 | I75: 1 | J75: 0 | K75: 113 | M75: =+D75-H75 -> 0 | N75: =+E75-I75 -> -1 | O75: =+F75-J75 -> 25 | P75: =+G75-K75 -> -1
B76: Inorganic fertilizer for Soybean Total | D76: 2500 | F76: 25 | G76: 112 | H76: 2500 | I76: 1 | J76: 0 | K76: 113 | M76: =+D76-H76 -> 0 | N76: =+E76-I76 -> -1 | O76: =+F76-J76 -> 25 | P76: =+G76-K76 -> -1
B77: DA Stations - Hand tractor with corn planter | C77: Regional_Office | D77: 4 | G77: 1200 | H77: 4 | J77: 0 | K77: 1200 | M77: =+D77-H77 -> 0 | N77: =+E77-I77 -> 0 | O77: =+F77-J77 -> 0 | P77: =+G77-K77 -> 0
B78: DA Stations - Hand tractor with corn planter Total | D78: 4 | G78: 1200 | H78: 4 | J78: 0 | K78: 1200 | M78: =+D78-H78 -> 0 | N78: =+E78-I78 -> 0 | O78: =+F78-J78 -> 0 | P78: =+G78-K78 -> 0
B79: DA Stations - Silage Chopper | C79: Regional_Office | D79: 4 | G79: 240 | H79: 4 | J79: 0 | K79: 240 | M79: =+D79-H79 -> 0 | N79: =+E79-I79 -> 0 | O79: =+F79-J79 -> 0 | P79: =+G79-K79 -> 0
B80: DA Stations - Silage Chopper Total | D80: 4 | G80: 240 | H80: 4 | J80: 0 | K80: 240 | M80: =+D80-H80 -> 0 | N80: =+E80-I80 -> 0 | O80: =+F80-J80 -> 0 | P80: =+G80-K80 -> 0
B81: DA Stations - Corn Mill | C81: Regional_Office | D81: 4 | G81: 1200 | H81: 4 | J81: 0 | K81: 1200 | M81: =+D81-H81 -> 0 | N81: =+E81-I81 -> 0 | O81: =+F81-J81 -> 0 | P81: =+G81-K81 -> 0
B82: DA Stations - Corn Mill Total | D82: 4 | G82: 1200 | H82: 4 | J82: 0 | K82: 1200 | M82: =+D82-H82 -> 0 | N82: =+E82-I82 -> 0 | O82: =+F82-J82 -> 0 | P82: =+G82-K82 -> 0
B83: DA Stations - Pelletizing Machine | C83: Regional_Office | D83: 4 | G83: 300 | H83: 4 | J83: 0 | K83: 300 | M83: =+D83-H83 -> 0 | N83: =+E83-I83 -> 0 | O83: =+F83-J83 -> 0 | P83: =+G83-K83 -> 0
B84: DA Stations - Pelletizing Machine Total | D84: 4 | G84: 300 | H84: 4 | J84: 0 | K84: 300 | M84: =+D84-H84 -> 0 | N84: =+E84-I84 -> 0 | O84: =+F84-J84 -> 0 | P84: =+G84-K84 -> 0
B85: DA Stations - Light Cargo Truck | C85: Regional_Office | D85: 1 | G85: 2100 | H85: 1 | J85: 0 | K85: 2100 | M85: =+D85-H85 -> 0 | N85: =+E85-I85 -> 0 | O85: =+F85-J85 -> 0 | P85: =+G85-K85 -> 0
B86: DA Stations - Light Cargo Truck Total | D86: 1 | G86: 2100 | H86: 1 | J86: 0 | K86: 2100 | M86: =+D86-H86 -> 0 | N86: =+E86-I86 -> 0 | O86: =+F86-J86 -> 0 | P86: =+G86-K86 -> 0
B87: DA Stations - Four-wheel Tractor (90 hp min) | C87: Regional_Office | D87: 1 | G87: 3100 | H87: 1 | J87: 0 | K87: 3100 | M87: =+D87-H87 -> 0 | N87: =+E87-I87 -> 0 | O87: =+F87-J87 -> 0 | P87: =+G87-K87 -> 0
B88: DA Stations - Four-wheel Tractor (90 hp min) Total | D88: 1 | G88: 3100 | H88: 1 | J88: 0 | K88: 3100 | M88: =+D88-H88 -> 0 | N88: =+E88-I88 -> 0 | O88: =+F88-J88 -> 0 | P88: =+G88-K88 -> 0
A89: PSS Total | D89: 10902212 | E89: 205 | F89: 3237 | G89: 788440 | H89: 10902212 | I89: 255 | J89: 0 | K89: 788440 | M89: =+D89-H89 -> 0 | N89: =+E89-I89 -> -50 | O89: =+F89-J89 -> 3237 | P89: =+G89-K89 -> 0
A90: ESETS | B90: Sustainable Land Management in Corn-based Sloping Areas (SLM-Corn) | C90: Quirino | H90: 1 | J90: 0 | K90: 3000 | M90: =+D90-H90 -> -1 | N90: =+E90-I90 -> 0 | O90: =+F90-J90 -> 0 | P90: =+G90-K90 -> -3000
C91: Regional_Office | D91: 1 | G91: 3000 | M91: =+D91-H91 -> 1 | N91: =+E91-I91 -> 0 | O91: =+F91-J91 -> 0 | P91: =+G91-K91 -> 3000
B92: Sustainable Land Management in Corn-based Sloping Areas (SLM-Corn) Total | D92: 1 | G92: 3000 | H92: 1 | J92: 0 | K92: 3000 | M92: =+D92-H92 -> 0 | N92: =+E92-I92 -> 0 | O92: =+F92-J92 -> 0 | P92: =+G92-K92 -> 0
B93: Establishment of Corn Derby | C93: Regional_Office | D93: 1 | G93: 1000 | H93: 1 | J93: 0 | K93: 1000 | M93: =+D93-H93 -> 0 | N93: =+E93-I93 -> 0 | O93: =+F93-J93 -> 0 | P93: =+G93-K93 -> 0
B94: Establishment of Corn Derby Total | D94: 1 | G94: 1000 | H94: 1 | J94: 0 | K94: 1000 | M94: =+D94-H94 -> 0 | N94: =+E94-I94 -> 0 | O94: =+F94-J94 -> 0 | P94: =+G94-K94 -> 0
B95: Training - Clientele-based - Corn Cluster Development training | C95: Regional_Office | D95: 6 | F95: 180 | G95: 210 | H95: 6 | J95: 180 | K95: 210 | M95: =+D95-H95 -> 0 | N95: =+E95-I95 -> 0 | O95: =+F95-J95 -> 0 | P95: =+G95-K95 -> 0
B96: Training - Clientele-based - Corn Cluster Development training Total | D96: 6 | F96: 180 | G96: 210 | H96: 6 | J96: 180 | K96: 210 | M96: =+D96-H96 -> 0 | N96: =+E96-I96 -> 0 | O96: =+F96-J96 -> 0 | P96: =+G96-K96 -> 0
B97: Training - Clientele-based - Corn Livelihood training | C97: Regional_Office | D97: 4 | F97: 120 | G97: 200 | H97: 4 | J97: 120 | K97: 200 | M97: =+D97-H97 -> 0 | N97: =+E97-I97 -> 0 | O97: =+F97-J97 -> 0 | P97: =+G97-K97 -> 0
B98: Training - Clientele-based - Corn Livelihood training Total | D98: 4 | F98: 120 | G98: 200 | H98: 4 | J98: 120 | K98: 200 | M98: =+D98-H98 -> 0 | N98: =+E98-I98 -> 0 | O98: =+F98-J98 -> 0 | P98: =+G98-K98 -> 0
B99: Training - Clientele-based - Corn Production Training | C99: Regional_Office | D99: 4 | F99: 120 | G99: 140 | H99: 4 | J99: 120 | K99: 140 | M99: =+D99-H99 -> 0 | N99: =+E99-I99 -> 0 | O99: =+F99-J99 -> 0 | P99: =+G99-K99 -> 0
B100: Training - Clientele-based - Corn Production Training Total | D100: 4 | F100: 120 | G100: 140 | H100: 4 | J100: 120 | K100: 140 | M100: =+D100-H100 -> 0 | N100: =+E100-I100 -> 0 | O100: =+F100-J100 -> 0 | P100: =+G100-K100 -> 0
B101: Training - Clientele-based - Integrated Pest Management Training | C101: Regional_Office | D101: 4 | F101: 120 | G101: 400 | H101: 4 | J101: 120 | K101: 400 | M101: =+D101-H101 -> 0 | N101: =+E101-I101 -> 0 | O101: =+F101-J101 -> 0 | P101: =+G101-K101 -> 0
B102: Training - Clientele-based - Integrated Pest Management Training Total | D102: 4 | F102: 120 | G102: 400 | H102: 4 | J102: 120 | K102: 400 | M102: =+D102-H102 -> 0 | N102: =+E102-I102 -> 0 | O102: =+F102-J102 -> 0 | P102: =+G102-K102 -> 0
...

Sheet BED13 vs BED2 checking
A1: FY 2025 PLAN AND BUDGET PROPOSAL | I1: FY 2025 PLAN AND BUDGET PROPOSAL
A2: BASED ON NATIONAL EXPENDITURE PROGRAM (NEP) | I2: BASED ON NATIONAL EXPENDITURE PROGRAM (NEP)
A3: BED 2: PHYSICAL | I3: BED 1 OBLIGATION AND BED 3 DISBURSEMENT
A4: NAME OF OU | I4: NAME OF OU
A5: PRPOPOSAL/BEDS | B5: BED 2 - PHYSICAL
I6: Sum of TOTAL (Php '000) | M6: PRPOPOSAL/BEDS
A7: PREXC SUB-PROGRAM | B7: STRATEGY | C7: ACTIVITY | D7: ALLOCATION (Php'000) | I7: PREXC SUB-PROGRAM | J7: STRATEGY | K7: ACTIVITY | L7: MONTH | M7: BED 1 - OBLIGATION | N7: BED 3 - DISBURSEMENT
A8: PSS | D8: 788440 | I8: PSS | M8: 788440 | N8: 788440
B9: OPV Seed Production | J9: OPV Seed Production | M9: 1105 | N9: 1105
C10: Seed Production - White Corn Registered Seeds | D10: 1105 | K10: Seed Production - White Corn Registered Seeds | M10: 1105 | N10: 1105
B11: Corn Seed Reserve | L11: MARCH | M11: 1105
C12: DRRM - White Corn Seed Procured OPV | D12: 1500 | L12: MAY | N12: 1105
C13: DRRM - Yellow Corn Seed Procured OPV | D13: 300 | J13: Corn Seed Reserve | M13: 252396 | N13: 252396
C14: DRRM - Yellow Corn Seed Procured Hybrid | D14: 250596 | K14: DRRM - White Corn Seed Procured OPV | M14: 1500 | N14: 1500
B15: Recommended Corn Production Technology | L15: MARCH | M15: 1500
C16: RCPT - Yellow Corn seeds | D16: 12000 | L16: MAY | N16: 1500
C17: RCPT - Inorganic fertilizer for YC seeds | D17: 24750 | K17: DRRM - Yellow Corn Seed Procured OPV | M17: 300 | N17: 300
B18: Soil amendments | L18: MARCH | M18: 300
C19: Biofertilizer | D19: 2720 | L19: MAY | N19: 300
C20: Soil Ameliorant | D20: 10000 | K20: DRRM - Yellow Corn Seed Procured Hybrid | M20: 250596 | N20: 250596
B21: Yellow Corn Production Enhancement Project | L21: APRIL | M21: 250596
C22: YCPEP - Yellow Corn Hybrid seeds | D22: 324000 | L22: JULY | N22: 250596
C23: YCPEP - Inorganic fertilizer for YC Hybrid seeds | D23: 121500 | J23: Recommended Corn Production Technology | M23: 36750 | N23: 36750
B24: Pest and Disease Management | K24: RCPT - Yellow Corn seeds | M24: 12000 | N24: 12000
C25: DRRM - Agricultural chemicals (Insecticide in liters) | D25: 6000 | L25: MARCH | M25: 12000
C26: DRRM - Agricultural chemicals (Rodenticides) | D26: 1500 | L26: AUGUST | N26: 12000
C27: DRRM - Agricultural chemicals (Pheromone lure) | D27: 2750 | K27: RCPT - Inorganic fertilizer for YC seeds | M27: 24750 | N27: 24750
C28: DRRM - Agricultural chemicals (Streptomycin) | D28: 4000 | L28: APRIL | M28: 17600
B29: Cassava Production Enhancement Project | L29: JULY | M29: 7150 | N29: 17600
C30: Cassava Production (seed pieces) | D30: 975 | L30: NOVEMBER | N30: 7150
C31: Cassava Procurement (seed pieces) | D31: 7500 | J31: Soil amendments | M31: 12720 | N31: 12720
C32: Inorganic fertilizer for Cassava | D32: 2691 | K32: Biofertilizer | M32: 2720 | N32: 2720
B33: Sorghum Production Enhancement Project | L33: MARCH | M33: 2720
C34: Seed Procurement - Sorghum | D34: 1750 | L34: JULY | N34: 2720
C35: Inorganic fertilizer for Sorghum | D35: 4500 | K35: Soil Ameliorant | M35: 10000 | N35: 10000
B36: Soybean Production Enhancement Project | L36: MARCH | M36: 7000
C37: Seed Production - Soybean | D37: 50 | L37: JULY | M37: 3000 | N37: 7000
C38: Inorganic fertilizer for Soybean | D38: 113 | L38: NOVEMBER | N38: 3000
B39: DA Facilities Management | J39: Yellow Corn Production Enhancement Project | M39: 445500 | N39: 445500
C40: DA Stations - Hand tractor with corn planter | D40: 1200 | K40: YCPEP - Yellow Corn Hybrid seeds | M40: 324000 | N40: 324000
C41: DA Stations - Silage Chopper | D41: 240 | L41: APRIL | M41: 324000
C42: DA Stations - Corn Mill | D42: 1200 | L42: AUGUST | N42: 324000
C43: DA Stations - Pelletizing Machine | D43: 300 | K43: YCPEP - Inorganic fertilizer for YC Hybrid seeds | M43: 121500 | N43: 121500
C44: DA Stations - Light Cargo Truck | D44: 2100 | L44: MARCH | M44: 86400
C45: DA Stations - Four-wheel Tractor (90 hp min) | D45: 3100 | L45: JULY | M45: 35100 | N45: 86400
A46: ESETS | D46: 17156 | L46: NOVEMBER | N46: 35100
B47: Model Farm establishment | J47: Pest and Disease Management | M47: 14250 | N47: 14250
C48: Sustainable Land Management in Corn-based Sloping Areas (SLM-Corn) | D48: 3000 | K48: DRRM - Agricultural chemicals (Insecticide in liters) | M48: 6000 | N48: 6000
C49: Model Farm - Cassava (sites) | D49: 650 | L49: MARCH | M49: 6000
C50: Model Farm - Sorghum (sites) | D50: 280 | L50: JUNE | N50: 6000
C51: Model Farm - Soybean (sites) | D51: 330 | K51: DRRM - Agricultural chemicals (Rodenticides) | M51: 1500 | N51: 1500
B52: Techno Demo establishment | L52: MARCH | M52: 1500
C53: Establishment of Corn Derby | D53: 1000 | L53: JUNE | N53: 1500
C54: Techno-Demo Sorghum (sites) | D54: 160 | K54: DRRM - Agricultural chemicals (Pheromone lure) | M54: 2750 | N54: 2750
C55: Techno-Demo Soybean (sites) | D55: 200 | L55: MARCH | M55: 2750
B56: Trainings | L56: JUNE | N56: 2750
C57: Training - Clientele-based - Corn Cluster Development training | D57: 140 | K57: DRRM - Agricultural chemicals (Streptomycin) | M57: 4000 | N57: 4000
C58: Training - Clientele-based - Corn Livelihood training | D58: 200 | L58: MARCH | M58: 4000
C59: Training - Clientele-based - Corn Production Training | D59: 140 | L59: JULY | N59: 4000
C60: Training - Clientele-based - Integrated Pest Management Training | D60: 400 | J60: Cassava Production Enhancement Project | M60: 11166 | N60: 11166
C61: Training - Clientele-based - Training on Operation and Maintenance of Farm Machinery and Equipment | D61: 300 | K61: Cassava Production (seed pieces) | M61: 975 | N61: 975
C62: Training - Clientele-based - Cassava Livelihood training | D62: 200 | L62: MARCH | M62: 975
C63: Training - Clientele-based - Cassava Production Training | D63: 140 | L63: MAY | N63: 975
C64: Training - Clientele-based - Sorghum Production Training | D64: 140 | K64: Cassava Procurement (seed pieces) | M64: 7500 | N64: 7500
C65: Training - Clientele-based - Soybean Production Training | D65: 140 | L65: MARCH | M65: 7500
B66: (blank) | L66: JULY | N66: 7500
C67: Training - Clientele-based - Corn Cluster Development training | D67: 70 | K67: Inorganic fertilizer for Cassava | M67: 2691 | N67: 2691
B68: Information, Education, and Communication Activities | L68: MARCH | M68: 1913.6
C69: Advocacy and Information Materials - IEC Materials Yellow Corn | D69: 200 | L69: JULY | M69: 777.4 | N69: 1913.6
C70: Advocacy and Information Materials - IEC Materials Cassava | D70: 150 | L70: NOVEMBER | N70: 777.4
C71: Advocacy and Information Materials - IEC Materials Sorghum | D71: 50 | J71: Sorghum Production Enhancement Project | M71: 6250 | N71: 6250
C72: Advocacy and Information Materials - IEC Materials Soybean | D72: 50 | K72: Seed Procurement - Sorghum | M72: 1750 | N72: 1750
C73: Advocacy and Information Materials - Radio Plugs | D73: 350 | L73: MARCH | M73: 1750
C74: Advocacy and Information Materials - TV Plugs | D74: 400 | L74: JULY | N74: 1750
B75: Extension Workers Incentives | K75: Inorganic fertilizer for Sorghum | M75: 4500 | N75: 4500
C76: Support to LGU Extension Workers Incentives - Provincial Coordinator | D76: 192 | L76: MARCH | M76: 3800
C77: Support to LGU Extension Workers Incentives - Municipal Agriculturist | D77: 576 | L77: JULY | M77: 700 | N77: 3800
C78: Support to LGU Extension Workers Incentives - Agricultural Extension Worker | D78: 7098 | L78: NOVEMBER | N78: 700
B79: Special Events | J79: Soybean Production Enhancement Project | M79: 163 | N79: 163
C80: Corn and Cassava Congress | D80: 600 | K80: Seed Production - Soybean | M80: 50 | N80: 50
A81: RND | D81: 5500 | L81: FEBRUARY | M81: 50
B82: R&D conducted | L82: MAY | N82: 50
C83: R&D New Studies Conducted - Production | D83: 5500 | K83: Inorganic fertilizer for Soybean | M83: 113 | N83: 113
A84: AMEFSS | D84: 122600 | L84: FEBRUARY | M84: 113
B85: Production related machinery & equipment | L85: MAY | N85: 113
C86: Farm Production - Four-wheel Tractor (90 hp min) | D86: 36000 | J86: DA Facilities Management | M86: 8140 | N86: 8140
C87: Farm Production - Double Row Corn seeder | D87: 2400 | K87: DA Stations - Hand tractor with corn planter | M87: 1200 | N87: 1200
C88: Farm Production - Mechanical four-row seeder | D88: 2000 | L88: APRIL | M88: 1200
C89: Farm Production - Two-row seeder | D89: 15000 | L89: AUGUST | N89: 1200
C90: Farm Production - Pneumatic Four-row seeder | D90: 1800 | K90: DA Stations - Silage Chopper | M90: 240 | N90: 240
C91: Farm Production - Combine Harvester | D91: 21000 | L91: APRIL | M91: 240
B92: Postharvest related machinery & equipment | L92: AUGUST | N92: 240
C93: Postharvest-related - Hauling Truck (not exceeding 3000cc) - four-wheel truck | D93: 11000 | K93: DA Stations - Corn Mill | M93: 1200 | N93: 1200
C94: Postharvest-related - Solar Bubble Dryer | D94: 4000 | L94: APRIL | M94: 1200
B95: Processing related machinery & equipment | L95: AUGUST | N95: 1200
C96: Postharvest-related - Corn Mill (1T/hr) | D96: 4400 | K96: DA Stations - Pelletizing Machine | M96: 300 | N96: 300
C97: Postharvest facilities - Waste Water Treatment System | D97: 20000 | L97: APRIL | M97: 300
B98: Postharvest facilities | L98: AUGUST | N98: 300
C99: Postharvest facilities - Multi Crop Drying Pavement (MCDP) | D99: 5000 | K99: DA Stations - Light Cargo Truck | M99: 2100 | N99: 2100
A100: INS | D100: 35000 | L100: JUNE | M100: 2100
...

Sheet comments
A1: FY 2025 PLAN AND BUDGET PROPOSAL
A2: BASED ON NATIONAL EXPENDITURE PROGRAM (NEP)
A3: BED 2: PHYSICAL
A4: NAME OF OU | B4: ='[1]CAPTURE SHEET - PHYSICAL'!C2 -> RFOII
A8: Yung mga Group Benef po sa PSS, pakilagyan ng number of individual for group
A9: PREXC SUB-PROGRAM | B9: ACTIVITY | C9: PROVINCE
A10: PSS | B10: Seed Production - White Corn Registered Seeds | C10: Cagayan
A11: PSS | B11: Seed Production - White Corn Registered Seeds | C11: Isabela
A12: PSS | B12: Seed Production - White Corn Registered Seeds | C12: Nueva_Vizcaya
A13: PSS | B13: Seed Production - White Corn Registered Seeds | C13: Quirino | D13: Nagbawas po kayo benef sa Quirino? | E13: edited
A14: PSS | B14: Seed Production - White Corn Registered Seeds | C14: Regional_Office
A15: PSS | B15: Seed Production - White Corn Registered Seeds Total
A16: PSS | B16: DRRM - White Corn Seed Procured OPV | C16: Regional_Office
A17: PSS | B17: DRRM - White Corn Seed Procured OPV Total
A18: PSS | B18: RCPT - Yellow Corn seeds | C18: Cagayan
A19: PSS | B19: RCPT - Yellow Corn seeds | C19: Isabela
A20: PSS | B20: RCPT - Yellow Corn seeds Total
A21: PSS | B21: RCPT - Inorganic fertilizer for YC seeds | C21: Cagayan
A22: PSS | B22: RCPT - Inorganic fertilizer for YC seeds | C22: Isabela
A23: PSS | B23: RCPT - Inorganic fertilizer for YC seeds Total
A24: PSS | B24: Biofertilizer | C24: Cagayan
A25: PSS | B25: Biofertilizer | C25: Isabela
A26: PSS | B26: Biofertilizer Total
A27: PSS | B27: Soil Ameliorant | C27: Cagayan
A28: PSS | B28: Soil Ameliorant | C28: Isabela
A29: PSS | B29: Soil Ameliorant Total
A30: PSS | B30: YCPEP - Yellow Corn Hybrid seeds | C30: Cagayan
A31: PSS | B31: YCPEP - Yellow Corn Hybrid seeds | C31: Isabela
A32: PSS | B32: YCPEP - Yellow Corn Hybrid seeds | C32: Nueva_Vizcaya
A33: PSS | B33: YCPEP - Yellow Corn Hybrid seeds | C33: Quirino
A34: PSS | B34: YCPEP - Yellow Corn Hybrid seeds Total
A35: PSS | B35: YCPEP - Inorganic fertilizer for YC Hybrid seeds | C35: Cagayan | D35: Pakicheck po, walang benef na nakalagay | E35: ok
A36: PSS | B36: YCPEP - Inorganic fertilizer for YC Hybrid seeds | C36: Isabela
A37: PSS | B37: YCPEP - Inorganic fertilizer for YC Hybrid seeds | C37: Nueva_Vizcaya
A38: PSS | B38: YCPEP - Inorganic fertilizer for YC Hybrid seeds | C38: Quirino
A39: PSS | B39: YCPEP - Inorganic fertilizer for YC Hybrid seeds Total
A40: PSS | B40: DRRM - Yellow Corn Seed Procured OPV | C40: Regional_Office
A41: PSS | B41: DRRM - Yellow Corn Seed Procured OPV Total
A42: PSS | B42: DRRM - Yellow Corn Seed Procured Hybrid | C42: Regional_Office
A43: PSS | B43: DRRM - Yellow Corn Seed Procured Hybrid Total
A44: PSS | B44: DRRM - Agricultural chemicals (Insecticide in liters) | C44: Regional_Office
A45: PSS | B45: DRRM - Agricultural chemicals (Insecticide in liters) Total
A46: PSS | B46: DRRM - Agricultural chemicals (Rodenticides) | C46: Regional_Office
A47: PSS | B47: DRRM - Agricultural chemicals (Rodenticides) Total
A48: PSS | B48: DRRM - Agricultural chemicals (Pheromone lure) | C48: Regional_Office
A49: PSS | B49: DRRM - Agricultural chemicals (Pheromone lure) Total
A50: PSS | B50: Cassava Production (seed pieces) | C50: Cagayan | D50: Pakicheck po, walang benef na nakalagay | E50: ok
A51: PSS | B51: Cassava Production (seed pieces) | C51: Isabela
A52: PSS | B52: Cassava Production (seed pieces) | C52: Nueva_Vizcaya
A53: PSS | B53: Cassava Production (seed pieces) | C53: Quirino
A54: PSS | B54: Cassava Production (seed pieces) | C54: Regional_Office
A55: PSS | B55: Cassava Production (seed pieces) Total
A56: PSS | B56: Cassava Procurement (seed pieces) | C56: Cagayan | D56: Pakicheck po, walang benef na nakalagay | E56: ok
A57: PSS | B57: Cassava Procurement (seed pieces) | C57: Isabela
A58: PSS | B58: Cassava Procurement (seed pieces) | C58: Nueva_Vizcaya
A59: PSS | B59: Cassava Procurement (seed pieces) | C59: Quirino
A60: PSS | B60: Cassava Procurement (seed pieces) Total
A61: PSS | B61: Inorganic fertilizer for Cassava | C61: Cagayan | D61: Pakicheck po, walang benef na nakalagay | E61: ok
A62: PSS | B62: Inorganic fertilizer for Cassava | C62: Isabela
A63: PSS | B63: Inorganic fertilizer for Cassava | C63: Nueva_Vizcaya
A64: PSS | B64: Inorganic fertilizer for Cassava | C64: Quirino
A65: PSS | B65: Inorganic fertilizer for Cassava Total
A66: PSS | B66: DRRM - Agricultural chemicals (Streptomycin) | C66: Regional_Office
A67: PSS | B67: DRRM - Agricultural chemicals (Streptomycin) Total
A68: PSS | B68: Seed Procurement - Sorghum | C68: Isabela | D68: Pakicheck po, walang benef na nakalagay | E68: ok
A69: PSS | B69: Seed Procurement - Sorghum Total
A70: PSS | B70: Inorganic fertilizer for Sorghum | C70: Isabela | D70: Pakicheck po, walang benef na nakalagay | E70: ok
A71: PSS | B71: Inorganic fertilizer for Sorghum Total
A72: PSS | B72: Seed Production - Soybean | C72: Isabela | D72: Pakicheck po, walang benef na nakalagay | E72: ok
A73: PSS | B73: Seed Production - Soybean | C73: Regional_Office
A74: PSS | B74: Seed Production - Soybean Total
A75: PSS | B75: Inorganic fertilizer for Soybean | C75: Isabela | D75: Pakicheck po, walang benef na nakalagay | E75: ok
A76: PSS | B76: Inorganic fertilizer for Soybean Total
A77: PSS | B77: DA Stations - Hand tractor with corn planter | C77: Regional_Office
A78: PSS | B78: DA Stations - Hand tractor with corn planter Total
A79: PSS | B79: DA Stations - Silage Chopper | C79: Regional_Office
A80: PSS | B80: DA Stations - Silage Chopper Total
A81: PSS | B81: DA Stations - Corn Mill | C81: Regional_Office
A82: PSS | B82: DA Stations - Corn Mill Total
A83: PSS | B83: DA Stations - Pelletizing Machine | C83: Regional_Office
A84: PSS | B84: DA Stations - Pelletizing Machine Total
A85: PSS | B85: DA Stations - Light Cargo Truck | C85: Regional_Office
A86: PSS | B86: DA Stations - Light Cargo Truck Total
A87: PSS | B87: DA Stations - Four-wheel Tractor (90 hp min) | C87: Regional_Office
A88: PSS | B88: DA Stations - Four-wheel Tractor (90 hp min) Total
A89: PSS Total
A90: ESETS | B90: Sustainable Land Management in Corn-based Sloping Areas (SLM-Corn) | C90: Quirino
A91: ESETS | B91: Sustainable Land Management in Corn-based Sloping Areas (SLM-Corn) Total
A92: ESETS | B92: Establishment of Corn Derby | C92: Regional_Office
A93: ESETS | B93: Establishment of Corn Derby Total
A94: ESETS | B94: Corn Congress | C94: Regional_Office
A95: ESETS | B95: Corn Congress Total
A96: ESETS | B96: Training - Clientele-based - Corn Cluster Development training | C96: Regional_Office
A97: ESETS | B97: Training - Clientele-based - Corn Cluster Development training Total
A98: ESETS | B98: Training - Clientele-based - Corn Livelihood training | C98: Regional_Office
A99: ESETS | B99: Training - Clientele-based - Corn Livelihood training Total
A100: ESETS | B100: Training - Clientele-based - Corn Production Training | C100: Regional_Office
A101: ESETS | B101: Training - Clientele-based - Corn Production Training Total
A102: ESETS | B102: Training - Clientele-based - Integrated Pest Management Training | C102: Regional_Office
A103: ESETS | B103: Training - Clientele-based - Integrated Pest Management Training Total
...

Sheet CAPTURE SHEET - FINANCIAL
A1: GROUP | B1: PRPOPOSAL/BEDS | C1: OU | D1: SPECIFIC COMMODITY | E1: COMMODITY | F1: PREXC PROGRAM | G1: PREXC SUB-PROGRAM | H1: COMMODITY PREXC SUB-PROGRAM | I1: PI LEVEL 1 | J1: PI LEVEL 2 | K1: PI LEVEL 3 | L1: ACTIVITY | M1: STRATEGY | N1: BRIEFER SUMMARY | O1: BRIEFER/PPT SUMMARY | P1: TAG-CLIMATE CHANGE | Q1: TAG-SENATE | R1: TAG-PIP | S1: TAG-PICS | T1: 8 PARADIGM | U1: ONE DA | V1: SEC LAUREL | W1: TYPE OF PROJECT | X1: INDICATOR TYPE | Y1: TAG-GAD | Z1: MONTH | AA1: QUARTER | AB1: SEMESTER | AC1: YEAR | AD1: MOOE (Php '000) | AE1: CO (Php '000) | AF1: TOTAL (Php '000) | AG1: blank prop/beds | AH1: blank ou | AI1: blank specific commodity | AJ1: blank commodity subprogram | AK1: blank activity | AL1: blank GAD | AM1: blank month | AN1: blank MOOE | AO1: blank CO
A2: =VLOOKUP(Table37[[#This Row],[OU]],OU!$A$15:$B$34,2,FALSE) -> RFOs | B2: BED 1 - OBLIGATION | C2: RFOII | D2: White Corn | E2: =VLOOKUP(Table37[[#This Row],[SPECIFIC COMMODITY]],TAGS!$W$48:$X$53,2,FALSE) -> Corn | F2: =VLOOKUP(Table37[[#This Row],[PREXC SUB-PROGRAM]],Table5[],2,FALSE) -> TECHNICAL AND SUPPORT SERVICES PROGRAM | G2: =VLOOKUP(Table37[[#This Row],[COMMODITY PREXC SUB-PROGRAM]],TAGS!$U$54:$V$76,2,FALSE) -> PSS | H2: Corn_PSS | I2: =VLOOKUP(Table37[[#This Row],[PI LEVEL 3]],'PI LEVEL'!A:C,3,FALSE) -> Seeds distributed | J2: =VLOOKUP(Table37[[#This Row],[PI LEVEL 3]],Table53729[[Performance Indicator Level 3]:[Performance Indicator Level 1]],2,FALSE) -> Corn Seeds distributed | K2: =VLOOKUP(Table37[[#This Row],[ACTIVITY]],TAGS!B:P,2,FALSE) -> White Corn Seeds distributed | L2: Seed Production - White Corn Registered Seeds | M2: =VLOOKUP(Table37[[#This Row],[ACTIVITY]],TAGS!$B:$P,4,FALSE) -> OPV Seed Production | N2: =VLOOKUP(Table37[[#This Row],[ACTIVITY]],TAGS!$B:$P,5,FALSE) -> OPV Seed Production | O2: =VLOOKUP(Table37[[#This Row],[ACTIVITY]],TAGS!$B:$P,6,FALSE) -> White corn seeds | P2: =VLOOKUP(Table37[[#This Row],[ACTIVITY]],TAGS!$B:$P,7,FALSE) -> NO | Q2: =VLOOKUP(Table37[[#This Row],[ACTIVITY]],TAGS!$B:$P,8,FALSE) -> PAP | R2: =VLOOKUP(Table37[[#This Row],[ACTIVITY]],TAGS!$B:$P,10,FALSE) -> PIP | S2: =VLOOKUP(Table37[[#This Row],[ACTIVITY]],TAGS!$B:$P,11,FALSE) -> PICS | T2: =VLOOKUP(Table37[[#This Row],[ACTIVITY]],TAGS!$B:$P,12,FALSE) -> Consolidation | U2: =VLOOKUP(Table37[[#This Row],[ACTIVITY]],TAGS!$B:$P,13,FALSE) -> 1. Bayanihan Agri Cluster | V2: =VLOOKUP(Table37[[#This Row],[ACTIVITY]],TAGS!$B:$P,14,FALSE) -> EXPAND AND IMPROVE AVAILABLE AGRI-FISHERY AREAS FOR INCREASED PRODUCTION | W2: =VLOOKUP(Table37[[#This Row],[ACTIVITY]],TAGS!$B:$P,15,FALSE) -> Farm Inputs | X2: =VLOOKUP(Table37[[#This Row],[PI LEVEL 3]],'PI LEVEL'!$A:$G,7,FALSE) -> DA-Level Output | Y2: NO | Z2: MARCH | AA2: =VLOOKUP(Table37[[#This Row],[MONTH]],TAGS!$W$67:$Y$81,2,FALSE) -> 1ST QTR | AB2: =VLOOKUP(Table37[[#This Row],[MONTH]],TAGS!$W$67:$Y$81,3,FALSE) -> 1ST SEMESTER | AC2: =VLOOKUP(Table37[[#This Row],[MONTH]],TAGS!$W$67:$Z$81,4,FALSE) -> 2025 | AD2: 505 | AF2: =SUM(Table37[[#This Row],[MOOE (Php ''000)]:[CO (Php ''000)]]) -> 505 | AG2: =ISBLANK(Table37[[#This Row],[PRPOPOSAL/BEDS]]) -> FALSE | AH2: =ISBLANK(Table37[[#This Row],[OU]]) -> FALSE | AI2: =ISBLANK(Table37[[#This Row],[SPECIFIC COMMODITY]]) -> FALSE | AJ2: =ISBLANK(Table37[[#This Row],[COMMODITY PREXC SUB-PROGRAM]]) -> FALSE | AK2: =ISBLANK(Table37[[#This Row],[ACTIVITY]]) -> FALSE | AL2: =ISBLANK(Table37[[#This Row],[TAG-GAD]]) -> FALSE | AM2: =ISBLANK(Table37[[#This Row],[MONTH]]) -> FALSE | AN2: =ISBLANK(Table37[[#This Row],[MOOE (Php ''000)]]) -> FALSE | AO2: =ISBLANK(Table37[[#This Row],[CO (Php ''000)]]) -> TRUE
A3: =VLOOKUP(Table37[[#This Row],[OU]],OU!$A$15:$B$34,2,FALSE) -> RFOs | B3: BED 1 - OBLIGATION | C3: RFOII | D3: White Corn | E3: =VLOOKUP(Table37[[#This Row],[SPECIFIC COMMODITY]],TAGS!$W$48:$X$53,2,FALSE) -> Corn | F3: =VLOOKUP(Table37[[#This Row],[PREXC SUB-PROGRAM]],Table5[],2,FALSE) -> TECHNICAL AND SUPPORT SERVICES PROGRAM | G3: =VLOOKUP(Table37[[#This Row],[COMMODITY PREXC SUB-PROGRAM]],TAGS!$U$54:$V$76,2,FALSE) -> PSS | H3: Corn_PSS | I3: =VLOOKUP(Table37[[#This Row],[PI LEVEL 3]],'PI LEVEL'!A:C,3,FALSE) -> Seeds distributed | J3: =VLOOKUP(Table37[[#This Row],[PI LEVEL 3]],Table53729[[Performance Indicator Level 3]:[Performance Indicator Level 1]],2,FALSE) -> Corn Seeds distributed | K3: =VLOOKUP(Table37[[#This Row],[ACTIVITY]],TAGS!B:P,2,FALSE) -> White Corn Seeds distributed | L3: Seed Production - White Corn Registered Seeds | M3: =VLOOKUP(Table37[[#This Row],[ACTIVITY]],TAGS!$B:$P,4,FALSE) -> OPV Seed Production | N3: =VLOOKUP(Table37[[#This Row],[ACTIVITY]],TAGS!$B:$P,5,FALSE) -> OPV Seed Production | O3: =VLOOKUP(Table37[[#This Row],[ACTIVITY]],TAGS!$B:$P,6,FALSE) -> White corn seeds | P3: =VLOOKUP(Table37[[#This Row],[ACTIVITY]],TAGS!$B:$P,7,FALSE) -> NO | Q3: =VLOOKUP(Table37[[#This Row],[ACTIVITY]],TAGS!$B:$P,8,FALSE) -> PAP | R3: =VLOOKUP(Table37[[#This Row],[ACTIVITY]],TAGS!$B:$P,10,FALSE) -> PIP | S3: =VLOOKUP(Table37[[#This Row],[ACTIVITY]],TAGS!$B:$P,11,FALSE) -> PICS | T3: =VLOOKUP(Table37[[#This Row],[ACTIVITY]],TAGS!$B:$P,12,FALSE) -> Consolidation | U3: =VLOOKUP(Table37[[#This Row],[ACTIVITY]],TAGS!$B:$P,13,FALSE) -> 1. Bayanihan Agri Cluster | V3: =VLOOKUP(Table37[[#This Row],[ACTIVITY]],TAGS!$B:$P,14,FALSE) -> EXPAND AND IMPROVE AVAILABLE AGRI-FISHERY AREAS FOR INCREASED PRODUCTION | W3: =VLOOKUP(Table37[[#This Row],[ACTIVITY]],TAGS!$B:$P,15,FALSE) -> Farm Inputs | X3: =VLOOKUP(Table37[[#This Row],[PI LEVEL 3]],'PI LEVEL'!$A:$G,7,FALSE) -> DA-Level Output | Y3: NO | Z3: MARCH | AA3: =VLOOKUP(Table37[[#This Row],[MONTH]],TAGS!$W$67:$Y$81,2,FALSE) -> 1ST QTR | AB3: =VLOOKUP(Table37[[#This Row],[MONTH]],TAGS!$W$67:$Y$81,3,FALSE) -> 1ST SEMESTER | AC3: =VLOOKUP(Table37[[#This Row],[MONTH]],TAGS!$W$67:$Z$81,4,FALSE) -> 2025 | AD3: 600 | AF3: =SUM(Table37[[#This Row],[MOOE (Php ''000)]:[CO (Php ''000)]]) -> 600 | AG3: =ISBLANK(Table37[[#This Row],[PRPOPOSAL/BEDS]]) -> FALSE | AH3: =ISBLANK(Table37[[#This Row],[OU]]) -> FALSE | AI3: =ISBLANK(Table37[[#This Row],[SPECIFIC COMMODITY]]) -> FALSE | AJ3: =ISBLANK(Table37[[#This Row],[COMMODITY PREXC SUB-PROGRAM]]) -> FALSE | AK3: =ISBLANK(Table37[[#This Row],[ACTIVITY]]) -> FALSE | AL3: =ISBLANK(Table37[[#This Row],[TAG-GAD]]) -> FALSE | AM3: =ISBLANK(Table37[[#This Row],[MONTH]]) -> FALSE | AN3: =ISBLANK(Table37[[#This Row],[MOOE (Php ''000)]]) -> FALSE | AO3: =ISBLANK(Table37[[#This Row],[CO (Php ''000)]]) -> TRUE
A4: =VLOOKUP(Table37[[#This Row],[OU]],OU!$A$15:$B$34,2,FALSE) -> RFOs | B4: BED 1 - OBLIGATION | C4: RFOII | D4: White Corn | E4: =VLOOKUP(Table37[[#This Row],[SPECIFIC COMMODITY]],TAGS!$W$48:$X$53,2,FALSE) -> Corn | F4: =VLOOKUP(Table37[[#This Row],[PREXC SUB-PROGRAM]],Table5[],2,FALSE) -> TECHNICAL AND SUPPORT SERVICES PROGRAM | G4: =VLOOKUP(Table37[[#This Row],[COMMODITY PREXC SUB-PROGRAM]],TAGS!$U$54:$V$76,2,FALSE) -> PSS | H4: Corn_PSS | I4: =VLOOKUP(Table37[[#This Row],[PI LEVEL 3]],'PI LEVEL'!A:C,3,FALSE) -> Seeds reserved | J4: =VLOOKUP(Table37[[#This Row],[PI LEVEL 3]],Table53729[[Performance Indicator Level 3]:[Performance Indicator Level 1]],2,FALSE) -> Corn Seeds reserved | K4: =VLOOKUP(Table37[[#This Row],[ACTIVITY]],TAGS!B:P,2,FALSE) -> White Corn Seeds reserved | L4: DRRM - White Corn Seed Procured OPV | M4: =VLOOKUP(Table37[[#This Row],[ACTIVITY]],TAGS!$B:$P,4,FALSE) -> Corn Seed Reserve | N4: =VLOOKUP(Table37[[#This Row],[ACTIVITY]],TAGS!$B:$P,5,FALSE) -> Corn Seed Reserve | O4: =VLOOKUP(Table37[[#This Row],[ACTIVITY]],TAGS!$B:$P,6,FALSE) -> White corn seeds reserve | P4: =VLOOKUP(Table37[[#This Row],[ACTIVITY]],TAGS!$B:$P,7,FALSE) -> YES | Q4: =VLOOKUP(Table37[[#This Row],[ACTIVITY]],TAGS!$B:$P,8,FALSE) -> PAP | R4: =VLOOKUP(Table37[[#This Row],[ACTIVITY]],TAGS!$B:$P,10,FALSE) -> PIP | S4: =VLOOKUP(Table37[[#This Row],[ACTIVITY]],TAGS!$B:$P,11,FALSE) -> PICS | T4: =VLOOKUP(Table37[[#This Row],[ACTIVITY]],TAGS!$B:$P,12,FALSE) -> Modernization | U4: =VLOOKUP(Table37[[#This Row],[ACTIVITY]],TAGS!$B:$P,13,FALSE) -> 9. Climate Change Adaptation & Mitigation Measures | V4: =VLOOKUP(Table37[[#This Row],[ACTIVITY]],TAGS!$B:$P,14,FALSE) -> EXPAND AND IMPROVE AVAILABLE AGRI-FISHERY AREAS FOR INCREASED PRODUCTION | W4: =VLOOKUP(Table37[[#This Row],[ACTIVITY]],TAGS!$B:$P,15,FALSE) -> Seed Reserve | X4: =VLOOKUP(Table37[[#This Row],[PI LEVEL 3]],'PI LEVEL'!$A:$G,7,FALSE) -> DA-Level Output | Y4: NO | Z4: MARCH | AA4: =VLOOKUP(Table37[[#This Row],[MONTH]],TAGS!$W$67:$Y$81,2,FALSE) -> 1ST QTR | AB4: =VLOOKUP(Table37[[#This Row],[MONTH]],TAGS!$W$67:$Y$81,3,FALSE) -> 1ST SEMESTER | AC4: =VLOOKUP(Table37[[#This Row],[MONTH]],TAGS!$W$67:$Z$81,4,FALSE) -> 2025 | AD4: 500 | AF4: =SUM(Table37[[#This Row],[MOOE (Php ''000)]:[CO (Php ''000)]]) -> 500 | AG4: =ISBLANK(Table37[[#This Row],[PRPOPOSAL/BEDS]]) -> FALSE | AH4: =ISBLANK(Table37[[#This Row],[OU]]) -> FALSE | AI4: =ISBLANK(Table37[[#This Row],[SPECIFIC COMMODITY]]) -> FALSE | AJ4: =ISBLANK(Table37[[#This Row],[COMMODITY PREXC SUB-PROGRAM]]) -> FALSE | AK4: =ISBLANK(Table37[[#This Row],[ACTIVITY]]) -> FALSE | AL4: =ISBLANK(Table37[[#This Row],[TAG-GAD]]) -> FALSE | AM4: =ISBLANK(Table37[[#This Row],[MONTH]]) -> FALSE | AN4: =ISBLANK(Table37[[#This Row],[MOOE (Php ''000)]]) -> FALSE | AO4: =ISBLANK(Table37[[#This Row],[CO (Php ''000)]]) -> TRUE
A5: =VLOOKUP(Table37[[#This Row],[OU]],OU!$A$15:$B$34,2,FALSE) -> RFOs | B5: BED 1 - OBLIGATION | C5: RFOII | D5: White Corn | E5: =VLOOKUP(Table37[[#This Row],[SPECIFIC COMMODITY]],TAGS!$W$48:$X$53,2,FALSE) -> Corn | F5: =VLOOKUP(Table37[[#This Row],[PREXC SUB-PROGRAM]],Table5[],2,FALSE) -> TECHNICAL AND SUPPORT SERVICES PROGRAM | G5: =VLOOKUP(Table37[[#This Row],[COMMODITY PREXC SUB-PROGRAM]],TAGS!$U$54:$V$76,2,FALSE) -> PSS | H5: Corn_PSS | I5: =VLOOKUP(Table37[[#This Row],[PI LEVEL 3]],'PI LEVEL'!A:C,3,FALSE) -> Seeds reserved | J5: =VLOOKUP(Table37[[#This Row],[PI LEVEL 3]],Table53729[[Performance Indicator Level 3]:[Performance Indicator Level 1]],2,FALSE) -> Corn Seeds reserved | K5: =VLOOKUP(Table37[[#This Row],[ACTIVITY]],TAGS!B:P,2,FALSE) -> White Corn Seeds reserved | L5: DRRM - White Corn Seed Procured OPV | M5: =VLOOKUP(Table37[[#This Row],[ACTIVITY]],TAGS!$B:$P,4,FALSE) -> Corn Seed Reserve | N5: =VLOOKUP(Table37[[#This Row],[ACTIVITY]],TAGS!$B:$P,5,FALSE) -> Corn Seed Reserve | O5: =VLOOKUP(Table37[[#This Row],[ACTIVITY]],TAGS!$B:$P,6,FALSE) -> White corn seeds reserve | P5: =VLOOKUP(Table37[[#This Row],[ACTIVITY]],TAGS!$B:$P,7,FALSE) -> YES | Q5: =VLOOKUP(Table37[[#This Row],[ACTIVITY]],TAGS!$B:$P,8,FALSE) -> PAP | R5: =VLOOKUP(Table37[[#This Row],[ACTIVITY]],TAGS!$B:$P,10,FALSE) -> PIP | S5: =VLOOKUP(Table37[[#This Row],[ACTIVITY]],TAGS!$B:$P,11,FALSE) -> PICS | T5: =VLOOKUP(Table37[[#This Row],[ACTIVITY]],TAGS!$B:$P,12,FALSE) -> Modernization | U5: =VLOOKUP(Table37[[#This Row],[ACTIVITY]],TAGS!$B:$P,13,FALSE) -> 9. Climate Change Adaptation & Mitigation Measures | V5: =VLOOKUP(Table37[[#This Row],[ACTIVITY]],TAGS!$B:$P,14,FALSE) -> EXPAND AND IMPROVE AVAILABLE AGRI-FISHERY AREAS FOR INCREASED PRODUCTION | W5: =VLOOKUP(Table37[[#This Row],[ACTIVITY]],TAGS!$B:$P,15,FALSE) -> Seed Reserve | X5: =VLOOKUP(Table37[[#This Row],[PI LEVEL 3]],'PI LEVEL'!$A:$G,7,FALSE) -> DA-Level Output | Y5: NO | Z5: MARCH | AA5: =VLOOKUP(Table37[[#This Row],[MONTH]],TAGS!$W$67:$Y$81,2,FALSE) -> 1ST QTR | AB5: =VLOOKUP(Table37[[#This Row],[MONTH]],TAGS!$W$67:$Y$81,3,FALSE) -> 1ST SEMESTER | AC5: =VLOOKUP(Table37[[#This Row],[MONTH]],TAGS!$W$67:$Z$81,4,FALSE) -> 2025 | AD5: 1000 | AF5: =SUM(Table37[[#This Row],[MOOE (Php ''000)]:[CO (Php ''000)]]) -> 1000 | AG5: =ISBLANK(Table37[[#This Row],[PRPOPOSAL/BEDS]]) -> FALSE | AH5: =ISBLANK(Table37[[#This Row],[OU]]) -> FALSE | AI5: =ISBLANK(Table37[[#This Row],[SPECIFIC COMMODITY]]) -> FALSE | AJ5: =ISBLANK(Table37[[#This Row],[COMMODITY PREXC SUB-PROGRAM]]) -> FALSE | AK5: =ISBLANK(Table37[[#This Row],[ACTIVITY]]) -> FALSE | AL5: =ISBLANK(Table37[[#This Row],[TAG-GAD]]) -> FALSE | AM5: =ISBLANK(Table37[[#This Row],[MONTH]]) -> FALSE | AN5: =ISBLANK(Table37[[#This Row],[MOOE (Php ''000)]]) -> FALSE | AO5: =ISBLANK(Table37[[#This Row],[CO (Php ''000)]]) -> TRUE
A6: =VLOOKUP(Table37[[#This Row],[OU]],OU!$A$15:$B$34,2,FALSE) -> RFOs | B6: BED 1 - OBLIGATION | C6: RFOII | D6: Yellow Corn | E6: =VLOOKUP(Table37[[#This Row],[SPECIFIC COMMODITY]],TAGS!$W$48:$X$53,2,FALSE) -> Corn | F6: =VLOOKUP(Table37[[#This Row],[PREXC SUB-PROGRAM]],Table5[],2,FALSE) -> TECHNICAL AND SUPPORT SERVICES PROGRAM | G6: =VLOOKUP(Table37[[#This Row],[COMMODITY PREXC SUB-PROGRAM]],TAGS!$U$54:$V$76,2,FALSE) -> PSS | H6: Corn_PSS | I6: =VLOOKUP(Table37[[#This Row],[PI LEVEL 3]],'PI LEVEL'!A:C,3,FALSE) -> Seeds distributed | J6: =VLOOKUP(Table37[[#This Row],[PI LEVEL 3]],Table53729[[Performance Indicator Level 3]:[Performance Indicator Level 1]],2,FALSE) -> Corn Seeds distributed | K6: =VLOOKUP(Table37[[#This Row],[ACTIVITY]],TAGS!B:P,2,FALSE) -> Yellow Corn Seeds distributed | L6: RCPT - Yellow Corn seeds | M6: =VLOOKUP(Table37[[#This Row],[ACTIVITY]],TAGS!$B:$P,4,FALSE) -> Recommended Corn Production Technology | N6: =VLOOKUP(Table37[[#This Row],[ACTIVITY]],TAGS!$B:$P,5,FALSE) -> Corn Seed Assistance | O6: =VLOOKUP(Table37[[#This Row],[ACTIVITY]],TAGS!$B:$P,6,FALSE) -> Yellow corn seeds | P6: =VLOOKUP(Table37[[#This Row],[ACTIVITY]],TAGS!$B:$P,7,FALSE) -> NO | Q6: =VLOOKUP(Table37[[#This Row],[ACTIVITY]],TAGS!$B:$P,8,FALSE) -> PAP | R6: =VLOOKUP(Table37[[#This Row],[ACTIVITY]],TAGS!$B:$P,10,FALSE) -> PIP | S6: =VLOOKUP(Table37[[#This Row],[ACTIVITY]],TAGS!$B:$P,11,FALSE) -> PICS | T6: =VLOOKUP(Table37[[#This Row],[ACTIVITY]],TAGS!$B:$P,12,FALSE) -> Consolidation | U6: =VLOOKUP(Table37[[#This Row],[ACTIVITY]],TAGS!$B:$P,13,FALSE) -> 1. Bayanihan Agri Cluster | V6: =VLOOKUP(Table37[[#This Row],[ACTIVITY]],TAGS!$B:$P,14,FALSE) -> EXPAND AND IMPROVE AVAILABLE AGRI-FISHERY AREAS FOR INCREASED PRODUCTION | W6: =VLOOKUP(Table37[[#This Row],[ACTIVITY]],TAGS!$B:$P,15,FALSE) -> Farm Inputs | X6: =VLOOKUP(Table37[[#This Row],[PI LEVEL 3]],'PI LEVEL'!$A:$G,7,FALSE) -> DA-Level Output | Y6: NO | Z6: MARCH | AA6: =VLOOKUP(Table37[[#This Row],[MONTH]],TAGS!$W$67:$Y$81,2,FALSE) -> 1ST QTR | AB6: =VLOOKUP(Table37[[#This Row],[MONTH]],TAGS!$W$67:$Y$81,3,FALSE) -> 1ST SEMESTER | AC6: =VLOOKUP(Table37[[#This Row],[MONTH]],TAGS!$W$67:$Z$81,4,FALSE) -> 2025 | AD6: 12000 | AF6: =SUM(Table37[[#This Row],[MOOE (Php ''000)]:[CO (Php ''000)]]) -> 12000 | AG6: =ISBLANK(Table37[[#This Row],[PRPOPOSAL/BEDS]]) -> FALSE | AH6: =ISBLANK(Table37[[#This Row],[OU]]) -> FALSE | AI6: =ISBLANK(Table37[[#This Row],[SPECIFIC COMMODITY]]) -> FALSE | AJ6: =ISBLANK(Table37[[#This Row],[COMMODITY PREXC SUB-PROGRAM]]) -> FALSE | AK6: =ISBLANK(Table37[[#This Row],[ACTIVITY]]) -> FALSE | AL6: =ISBLANK(Table37[[#This Row],[TAG-GAD]]) -> FALSE | AM6: =ISBLANK(Table37[[#This Row],[MONTH]]) -> FALSE | AN6: =ISBLANK(Table37[[#This Row],[MOOE (Php ''000)]]) -> FALSE | AO6: =ISBLANK(Table37[[#This Row],[CO (Php ''000)]]) -> TRUE
A7: =VLOOKUP(Table37[[#This Row],[OU]],OU!$A$15:$B$34,2,FALSE) -> RFOs | B7: BED 1 - OBLIGATION | C7: RFOII | D7: Yellow Corn | E7: =VLOOKUP(Table37[[#This Row],[SPECIFIC COMMODITY]],TAGS!$W$48:$X$53,2,FALSE) -> Corn | F7: =VLOOKUP(Table37[[#This Row],[PREXC SUB-PROGRAM]],Table5[],2,FALSE) -> TECHNICAL AND SUPPORT SERVICES PROGRAM | G7: =VLOOKUP(Table37[[#This Row],[COMMODITY PREXC SUB-PROGRAM]],TAGS!$U$54:$V$76,2,FALSE) -> PSS | H7: Corn_PSS | I7: =VLOOKUP(Table37[[#This Row],[PI LEVEL 3]],'PI LEVEL'!A:C,3,FALSE) -> Fertilizers and other soil ammendment distributed | J7: =VLOOKUP(Table37[[#This Row],[PI LEVEL 3]],Table53729[[Performance Indicator Level 3]:[Performance Indicator Level 1]],2,FALSE) -> Fertilizers distributed | K7: =VLOOKUP(Table37[[#This Row],[ACTIVITY]],TAGS!B:P,2,FALSE) -> Inorganic fertilizer distributed | L7: RCPT - Inorganic fertilizer for YC seeds | M7: =VLOOKUP(Table37[[#This Row],[ACTIVITY]],TAGS!$B:$P,4,FALSE) -> Recommended Corn Production Technology | N7: =VLOOKUP(Table37[[#This Row],[ACTIVITY]],TAGS!$B:$P,5,FALSE) -> Soil Fertilization | O7: =VLOOKUP(Table37[[#This Row],[ACTIVITY]],TAGS!$B:$P,6,FALSE) -> Inorganic fertilizer | P7: =VLOOKUP(Table37[[#This Row],[ACTIVITY]],TAGS!$B:$P,7,FALSE) -> NO | Q7: =VLOOKUP(Table37[[#This Row],[ACTIVITY]],TAGS!$B:$P,8,FALSE) -> PAP | R7: =VLOOKUP(Table37[[#This Row],[ACTIVITY]],TAGS!$B:$P,10,FALSE) -> PIP | S7: =VLOOKUP(Table37[[#This Row],[ACTIVITY]],TAGS!$B:$P,11,FALSE) -> PICS | T7: =VLOOKUP(Table37[[#This Row],[ACTIVITY]],TAGS!$B:$P,12,FALSE) -> Consolidation | U7: =VLOOKUP(Table37[[#This Row],[ACTIVITY]],TAGS!$B:$P,13,FALSE) -> 1. Bayanihan Agri Cluster | V7: =VLOOKUP(Table37[[#This Row],[ACTIVITY]],TAGS!$B:$P,14,FALSE) -> EXPAND AND IMPROVE AVAILABLE AGRI-FISHERY AREAS FOR INCREASED PRODUCTION | W7: =VLOOKUP(Table37[[#This Row],[ACTIVITY]],TAGS!$B:$P,15,FALSE) -> Farm Inputs | X7: =VLOOKUP(Table37[[#This Row],[PI LEVEL 3]],'PI LEVEL'!$A:$G,7,FALSE) -> DA-Level Output | Y7: NO | Z7: APRIL | AA7: =VLOOKUP(Table37[[#This Row],[MONTH]],TAGS!$W$67:$Y$81,2,FALSE) -> 2ND QTR | AB7: =VLOOKUP(Table37[[#This Row],[MONTH]],TAGS!$W$67:$Y$81,3,FALSE) -> 1ST SEMESTER | AC7: =VLOOKUP(Table37[[#This Row],[MONTH]],TAGS!$W$67:$Z$81,4,FALSE) -> 2025 | AD7: 17600 | AF7: =SUM(Table37[[#This Row],[MOOE (Php ''000)]:[CO (Php ''000)]]) -> 17600 | AG7: =ISBLANK(Table37[[#This Row],[PRPOPOSAL/BEDS]]) -> FALSE | AH7: =ISBLANK(Table37[[#This Row],[OU]]) -> FALSE | AI7: =ISBLANK(Table37[[#This Row],[SPECIFIC COMMODITY]]) -> FALSE | AJ7: =ISBLANK(Table37[[#This Row],[COMMODITY PREXC SUB-PROGRAM]]) -> FALSE | AK7: =ISBLANK(Table37[[#This Row],[ACTIVITY]]) -> FALSE | AL7: =ISBLANK(Table37[[#This Row],[TAG-GAD]]) -> FALSE | AM7: =ISBLANK(Table37[[#This Row],[MONTH]]) -> FALSE | AN7: =ISBLANK(Table37[[#This Row],[MOOE (Php ''000)]]) -> FALSE | AO7: =ISBLANK(Table37[[#This Row],[CO (Php ''000)]]) -> TRUE
A8: =VLOOKUP(Table37[[#This Row],[OU]],OU!$A$15:$B$34,2,FALSE) -> RFOs | B8: BED 1 - OBLIGATION | C8: RFOII | D8: Yellow Corn | E8: =VLOOKUP(Table37[[#This Row],[SPECIFIC COMMODITY]],TAGS!$W$48:$X$53,2,FALSE) -> Corn | F8: =VLOOKUP(Table37[[#This Row],[PREXC SUB-PROGRAM]],Table5[],2,FALSE) -> TECHNICAL AND SUPPORT SERVICES PROGRAM | G8: =VLOOKUP(Table37[[#This Row],[COMMODITY PREXC SUB-PROGRAM]],TAGS!$U$54:$V$76,2,FALSE) -> PSS | H8: Corn_PSS | I8: =VLOOKUP(Table37[[#This Row],[PI LEVEL 3]],'PI LEVEL'!A:C,3,FALSE) -> Fertilizers and other soil ammendment distributed | J8: =VLOOKUP(Table37[[#This Row],[PI LEVEL 3]],Table53729[[Performance Indicator Level 3]:[Performance Indicator Level 1]],2,FALSE) -> Fertilizers distributed | K8: =VLOOKUP(Table37[[#This Row],[ACTIVITY]],TAGS!B:P,2,FALSE) -> Inorganic fertilizer distributed | L8: RCPT - Inorganic fertilizer for YC seeds | M8: =VLOOKUP(Table37[[#This Row],[ACTIVITY]],TAGS!$B:$P,4,FALSE) -> Recommended Corn Production Technology | N8: =VLOOKUP(Table37[[#This Row],[ACTIVITY]],TAGS!$B:$P,5,FALSE) -> Soil Fertilization | O8: =VLOOKUP(Table37[[#This Row],[ACTIVITY]],TAGS!$B:$P,6,FALSE) -> Inorganic fertilizer | P8: =VLOOKUP(Table37[[#This Row],[ACTIVITY]],TAGS!$B:$P,7,FALSE) -> NO | Q8: =VLOOKUP(Table37[[#This Row],[ACTIVITY]],TAGS!$B:$P,8,FALSE) -> PAP | R8: =VLOOKUP(Table37[[#This Row],[ACTIVITY]],TAGS!$B:$P,10,FALSE) -> PIP | S8: =VLOOKUP(Table37[[#This Row],[ACTIVITY]],TAGS!$B:$P,11,FALSE) -> PICS | T8: =VLOOKUP(Table37[[#This Row],[ACTIVITY]],TAGS!$B:$P,12,FALSE) -> Consolidation | U8: =VLOOKUP(Table37[[#This Row],[ACTIVITY]],TAGS!$B:$P,13,FALSE) -> 1. Bayanihan Agri Cluster | V8: =VLOOKUP(Table37[[#This Row],[ACTIVITY]],TAGS!$B:$P,14,FALSE) -> EXPAND AND IMPROVE AVAILABLE AGRI-FISHERY AREAS FOR INCREASED PRODUCTION | W8: =VLOOKUP(Table37[[#This Row],[ACTIVITY]],TAGS!$B:$P,15,FALSE) -> Farm Inputs | X8: =VLOOKUP(Table37[[#This Row],[PI LEVEL 3]],'PI LEVEL'!$A:$G,7,FALSE) -> DA-Level Output | Y8: NO | Z8: JULY | AA8: =VLOOKUP(Table37[[#This Row],[MONTH]],TAGS!$W$67:$Y$81,2,FALSE) -> 3RD QTR | AB8: =VLOOKUP(Table37[[#This Row],[MONTH]],TAGS!$W$67:$Y$81,3,FALSE) -> 2ND SEMESTER | AC8: =VLOOKUP(Table37[[#This Row],[MONTH]],TAGS!$W$67:$Z$81,4,FALSE) -> 2025 | AD8: 7150 | AF8: =SUM(Table37[[#This Row],[MOOE (Php ''000)]:[CO (Php ''000)]]) -> 7150 | AG8: =ISBLANK(Table37[[#This Row],[PRPOPOSAL/BEDS]]) -> FALSE | AH8: =ISBLANK(Table37[[#This Row],[OU]]) -> FALSE | AI8: =ISBLANK(Table37[[#This Row],[SPECIFIC COMMODITY]]) -> FALSE | AJ8: =ISBLANK(Table37[[#This Row],[COMMODITY PREXC SUB-PROGRAM]]) -> FALSE | AK8: =ISBLANK(Table37[[#This Row],[ACTIVITY]]) -> FALSE | AL8: =ISBLANK(Table37[[#This Row],[TAG-GAD]]) -> FALSE | AM8: =ISBLANK(Table37[[#This Row],[MONTH]]) -> FALSE | AN8: =ISBLANK(Table37[[#This Row],[MOOE (Php ''000)]]) -> FALSE | AO8: =ISBLANK(Table37[[#This Row],[CO (Php ''000)]]) -> TRUE
A9: =VLOOKUP(Table37[[#This Row],[OU]],OU!$A$15:$B$34,2,FALSE) -> RFOs | B9: BED 1 - OBLIGATION | C9: RFOII | D9: Yellow Corn | E9: =VLOOKUP(Table37[[#This Row],[SPECIFIC COMMODITY]],TAGS!$W$48:$X$53,2,FALSE) -> Corn | F9: =VLOOKUP(Table37[[#This Row],[PREXC SUB-PROGRAM]],Table5[],2,FALSE) -> TECHNICAL AND SUPPORT SERVICES PROGRAM | G9: =VLOOKUP(Table37[[#This Row],[COMMODITY PREXC SUB-PROGRAM]],TAGS!$U$54:$V$76,2,FALSE) -> PSS | H9: Corn_PSS | I9: =VLOOKUP(Table37[[#This Row],[PI LEVEL 3]],'PI LEVEL'!A:C,3,FALSE) -> Fertilizers and other soil ammendment distributed | J9: =VLOOKUP(Table37[[#This Row],[PI LEVEL 3]],Table53729[[Performance Indicator Level 3]:[Performance Indicator Level 1]],2,FALSE) -> Fertilizers distributed | K9: =VLOOKUP(Table37[[#This Row],[ACTIVITY]],TAGS!B:P,2,FALSE) -> Biofertilizer distributed (pack) | L9: Biofertilizer | M9: =VLOOKUP(Table37[[#This Row],[ACTIVITY]],TAGS!$B:$P,4,FALSE) -> Soil amendments | N9: =VLOOKUP(Table37[[#This Row],[ACTIVITY]],TAGS!$B:$P,5,FALSE) -> Soil Fertilization | O9: =VLOOKUP(Table37[[#This Row],[ACTIVITY]],TAGS!$B:$P,6,FALSE) -> Biofertilizer | P9: =VLOOKUP(Table37[[#This Row],[ACTIVITY]],TAGS!$B:$P,7,FALSE) -> NO | Q9: =VLOOKUP(Table37[[#This Row],[ACTIVITY]],TAGS!$B:$P,8,FALSE) -> PAP | R9: =VLOOKUP(Table37[[#This Row],[ACTIVITY]],TAGS!$B:$P,10,FALSE) -> PIP | S9: =VLOOKUP(Table37[[#This Row],[ACTIVITY]],TAGS!$B:$P,11,FALSE) -> PICS | T9: =VLOOKUP(Table37[[#This Row],[ACTIVITY]],TAGS!$B:$P,12,FALSE) -> Consolidation | U9: =VLOOKUP(Table37[[#This Row],[ACTIVITY]],TAGS!$B:$P,13,FALSE) -> 1. Bayanihan Agri Cluster | V9: =VLOOKUP(Table37[[#This Row],[ACTIVITY]],TAGS!$B:$P,14,FALSE) -> EXPAND AND IMPROVE AVAILABLE AGRI-FISHERY AREAS FOR INCREASED PRODUCTION | W9: =VLOOKUP(Table37[[#This Row],[ACTIVITY]],TAGS!$B:$P,15,FALSE) -> Farm Inputs | X9: =VLOOKUP(Table37[[#This Row],[PI LEVEL 3]],'PI LEVEL'!$A:$G,7,FALSE) -> DA-Level Output | Y9: NO | Z9: MARCH | AA9: =VLOOKUP(Table37[[#This Row],[MONTH]],TAGS!$W$67:$Y$81,2,FALSE) -> 1ST QTR | AB9: =VLOOKUP(Table37[[#This Row],[MONTH]],TAGS!$W$67:$Y$81,3,FALSE) -> 1ST SEMESTER | AC9: =VLOOKUP(Table37[[#This Row],[MONTH]],TAGS!$W$67:$Z$81,4,FALSE) -> 2025 | AD9: 2720 | AF9: =SUM(Table37[[#This Row],[MOOE (Php ''000)]:[CO (Php ''000)]]) -> 2720 | AG9: =ISBLANK(Table37[[#This Row],[PRPOPOSAL/BEDS]]) -> FALSE | AH9: =ISBLANK(Table37[[#This Row],[OU]]) -> FALSE | AI9: =ISBLANK(Table37[[#This Row],[SPECIFIC COMMODITY]]) -> FALSE | AJ9: =ISBLANK(Table37[[#This Row],[COMMODITY PREXC SUB-PROGRAM]]) -> FALSE | AK9: =ISBLANK(Table37[[#This Row],[ACTIVITY]]) -> FALSE | AL9: =ISBLANK(Table37[[#This Row],[TAG-GAD]]) -> FALSE | AM9: =ISBLANK(Table37[[#This Row],[MONTH]]) -> FALSE | AN9: =ISBLANK(Table37[[#This Row],[MOOE (Php ''000)]]) -> FALSE | AO9: =ISBLANK(Table37[[#This Row],[CO (Php ''000)]]) -> TRUE
A10: =VLOOKUP(Table37[[#This Row],[OU]],OU!$A$15:$B$34,2,FALSE) -> RFOs | B10: BED 1 - OBLIGATION | C10: RFOII | D10: Yellow Corn | E10: =VLOOKUP(Table37[[#This Row],[SPECIFIC COMMODITY]],TAGS!$W$48:$X$53,2,FALSE) -> Corn | F10: =VLOOKUP(Table37[[#This Row],[PREXC SUB-PROGRAM]],Table5[],2,FALSE) -> TECHNICAL AND SUPPORT SERVICES PROGRAM | G10: =VLOOKUP(Table37[[#This Row],[COMMODITY PREXC SUB-PROGRAM]],TAGS!$U$54:$V$76,2,FALSE) -> PSS | H10: Corn_PSS | I10: =VLOOKUP(Table37[[#This Row],[PI LEVEL 3]],'PI LEVEL'!A:C,3,FALSE) -> Fertilizers and other soil ammendment distributed | J10: =VLOOKUP(Table37[[#This Row],[PI LEVEL 3]],Table53729[[Performance Indicator Level 3]:[Performance Indicator Level 1]],2,FALSE) -> Fertilizers distributed | K10: =VLOOKUP(Table37[[#This Row],[ACTIVITY]],TAGS!B:P,2,FALSE) -> Organic fertilizer distributed | L10: Soil Ameliorant | M10: =VLOOKUP(Table37[[#This Row],[ACTIVITY]],TAGS!$B:$P,4,FALSE) -> Soil amendments | N10: =VLOOKUP(Table37[[#This Row],[ACTIVITY]],TAGS!$B:$P,5,FALSE) -> Soil Fertilization | O10: =VLOOKUP(Table37[[#This Row],[ACTIVITY]],TAGS!$B:$P,6,FALSE) -> Soil ameliorant | P10: =VLOOKUP(Table37[[#This Row],[ACTIVITY]],TAGS!$B:$P,7,FALSE) -> NO | Q10: =VLOOKUP(Table37[[#This Row],[ACTIVITY]],TAGS!$B:$P,8,FALSE) -> PAP | R10: =VLOOKUP(Table37[[#This Row],[ACTIVITY]],TAGS!$B:$P,10,FALSE) -> PIP | S10: =VLOOKUP(Table37[[#This Row],[ACTIVITY]],TAGS!$B:$P,11,FALSE) -> PICS | T10: =VLOOKUP(Table37[[#This Row],[ACTIVITY]],TAGS!$B:$P,12,FALSE) -> Consolidation | U10: =VLOOKUP(Table37[[#This Row],[ACTIVITY]],TAGS!$B:$P,13,FALSE) -> 1. Bayanihan Agri Cluster | V10: =VLOOKUP(Table37[[#This Row],[ACTIVITY]],TAGS!$B:$P,14,FALSE) -> EXPAND AND IMPROVE AVAILABLE AGRI-FISHERY AREAS FOR INCREASED PRODUCTION | W10: =VLOOKUP(Table37[[#This Row],[ACTIVITY]],TAGS!$B:$P,15,FALSE) -> Farm Inputs | X10: =VLOOKUP(Table37[[#This Row],[PI LEVEL 3]],'PI LEVEL'!$A:$G,7,FALSE) -> DA-Level Output | Y10: NO | Z10: MARCH | AA10: =VLOOKUP(Table37[[#This Row],[MONTH]],TAGS!$W$67:$Y$81,2,FALSE) -> 1ST QTR | AB10: =VLOOKUP(Table37[[#This Row],[MONTH]],TAGS!$W$67:$Y$81,3,FALSE) -> 1ST SEMESTER | AC10: =VLOOKUP(Table37[[#This Row],[MONTH]],TAGS!$W$67:$Z$81,4,FALSE) -> 2025 | AD10: 7000 | AF10: =SUM(Table37[[#This Row],[MOOE (Php ''000)]:[CO (Php ''000)]]) -> 7000 | AG10: =ISBLANK(Table37[[#This Row],[PRPOPOSAL/BEDS]]) -> FALSE | AH10: =ISBLANK(Table37[[#This Row],[OU]]) -> FALSE | AI10: =ISBLANK(Table37[[#This Row],[SPECIFIC COMMODITY]]) -> FALSE | AJ10: =ISBLANK(Table37[[#This Row],[COMMODITY PREXC SUB-PROGRAM]]) -> FALSE | AK10: =ISBLANK(Table37[[#This Row],[ACTIVITY]]) -> FALSE | AL10: =ISBLANK(Table37[[#This Row],[TAG-GAD]]) -> FALSE | AM10: =ISBLANK(Table37[[#This Row],[MONTH]]) -> FALSE | AN10: =ISBLANK(Table37[[#This Row],[MOOE (Php ''000)]]) -> FALSE | AO10: =ISBLANK(Table37[[#This Row],[CO (Php ''000)]]) -> TRUE
A11: =VLOOKUP(Table37[[#This Row],[OU]],OU!$A$15:$B$34,2,FALSE) -> RFOs | B11: BED 1 - OBLIGATION | C11: RFOII | D11: Yellow Corn | E11: =VLOOKUP(Table37[[#This Row],[SPECIFIC COMMODITY]],TAGS!$W$48:$X$53,2,FALSE) -> Corn | F11: =VLOOKUP(Table37[[#This Row],[PREXC SUB-PROGRAM]],Table5[],2,FALSE) -> TECHNICAL AND SUPPORT SERVICES PROGRAM | G11: =VLOOKUP(Table37[[#This Row],[COMMODITY PREXC SUB-PROGRAM]],TAGS!$U$54:$V$76,2,FALSE) -> PSS | H11: Corn_PSS | I11: =VLOOKUP(Table37[[#This Row],[PI LEVEL 3]],'PI LEVEL'!A:C,3,FALSE) -> Fertilizers and other soil ammendment distributed | J11: =VLOOKUP(Table37[[#This Row],[PI LEVEL 3]],Table53729[[Performance Indicator Level 3]:[Performance Indicator Level 1]],2,FALSE) -> Fertilizers distributed | K11: =VLOOKUP(Table37[[#This Row],[ACTIVITY]],TAGS!B:P,2,FALSE) -> Organic fertilizer distributed | L11: Soil Ameliorant | M11: =VLOOKUP(Table37[[#This Row],[ACTIVITY]],TAGS!$B:$P,4,FALSE) -> Soil amendments | N11: =VLOOKUP(Table37[[#This Row],[ACTIVITY]],TAGS!$B:$P,5,FALSE) -> Soil Fertilization | O11: =VLOOKUP(Table37[[#This Row],[ACTIVITY]],TAGS!$B:$P,6,FALSE) -> Soil ameliorant | P11: =VLOOKUP(Table37[[#This Row],[ACTIVITY]],TAGS!$B:$P,7,FALSE) -> NO | Q11: =VLOOKUP(Table37[[#This Row],[ACTIVITY]],TAGS!$B:$P,8,FALSE) -> PAP | R11: =VLOOKUP(Table37[[#This Row],[ACTIVITY]],TAGS!$B:$P,10,FALSE) -> PIP | S11: =VLOOKUP(Table37[[#This Row],[ACTIVITY]],TAGS!$B:$P,11,FALSE) -> PICS | T11: =VLOOKUP(Table37[[#This Row],[ACTIVITY]],TAGS!$B:$P,12,FALSE) -> Consolidation | U11: =VLOOKUP(Table37[[#This Row],[ACTIVITY]],TAGS!$B:$P,13,FALSE) -> 1. Bayanihan Agri Cluster | V11: =VLOOKUP(Table37[[#This Row],[ACTIVITY]],TAGS!$B:$P,14,FALSE) -> EXPAND AND IMPROVE AVAILABLE AGRI-FISHERY AREAS FOR INCREASED PRODUCTION | W11: =VLOOKUP(Table37[[#This Row],[ACTIVITY]],TAGS!$B:$P,15,FALSE) -> Farm Inputs | X11: =VLOOKUP(Table37[[#This Row],[PI LEVEL 3]],'PI LEVEL'!$A:$G,7,FALSE) -> DA-Level Output | Y11: NO | Z11: JULY | AA11: =VLOOKUP(Table37[[#This Row],[MONTH]],TAGS!$W$67:$Y$81,2,FALSE) -> 3RD QTR | AB11: =VLOOKUP(Table37[[#This Row],[MONTH]],TAGS!$W$67:$Y$81,3,FALSE) -> 2ND SEMESTER | AC11: =VLOOKUP(Table37[[#This Row],[MONTH]],TAGS!$W$67:$Z$81,4,FALSE) -> 2025 | AD11: 3000 | AF11: =SUM(Table37[[#This Row],[MOOE (Php ''000)]:[CO (Php ''000)]]) -> 3000 | AG11: =ISBLANK(Table37[[#This Row],[PRPOPOSAL/BEDS]]) -> FALSE | AH11: =ISBLANK(Table37[[#This Row],[OU]]) -> FALSE | AI11: =ISBLANK(Table37[[#This Row],[SPECIFIC COMMODITY]]) -> FALSE | AJ11: =ISBLANK(Table37[[#This Row],[COMMODITY PREXC SUB-PROGRAM]]) -> FALSE | AK11: =ISBLANK(Table37[[#This Row],[ACTIVITY]]) -> FALSE | AL11: =ISBLANK(Table37[[#This Row],[TAG-GAD]]) -> FALSE | AM11: =ISBLANK(Table37[[#This Row],[MONTH]]) -> FALSE | AN11: =ISBLANK(Table37[[#This Row],[MOOE (Php ''000)]]) -> FALSE | AO11: =ISBLANK(Table37[[#This Row],[CO (Php ''000)]]) -> TRUE
A12: =VLOOKUP(Table37[[#This Row],[OU]],OU!$A$15:$B$34,2,FALSE) -> RFOs | B12: BED 1 - OBLIGATION | C12: RFOII | D12: Yellow Corn | E12: =VLOOKUP(Table37[[#This Row],[SPECIFIC COMMODITY]],TAGS!$W$48:$X$53,2,FALSE) -> Corn | F12: =VLOOKUP(Table37[[#This Row],[PREXC SUB-PROGRAM]],Table5[],2,FALSE) -> TECHNICAL AND SUPPORT SERVICES PROGRAM | G12: =VLOOKUP(Table37[[#This Row],[COMMODITY PREXC SUB-PROGRAM]],TAGS!$U$54:$V$76,2,FALSE) -> PSS | H12: Corn_PSS | I12: =VLOOKUP(Table37[[#This Row],[PI LEVEL 3]],'PI LEVEL'!A:C,3,FALSE) -> Seeds distributed | J12: =VLOOKUP(Table37[[#This Row],[PI LEVEL 3]],Table53729[[Performance Indicator Level 3]:[Performance Indicator Level 1]],2,FALSE) -> Corn Seeds distributed | K12: =VLOOKUP(Table37[[#This Row],[ACTIVITY]],TAGS!B:P,2,FALSE) -> Yellow Corn Seeds distributed | L12: YCPEP - Yellow Corn Hybrid seeds | M12: =VLOOKUP(Table37[[#This Row],[ACTIVITY]],TAGS!$B:$P,4,FALSE) -> Yellow Corn Production Enhancement Project | N12: =VLOOKUP(Table37[[#This Row],[ACTIVITY]],TAGS!$B:$P,5,FALSE) -> Corn Seed Assistance | O12: =VLOOKUP(Table37[[#This Row],[ACTIVITY]],TAGS!$B:$P,6,FALSE) -> Yellow corn seeds | P12: =VLOOKUP(Table37[[#This Row],[ACTIVITY]],TAGS!$B:$P,7,FALSE) -> NO | Q12: =VLOOKUP(Table37[[#This Row],[ACTIVITY]],TAGS!$B:$P,8,FALSE) -> PAP | R12: =VLOOKUP(Table37[[#This Row],[ACTIVITY]],TAGS!$B:$P,10,FALSE) -> PIP | S12: =VLOOKUP(Table37[[#This Row],[ACTIVITY]],TAGS!$B:$P,11,FALSE) -> PICS | T12: =VLOOKUP(Table37[[#This Row],[ACTIVITY]],TAGS!$B:$P,12,FALSE) -> Consolidation | U12: =VLOOKUP(Table37[[#This Row],[ACTIVITY]],TAGS!$B:$P,13,FALSE) -> 1. Bayanihan Agri Cluster | V12: =VLOOKUP(Table37[[#This Row],[ACTIVITY]],TAGS!$B:$P,14,FALSE) -> EXPAND AND IMPROVE AVAILABLE AGRI-FISHERY AREAS FOR INCREASED PRODUCTION | W12: =VLOOKUP(Table37[[#This Row],[ACTIVITY]],TAGS!$B:$P,15,FALSE) -> Farm Inputs | X12: =VLOOKUP(Table37[[#This Row],[PI LEVEL 3]],'PI LEVEL'!$A:$G,7,FALSE) -> DA-Level Output | Y12: NO | Z12: APRIL | AA12: =VLOOKUP(Table37[[#This Row],[MONTH]],TAGS!$W$67:$Y$81,2,FALSE) -> 2ND QTR | AB12: =VLOOKUP(Table37[[#This Row],[MONTH]],TAGS!$W$67:$Y$81,3,FALSE) -> 1ST SEMESTER | AC12: =VLOOKUP(Table37[[#This Row],[MONTH]],TAGS!$W$67:$Z$81,4,FALSE) -> 2025 | AD12: 324000 | AF12: =SUM(Table37[[#This Row],[MOOE (Php ''000)]:[CO (Php ''000)]]) -> 324000 | AG12: =ISBLANK(Table37[[#This Row],[PRPOPOSAL/BEDS]]) -> FALSE | AH12: =ISBLANK(Table37[[#This Row],[OU]]) -> FALSE | AI12: =ISBLANK(Table37[[#This Row],[SPECIFIC COMMODITY]]) -> FALSE | AJ12: =ISBLANK(Table37[[#This Row],[COMMODITY PREXC SUB-PROGRAM]]) -> FALSE | AK12: =ISBLANK(Table37[[#This Row],[ACTIVITY]]) -> FALSE | AL12: =ISBLANK(Table37[[#This Row],[TAG-GAD]]) -> FALSE | AM12: =ISBLANK(Table37[[#This Row],[MONTH]]) -> FALSE | AN12: =ISBLANK(Table37[[#This Row],[MOOE (Php ''000)]]) -> FALSE | AO12: =ISBLANK(Table37[[#This Row],[CO (Php ''000)]]) -> TRUE
A13: =VLOOKUP(Table37[[#This Row],[OU]],OU!$A$15:$B$34,2,FALSE) -> RFOs | B13: BED 1 - OBLIGATION | C13: RFOII | D13: Yellow Corn | E13: =VLOOKUP(Table37[[#This Row],[SPECIFIC COMMODITY]],TAGS!$W$48:$X$53,2,FALSE) -> Corn | F13: =VLOOKUP(Table37[[#This Row],[PREXC SUB-PROGRAM]],Table5[],2,FALSE) -> TECHNICAL AND SUPPORT SERVICES PROGRAM | G13: =VLOOKUP(Table37[[#This Row],[COMMODITY PREXC SUB-PROGRAM]],TAGS!$U$54:$V$76,2,FALSE) -> PSS | H13: Corn_PSS | I13: =VLOOKUP(Table37[[#This Row],[PI LEVEL 3]],'PI LEVEL'!A:C,3,FALSE) -> Fertilizers and other soil ammendment distributed | J13: =VLOOKUP(Table37[[#This Row],[PI LEVEL 3]],Table53729[[Performance Indicator Level 3]:[Performance Indicator Level 1]],2,FALSE) -> Fertilizers distributed | K13: =VLOOKUP(Table37[[#This Row],[ACTIVITY]],TAGS!B:P,2,FALSE) -> Inorganic fertilizer distributed | L13: YCPEP - Inorganic fertilizer for YC Hybrid seeds | M13: =VLOOKUP(Table37[[#This Row],[ACTIVITY]],TAGS!$B:$P,4,FALSE) -> Yellow Corn Production Enhancement Project | N13: =VLOOKUP(Table37[[#This Row],[ACTIVITY]],TAGS!$B:$P,5,FALSE) -> Soil Fertilization | O13: =VLOOKUP(Table37[[#This Row],[ACTIVITY]],TAGS!$B:$P,6,FALSE) -> Inorganic fertilizer | P13: =VLOOKUP(Table37[[#This Row],[ACTIVITY]],TAGS!$B:$P,7,FALSE) -> NO | Q13: =VLOOKUP(Table37[[#This Row],[ACTIVITY]],TAGS!$B:$P,8,FALSE) -> PAP | R13: =VLOOKUP(Table37[[#This Row],[ACTIVITY]],TAGS!$B:$P,10,FALSE) -> PIP | S13: =VLOOKUP(Table37[[#This Row],[ACTIVITY]],TAGS!$B:$P,11,FALSE) -> PICS | T13: =VLOOKUP(Table37[[#This Row],[ACTIVITY]],TAGS!$B:$P,12,FALSE) -> Consolidation | U13: =VLOOKUP(Table37[[#This Row],[ACTIVITY]],TAGS!$B:$P,13,FALSE) -> 1. Bayanihan Agri Cluster | V13: =VLOOKUP(Table37[[#This Row],[ACTIVITY]],TAGS!$B:$P,14,FALSE) -> EXPAND AND IMPROVE AVAILABLE AGRI-FISHERY AREAS FOR INCREASED PRODUCTION | W13: =VLOOKUP(Table37[[#This Row],[ACTIVITY]],TAGS!$B:$P,15,FALSE) -> Farm Inputs | X13: =VLOOKUP(Table37[[#This Row],[PI LEVEL 3]],'PI LEVEL'!$A:$G,7,FALSE) -> DA-Level Output | Y13: NO | Z13: MARCH | AA13: =VLOOKUP(Table37[[#This Row],[MONTH]],TAGS!$W$67:$Y$81,2,FALSE) -> 1ST QTR | AB13: =VLOOKUP(Table37[[#This Row],[MONTH]],TAGS!$W$67:$Y$81,3,FALSE) -> 1ST SEMESTER | AC13: =VLOOKUP(Table37[[#This Row],[MONTH]],TAGS!$W$67:$Z$81,4,FALSE) -> 2025 | AD13: 86400 | AF13: =SUM(Table37[[#This Row],[MOOE (Php ''000)]:[CO (Php ''000)]]) -> 86400 | AG13: =ISBLANK(Table37[[#This Row],[PRPOPOSAL/BEDS]]) -> FALSE | AH13: =ISBLANK(Table37[[#This Row],[OU]]) -> FALSE | AI13: =ISBLANK(Table37[[#This Row],[SPECIFIC COMMODITY]]) -> FALSE | AJ13: =ISBLANK(Table37[[#This Row],[COMMODITY PREXC SUB-PROGRAM]]) -> FALSE | AK13: =ISBLANK(Table37[[#This Row],[ACTIVITY]]) -> FALSE | AL13: =ISBLANK(Table37[[#This Row],[TAG-GAD]]) -> FALSE | AM13: =ISBLANK(Table37[[#This Row],[MONTH]]) -> FALSE | AN13: =ISBLANK(Table37[[#This Row],[MOOE (Php ''000)]]) -> FALSE | AO13: =ISBLANK(Table37[[#This Row],[CO (Php ''000)]]) -> TRUE
... A29: =VLOOKUP(Table37[[#This Row],[OU]],OU!$A$15:$B$34,2,FALSE) -> RFOs | B29: BED 1 - OBLIGATION | C29: RFOII | D29: Soybean | E29: =VLOOKUP(Table37[[#This Row],[SPECIFIC COMMODITY]],TAGS!$W$48:$X$53,2,FALSE) -> Soybean | F29: =VLOOKUP(Table37[[#This Row],[PREXC SUB-PROGRAM]],Table5[],2,FALSE) -> TECHNICAL AND SUPPORT SERVICES PROGRAM | G29: =VLOOKUP(Table37[[#This Row],[COMMODITY PREXC SUB-PROGRAM]],TAGS!$U$54:$V$76,2,FALSE) -> PSS | H29: Soybean_PSS | I29: =VLOOKUP(Table37[[#This Row],[PI LEVEL 3]],'PI LEVEL'!A:C,3,FALSE) -> Fertilizers and other soil ammendment distributed | J29: =VLOOKUP(Table37[[#This Row],[PI LEVEL 3]],Table53729[[Performance Indicator Level 3]:[Performance Indicator Level 1]],2,FALSE) -> Fertilizers distributed | K29: =VLOOKUP(Table37[[#This Row],[ACTIVITY]],TAGS!B:P,2,FALSE) -> Inorganic fertilizer distributed | L29: Inorganic fertilizer for Soybean | M29: =VLOOKUP(Table37[[#This Row],[ACTIVITY]],TAGS!$B:$P,4,FALSE) -> Soybean Production Enhancement Project | N29: =VLOOKUP(Table37[[#This Row],[ACTIVITY]],TAGS!$B:$P,5,FALSE) -> Soil Fertilization | O29: =VLOOKUP(Table37[[#This Row],[ACTIVITY]],TAGS!$B:$P,6,FALSE) -> Inorganic fertilizer | P29: =VLOOKUP(Table37[[#This Row],[ACTIVITY]],TAGS!$B:$P,7,FALSE) -> NO | Q29: =VLOOKUP(Table37[[#This Row],[ACTIVITY]],TAGS!$B:$P,8,FALSE) -> PAP | R29: =VLOOKUP(Table37[[#This Row],[ACTIVITY]],TAGS!$B:$P,10,FALSE) -> PIP | S29: =VLOOKUP(Table37[[#This Row],[ACTIVITY]],TAGS!$B:$P,11,FALSE) -> PICS | T29: =VLOOKUP(Table37[[#This Row],[ACTIVITY]],TAGS!$B:$P,12,FALSE) -> Consolidation | U29: =VLOOKUP(Table37[[#This Row],[ACTIVITY]],TAGS!$B:$P,13,FALSE) -> 1. Bayanihan Agri Cluster | V29: =VLOOKUP(Table37[[#This Row],[ACTIVITY]],TAGS!$B:$P,14,FALSE) -> EXPAND AND IMPROVE AVAILABLE AGRI-FISHERY AREAS FOR INCREASED PRODUCTION | W29: =VLOOKUP(Table37[[#This Row],[ACTIVITY]],TAGS!$B:$P,15,FALSE) -> Farm Inputs | X29: =VLOOKUP(Table37[[#This Row],[PI LEVEL 3]],'PI LEVEL'!$A:$G,7,FALSE) -> DA-Level Output | Y29: NO | Z29: FEBRUARY | AA29: =VLOOKUP(Table37[[#This Row],[MONTH]],TAGS!$W$67:$Y$81,2,FALSE) -> 1ST QTR | AB29: =VLOOKUP(Table37[[#This Row],[MONTH]],TAGS!$W$67:$Y$81,3,FALSE) -> 1ST SEMESTER | AC29: =VLOOKUP(Table37[[#This Row],[MONTH]],TAGS!$W$67:$Z$81,4,FALSE) -> 2025 | AD29: 113 | AF29: =SUM(Table37[[#This Row],[MOOE (Php ''000)]:[CO (Php ''000)]]) -> 113 | AG29: =ISBLANK(Table37[[#This Row],[PRPOPOSAL/BEDS]]) -> FALSE | AH29: =ISBLANK(Table37[[#This Row],[OU]]) -> FALSE | AI29: =ISBLANK(Table37[[#This Row],[SPECIFIC COMMODITY]]) -> FALSE | AJ29: =ISBLANK(Table37[[#This Row],[COMMODITY PREXC SUB-PROGRAM]]) -> FALSE | AK29: =ISBLANK(Table37[[#This Row],[ACTIVITY]]) -> FALSE | AL29: =ISBLANK(Table37[[#This Row],[TAG-GAD]]) -> FALSE | AM29: =ISBLANK(Table37[[#This Row],[MONTH]]) -> FALSE | AN29: =ISBLANK(Table37[[#This Row],[MOOE (Php ''000)]]) -> FALSE | AO29: =ISBLANK(Table37[[#This Row],[CO (Php ''000)]]) -> TRUE
A30: =VLOOKUP(Table37[[#This Row],[OU]],OU!$A$15:$B$34,2,FALSE) -> RFOs | B30: BED 1 - OBLIGATION | C30: RFOII | D30: Multi_commodity | E30: =VLOOKUP(Table37[[#This Row],[SPECIFIC COMMODITY]],TAGS!$W$48:$X$53,2,FALSE) -> Multi_commodity | F30: =VLOOKUP(Table37[[#This Row],[PREXC SUB-PROGRAM]],Table5[],2,FALSE) -> TECHNICAL AND SUPPORT SERVICES PROGRAM | G30: =VLOOKUP(Table37[[#This Row],[COMMODITY PREXC SUB-PROGRAM]],TAGS!$U$54:$V$76,2,FALSE) -> PSS | H30: Multicommodity_PSS | I30: =VLOOKUP(Table37[[#This Row],[PI LEVEL 3]],'PI LEVEL'!A:C,3,FALSE) -> Farm machinery and equipment procured for stations | J30: =VLOOKUP(Table37[[#This Row],[PI LEVEL 3]],Table53729[[Performance Indicator Level 3]:[Performance Indicator Level 1]],2,FALSE) -> Farm machinery and equipment procured for stations | K30: =VLOOKUP(Table37[[#This Row],[ACTIVITY]],TAGS!B:P,2,FALSE) -> Production machinery and equipment procured for stations | L30: DA Stations - Hand tractor with corn planter | M30: =VLOOKUP(Table37[[#This Row],[ACTIVITY]],TAGS!$B:$P,4,FALSE) -> DA Facilities Management | N30: =VLOOKUP(Table37[[#This Row],[ACTIVITY]],TAGS!$B:$P,5,FALSE) -> Support to DA Stations | O30: =VLOOKUP(Table37[[#This Row],[ACTIVITY]],TAGS!$B:$P,6,FALSE) -> Machinery & Equipment for DA Stations | P30: =VLOOKUP(Table37[[#This Row],[ACTIVITY]],TAGS!$B:$P,7,FALSE) -> NO | Q30: =VLOOKUP(Table37[[#This Row],[ACTIVITY]],TAGS!$B:$P,8,FALSE) -> PAP | R30: =VLOOKUP(Table37[[#This Row],[ACTIVITY]],TAGS!$B:$P,10,FALSE) -> PIP | S30: =VLOOKUP(Table37[[#This Row],[ACTIVITY]],TAGS!$B:$P,11,FALSE) -> PICS | T30: =VLOOKUP(Table37[[#This Row],[ACTIVITY]],TAGS!$B:$P,12,FALSE) -> Modernization | U30: =VLOOKUP(Table37[[#This Row],[ACTIVITY]],TAGS!$B:$P,13,FALSE) -> 8. Farm Mechanization and Farm Investments | V30: =VLOOKUP(Table37[[#This Row],[ACTIVITY]],TAGS!$B:$P,14,FALSE) -> 0 | W30: =VLOOKUP(Table37[[#This Row],[ACTIVITY]],TAGS!$B:$P,15,FALSE) -> DA Station | X30: =VLOOKUP(Table37[[#This Row],[PI LEVEL 3]],'PI LEVEL'!$A:$G,7,FALSE) -> DA-Level Output | Y30: NO | Z30: APRIL | AA30: =VLOOKUP(Table37[[#This Row],[MONTH]],TAGS!$W$67:$Y$81,2,FALSE) -> 2ND QTR | AB30: =VLOOKUP(Table37[[#This Row],[MONTH]],TAGS!$W$67:$Y$81,3,FALSE) -> 1ST SEMESTER | AC30: =VLOOKUP(Table37[[#This Row],[MONTH]],TAGS!$W$67:$Z$81,4,FALSE) -> 2025 | AE30: 1200 | AF30: =SUM(Table37[[#This Row],[MOOE (Php ''000)]:[CO (Php ''000)]]) -> 1200 | AG30: =ISBLANK(Table37[[#This Row],[PRPOPOSAL/BEDS]]) -> FALSE | AH30: =ISBLANK(Table37[[#This Row],[OU]]) -> FALSE | AI30: =ISBLANK(Table37[[#This Row],[SPECIFIC COMMODITY]]) -> FALSE | AJ30: =ISBLANK(Table37[[#This Row],[COMMODITY PREXC SUB-PROGRAM]]) -> FALSE | AK30: =ISBLANK(Table37[[#This Row],[ACTIVITY]]) -> FALSE | AL30: =ISBLANK(Table37[[#This Row],[TAG-GAD]]) -> FALSE | AM30: =ISBLANK(Table37[[#This Row],[MONTH]]) -> FALSE | AN30: =ISBLANK(Table37[[#This Row],[MOOE (Php ''000)]]) -> TRUE | AO30: =ISBLANK(Table37[[#This Row],[CO (Php ''000)]]) -> FALSE
A31: =VLOOKUP(Table37[[#This Row],[OU]],OU!$A$15:$B$34,2,FALSE) -> RFOs | B31: BED 1 - OBLIGATION | C31: RFOII | D31: Multi_commodity | E31: =VLOOKUP(Table37[[#This Row],[SPECIFIC COMMODITY]],TAGS!$W$48:$X$53,2,FALSE) -> Multi_commodity | F31: =VLOOKUP(Table37[[#This Row],[PREXC SUB-PROGRAM]],Table5[],2,FALSE) -> TECHNICAL AND SUPPORT SERVICES PROGRAM | G31: =VLOOKUP(Table37[[#This Row],[COMMODITY PREXC SUB-PROGRAM]],TAGS!$U$54:$V$76,2,FALSE) -> PSS | H31: Multicommodity_PSS | I31: =VLOOKUP(Table37[[#This Row],[PI LEVEL 3]],'PI LEVEL'!A:C,3,FALSE) -> Farm machinery and equipment procured for stations | J31: =VLOOKUP(Table37[[#This Row],[PI LEVEL 3]],Table53729[[Performance Indicator Level 3]:[Performance Indicator Level 1]],2,FALSE) -> Farm machinery and equipment procured for stations | K31: =VLOOKUP(Table37[[#This Row],[ACTIVITY]],TAGS!B:P,2,FALSE) -> Postharvest machinery and equipment procured for stations | L31: DA Stations - Silage Chopper | M31: =VLOOKUP(Table37[[#This Row],[ACTIVITY]],TAGS!$B:$P,4,FALSE) -> DA Facilities Management | N31: =VLOOKUP(Table37[[#This Row],[ACTIVITY]],TAGS!$B:$P,5,FALSE) -> Support to DA Stations | O31: =VLOOKUP(Table37[[#This Row],[ACTIVITY]],TAGS!$B:$P,6,FALSE) -> Machinery & Equipment for DA Stations | P31: =VLOOKUP(Table37[[#This Row],[ACTIVITY]],TAGS!$B:$P,7,FALSE) -> NO | Q31: =VLOOKUP(Table37[[#This Row],[ACTIVITY]],TAGS!$B:$P,8,FALSE) -> PAP | R31: =VLOOKUP(Table37[[#This Row],[ACTIVITY]],TAGS!$B:$P,10,FALSE) -> PIP | S31: =VLOOKUP(Table37[[#This Row],[ACTIVITY]],TAGS!$B:$P,11,FALSE) -> PICS | T31: =VLOOKUP(Table37[[#This Row],[ACTIVITY]],TAGS!$B:$P,12,FALSE) -> Modernization | U31: =VLOOKUP(Table37[[#This Row],[ACTIVITY]],TAGS!$B:$P,13,FALSE) -> 8. Farm Mechanization and Farm Investments | V31: =VLOOKUP(Table37[[#This Row],[ACTIVITY]],TAGS!$B:$P,14,FALSE) -> 0 | W31: =VLOOKUP(Table37[[#This Row],[ACTIVITY]],TAGS!$B:$P,15,FALSE) -> DA Station | X31: =VLOOKUP(Table37[[#This Row],[PI LEVEL 3]],'PI LEVEL'!$A:$G,7,FALSE) -> DA-Level Output | Y31: NO | Z31: APRIL | AA31: =VLOOKUP(Table37[[#This Row],[MONTH]],TAGS!$W$67:$Y$81,2,FALSE) -> 2ND QTR | AB31: =VLOOKUP(Table37[[#This Row],[MONTH]],TAGS!$W$67:$Y$81,3,FALSE) -> 1ST SEMESTER | AC31: =VLOOKUP(Table37[[#This Row],[MONTH]],TAGS!$W$67:$Z$81,4,FALSE) -> 2025 | AE31: 240 | AF31: =SUM(Table37[[#This Row],[MOOE (Php ''000)]:[CO (Php ''000)]]) -> 240 | AG31: =ISBLANK(Table37[[#This Row],[PRPOPOSAL/BEDS]]) -> FALSE | AH31: =ISBLANK(Table37[[#This Row],[OU]]) -> FALSE | AI31: =ISBLANK(Table37[[#This Row],[SPECIFIC COMMODITY]]) -> FALSE | AJ31: =ISBLANK(Table37[[#This Row],[COMMODITY PREXC SUB-PROGRAM]]) -> FALSE | AK31: =ISBLANK(Table37[[#This Row],[ACTIVITY]]) -> FALSE | AL31: =ISBLANK(Table37[[#This Row],[TAG-GAD]]) -> FALSE | AM31: =ISBLANK(Table37[[#This Row],[MONTH]]) -> FALSE | AN31: =ISBLANK(Table37[[#This Row],[MOOE (Php ''000)]]) -> TRUE | AO31: =ISBLANK(Table37[[#This Row],[CO (Php ''000)]]) -> FALSE
A32: =VLOOKUP(Table37[[#This Row],[OU]],OU!$A$15:$B$34,2,FALSE) -> RFOs | B32: BED 1 - OBLIGATION | C32: RFOII | D32: Multi_commodity | E32: =VLOOKUP(Table37[[#This Row],[SPECIFIC COMMODITY]],TAGS!$W$48:$X$53,2,FALSE) -> Multi_commodity | F32: =VLOOKUP(Table37[[#This Row],[PREXC SUB-PROGRAM]],Table5[],2,FALSE) -> TECHNICAL AND SUPPORT SERVICES PROGRAM | G32: =VLOOKUP(Table37[[#This Row],[COMMODITY PREXC SUB-PROGRAM]],TAGS!$U$54:$V$76,2,FALSE) -> PSS | H32: Multicommodity_PSS | I32: =VLOOKUP(Table37[[#This Row],[PI LEVEL 3]],'PI LEVEL'!A:C,3,FALSE) -> Farm machinery and equipment procured for stations | J32: =VLOOKUP(Table37[[#This Row],[PI LEVEL 3]],Table53729[[Performance Indicator Level 3]:[Performance Indicator Level 1]],2,FALSE) -> Farm machinery and equipment procured for stations | K32: =VLOOKUP(Table37[[#This Row],[ACTIVITY]],TAGS!B:P,2,FALSE) -> Postharvest machinery and equipment procured for stations | L32: DA Stations - Corn Mill | M32: =VLOOKUP(Table37[[#This Row],[ACTIVITY]],TAGS!$B:$P,4,FALSE) -> DA Facilities Management | N32: =VLOOKUP(Table37[[#This Row],[ACTIVITY]],TAGS!$B:$P,5,FALSE) -> Support to DA Stations | O32: =VLOOKUP(Table37[[#This Row],[ACTIVITY]],TAGS!$B:$P,6,FALSE) -> Machinery & Equipment for DA Stations | P32: =VLOOKUP(Table37[[#This Row],[ACTIVITY]],TAGS!$B:$P,7,FALSE) -> NO | Q32: =VLOOKUP(Table37[[#This Row],[ACTIVITY]],TAGS!$B:$P,8,FALSE) -> PAP | R32: =VLOOKUP(Table37[[#This Row],[ACTIVITY]],TAGS!$B:$P,10,FALSE) -> PIP | S32: =VLOOKUP(Table37[[#This Row],[ACTIVITY]],TAGS!$B:$P,11,FALSE) -> PICS | T32: =VLOOKUP(Table37[[#This Row],[ACTIVITY]],TAGS!$B:$P,12,FALSE) -> Modernization | U32: =VLOOKUP(Table37[[#This Row],[ACTIVITY]],TAGS!$B:$P,13,FALSE) -> 8. Farm Mechanization and Farm Investments | V32: =VLOOKUP(Table37[[#This Row],[ACTIVITY]],TAGS!$B:$P,14,FALSE) -> 0 | W32: =VLOOKUP(Table37[[#This Row],[ACTIVITY]],TAGS!$B:$P,15,FALSE) -> DA Station | X32: =VLOOKUP(Table37[[#This Row],[PI LEVEL 3]],'PI LEVEL'!$A:$G,7,FALSE) -> DA-Level Output | Y32: NO | Z32: APRIL | AA32: =VLOOKUP(Table37[[#This Row],[MONTH]],TAGS!$W$67:$Y$81,2,FALSE) -> 2ND QTR | AB32: =VLOOKUP(Table37[[#This Row],[MONTH]],TAGS!$W$67:$Y$81,3,FALSE) -> 1ST SEMESTER | AC32: =VLOOKUP(Table37[[#This Row],[MONTH]],TAGS!$W$67:$Z$81,4,FALSE) -> 2025 | AE32: 1200 | AF32: =SUM(Table37[[#This Row],[MOOE (Php ''000)]:[CO (Php ''000)]]) -> 1200 | AG32: =ISBLANK(Table37[[#This Row],[PRPOPOSAL/BEDS]]) -> FALSE | AH32: =ISBLANK(Table37[[#This Row],[OU]]) -> FALSE | AI32: =ISBLANK(Table37[[#This Row],[SPECIFIC COMMODITY]]) -> FALSE | AJ32: =ISBLANK(Table37[[#This Row],[COMMODITY PREXC SUB-PROGRAM]]) -> FALSE | AK32: =ISBLANK(Table37[[#This Row],[ACTIVITY]]) -> FALSE | AL32: =ISBLANK(Table37[[#This Row],[TAG-GAD]]) -> FALSE | AM32: =ISBLANK(Table37[[#This Row],[MONTH]]) -> FALSE | AN32: =ISBLANK(Table37[[#This Row],[MOOE (Php ''000)]]) -> TRUE | AO32: =ISBLANK(Table37[[#This Row],[CO (Php ''000)]]) -> FALSE
A33: =VLOOKUP(Table37[[#This Row],[OU]],OU!$A$15:$B$34,2,FALSE) -> RFOs | B33: BED 1 - OBLIGATION | C33: RFOII | D33: Multi_commodity | E33: =VLOOKUP(Table37[[#This Row],[SPECIFIC COMMODITY]],TAGS!$W$48:$X$53,2,FALSE) -> Multi_commodity | F33: =VLOOKUP(Table37[[#This Row],[PREXC SUB-PROGRAM]],Table5[],2,FALSE) -> TECHNICAL AND SUPPORT SERVICES PROGRAM | G33: =VLOOKUP(Table37[[#This Row],[COMMODITY PREXC SUB-PROGRAM]],TAGS!$U$54:$V$76,2,FALSE) -> PSS | H33: Multicommodity_PSS | I33: =VLOOKUP(Table37[[#This Row],[PI LEVEL 3]],'PI LEVEL'!A:C,3,FALSE) -> Farm machinery and equipment procured for stations | J33: =VLOOKUP(Table37[[#This Row],[PI LEVEL 3]],Table53729[[Performance Indicator Level 3]:[Performance Indicator Level 1]],2,FALSE) -> Farm machinery and equipment procured for stations | K33: =VLOOKUP(Table37[[#This Row],[ACTIVITY]],TAGS!B:P,2,FALSE) -> Postharvest machinery and equipment procured for stations | L33: DA Stations - Pelletizing Machine | M33: =VLOOKUP(Table37[[#This Row],[ACTIVITY]],TAGS!$B:$P,4,FALSE) -> DA Facilities Management | N33: =VLOOKUP(Table37[[#This Row],[ACTIVITY]],TAGS!$B:$P,5,FALSE) -> Support to DA Stations | O33: =VLOOKUP(Table37[[#This Row],[ACTIVITY]],TAGS!$B:$P,6,FALSE) -> Machinery & Equipment for DA Stations | P33: =VLOOKUP(Table37[[#This Row],[ACTIVITY]],TAGS!$B:$P,7,FALSE) -> NO | Q33: =VLOOKUP(Table37[[#This Row],[ACTIVITY]],TAGS!$B:$P,8,FALSE) -> PAP | R33: =VLOOKUP(Table37[[#This Row],[ACTIVITY]],TAGS!$B:$P,10,FALSE) -> PIP | S33: =VLOOKUP(Table37[[#This Row],[ACTIVITY]],TAGS!$B:$P,11,FALSE) -> PICS | T33: =VLOOKUP(Table37[[#This Row],[ACTIVITY]],TAGS!$B:$P,12,FALSE) -> Modernization | U33: =VLOOKUP(Table37[[#This Row],[ACTIVITY]],TAGS!$B:$P,13,FALSE) -> 8. Farm Mechanization and Farm Investments | V33: =VLOOKUP(Table37[[#This Row],[ACTIVITY]],TAGS!$B:$P,14,FALSE) -> 0 | W33: =VLOOKUP(Table37[[#This Row],[ACTIVITY]],TAGS!$B:$P,15,FALSE) -> DA Station | X33: =VLOOKUP(Table37[[#This Row],[PI LEVEL 3]],'PI LEVEL'!$A:$G,7,FALSE) -> DA-Level Output | Y33: NO | Z33: APRIL | AA33: =VLOOKUP(Table37[[#This Row],[MONTH]],TAGS!$W$67:$Y$81,2,FALSE) -> 2ND QTR | AB33: =VLOOKUP(Table37[[#This Row],[MONTH]],TAGS!$W$67:$Y$81,3,FALSE) -> 1ST SEMESTER | AC33: =VLOOKUP(Table37[[#This Row],[MONTH]],TAGS!$W$67:$Z$81,4,FALSE) -> 2025 | AE33: 300 | AF33: =SUM(Table37[[#This Row],[MOOE (Php ''000)]:[CO (Php ''000)]]) -> 300 | AG33: =ISBLANK(Table37[[#This Row],[PRPOPOSAL/BEDS]]) -> FALSE | AH33: =ISBLANK(Table37[[#This Row],[OU]]) -> FALSE | AI33: =ISBLANK(Table37[[#This Row],[SPECIFIC COMMODITY]]) -> FALSE | AJ33: =ISBLANK(Table37[[#This Row],[COMMODITY PREXC SUB-PROGRAM]]) -> FALSE | AK33: =ISBLANK(Table37[[#This Row],[ACTIVITY]]) -> FALSE | AL33: =ISBLANK(Table37[[#This Row],[TAG-GAD]]) -> FALSE | AM33: =ISBLANK(Table37[[#This Row],[MONTH]]) -> FALSE | AN33: =ISBLANK(Table37[[#This Row],[MOOE (Php ''000)]]) -> TRUE | AO33: =ISBLANK(Table37[[#This Row],[CO (Php ''000)]]) -> FALSE
